Workbook

Sheet Início
B1: CONTROLE DE FERRAMENTAS E PATRIMÔNIO
B3: EICES Engenharia — Instalações, Consultoria e Soluções Energéticas
B6: Manual de uso — leia antes de operar a planilha. Este arquivo é o padrão oficial da EICES para controle de ferramentas.
B8: 1. PARA QUE SERVE
B9: Registrar TODA ferramenta própria da EICES, saber onde cada uma está hoje, o que quebrou, o que está em manutenção,
B10: quanto se gasta de locação por mês e o que precisa comprar. Substitui os controles antigos — a partir de agora, tudo aqui.
B12: 2. AS 6 ABAS
B13: PATRIMÔNIO — cadastro de cada ferramenta própria (1 linha por ferramenta). É a base de tudo.
B14: MOVIMENTAÇÃO — o "filme": cada vez que uma ferramenta muda de obra, quebra, some ou é baixada, registre 1 linha aqui.
B15: MANUTENÇÃO — ficha de cada conserto: onde quebrou, custo, quando entrou e voltou.
B16: LOCADO — ferramentas alugadas de terceiros (Ônix, Impacto, etc.). Controla o custo mensal de locação. Ao devolver, preencha a Data Devolução.
B17: RÁDIO — controle à parte, por obra: quantidade, custo, quebra/sumiço, de quem foi descontado e devolução ao encerrar a obra.
... B34: 5. LEGENDA DE CORES
C35: Valor estimado (sem nota fiscal)
C36: Coluna automática — não editar (travada)
C37: Cabeçalho
B39: 6. PADRÃO DE CÓDIGO DE PATRIMÔNIO (proposta — PREFIXO-NN)
B40: Formato: 3 letras da categoria + hífen + número de 2 dígitos. Ex.: PAR-01 (parafusadeira 1), PEZ-02 (perfuratriz 2).
B41: Tabela de prefixos por categoria:
B42: PAR | C42: PARAFUSADEIRA | D42: FUR | E42: FURADEIRA | F42: ROM | G42: ROMPEDOR
B43: ESM | C43: ESMERILHADEIRA | D43: SMA | E43: SERRA MÁRMORE | F43: SES | G43: SERRA DE ESQUADRIA
B44: MT5 | C44: MARTELETE 5KG | D44: M10 | E44: MARTELETE 10KG | F44: LAS | G44: LASER
B45: TLA | C45: TRIPÉ LASER | D45: PEZ | E45: PERFURATRIZ | F45: PEX | G45: PERFURATRIZ EXTRATORA
B46: MOR | C46: MORSA | D46: TER | E46: TERMOFUSOR | F46: SOP | G46: SOPRADOR
B47: VAZ | C47: VAZADOR | D47: PFP | E47: PISTOLA FINCA PINO | F47: MTA | G47: MÁQUINA TESTE ÁGUA
B48: MTE | C48: MÁQUINA TESTE ELÉTRICA | D48: COM | E48: COMPRESSOR | F48: PPE | G48: PRENSA PEX
B49: PTE | C49: PRENSA TERMINAL | D49: PGA | E49: PRENSA GÁS | F49: MTI | G49: MÁQUINA DE TINTA
B50: MAN | C50: MANÔMETRO | D50: TCF | E50: TESOURA CORTA FERRO
B53: Código locado usa o código da própria locadora (quando vier na ferramenta). Rádio não usa código individual.

Sheet Patrimônio
B1: PATRIMÔNIO — FERRAMENTAS PRÓPRIAS EICES
B3: Cadastro-base. Preencha as colunas brancas. Cinza = automático.
A6: Código | B6: Categoria | C6: Item / Descrição | D6: Marca | E6: Modelo | F6: Nº de Série | G6: Valor (R$) | H6: Estimado? (S/N) | I6: Nota Fiscal | J6: Obra Atual | K6: Responsável | L6: Status | M6: Observação | N6: Locação EICES / mês (R$)
A7: PAR-01 | B7: PARAFUSADEIRA | C7: Parafusadeira | D7: BOSCH | E7: GSR 185 -LI | F7: 330 43 0275 | G7: 697.9 | H7: N | I7: 941194 | J7: {=IF($A7="","",IFERROR(_xlfn.XLOOKUP($A7,'Movimentação'!$B$7:$B$1006,'Movimentação'!$E$7:$E$1006,"",0,-1),""))} -> ESCRITÓRIO | K7: {=IF($A7="","",IFERROR(_xlfn.XLOOKUP($A7,'Movimentação'!$B$7:$B$1006,'Movimentação'!$G$7:$G$1006,"",0,-1),""))} -> LAÉRCIO | L7: =IF($A7="","",IF($Q7=1,"MANUTENÇÃO",IF($P7="BAIXA","BAIXADO",IF($P7="FURTO","FURTADO",IF($J7<>"","EM OBRA","PENDENTE-PROCURAR"))))) -> EM OBRA | N7: {=IF($A7="","",IFERROR(IF(OR($L7="BAIXADO",$L7="FURTADO"),0,INDEX(Listas!$J$2:$J$40,MATCH($B7,Listas!$I$2:$I$40,0))),""))} -> 200 | P7: {=IF($A7="","",IFERROR(_xlfn.XLOOKUP($A7,'Movimentação'!$B$7:$B$1006,'Movimentação'!$F$7:$F$1006,"",0,-1),""))} -> TRANSFERÊNCIA | Q7: =IF(COUNTIFS('Manutenção'!$B$7:$B$1006,$A7,'Manutenção'!$H$7:$H$1006,"EM CONSERTO")>0,1,0) -> 0
A8: PAR-02 | B8: PARAFUSADEIRA | C8: Parafusadeira | D8: BOSCH | E8: GSR 185 -LI | F8: 330 43 0280 | G8: 697.9 | H8: N | I8: 941194 | J8: {=IF($A8="","",IFERROR(_xlfn.XLOOKUP($A8,'Movimentação'!$B$7:$B$1006,'Movimentação'!$E$7:$E$1006,"",0,-1),""))} -> ARENGA (TRISUL) | K8: {=IF($A8="","",IFERROR(_xlfn.XLOOKUP($A8,'Movimentação'!$B$7:$B$1006,'Movimentação'!$G$7:$G$1006,"",0,-1),""))} -> LUCIENY | L8: =IF($A8="","",IF($Q8=1,"MANUTENÇÃO",IF($P8="BAIXA","BAIXADO",IF($P8="FURTO","FURTADO",IF($J8<>"","EM OBRA","PENDENTE-PROCURAR"))))) -> EM OBRA | N8: {=IF($A8="","",IFERROR(IF(OR($L8="BAIXADO",$L8="FURTADO"),0,INDEX(Listas!$J$2:$J$40,MATCH($B8,Listas!$I$2:$I$40,0))),""))} -> 200 | P8: {=IF($A8="","",IFERROR(_xlfn.XLOOKUP($A8,'Movimentação'!$B$7:$B$1006,'Movimentação'!$F$7:$F$1006,"",0,-1),""))} -> TRANSFERÊNCIA | Q8: =IF(COUNTIFS('Manutenção'!$B$7:$B$1006,$A8,'Manutenção'!$H$7:$H$1006,"EM CONSERTO")>0,1,0) -> 0
A9: PAR-03 | B9: PARAFUSADEIRA | C9: Parafusadeira | D9: BOSCH | E9: GSR 185 -LI | F9: 330 43 0274 | G9: 697.9 | H9: N | I9: 941194 | J9: {=IF($A9="","",IFERROR(_xlfn.XLOOKUP($A9,'Movimentação'!$B$7:$B$1006,'Movimentação'!$E$7:$E$1006,"",0,-1),""))} -> ALPHA ONE | K9: {=IF($A9="","",IFERROR(_xlfn.XLOOKUP($A9,'Movimentação'!$B$7:$B$1006,'Movimentação'!$G$7:$G$1006,"",0,-1),""))} -> EICES | L9: =IF($A9="","",IF($Q9=1,"MANUTENÇÃO",IF($P9="BAIXA","BAIXADO",IF($P9="FURTO","FURTADO",IF($J9<>"","EM OBRA","PENDENTE-PROCURAR"))))) -> FURTADO | N9: {=IF($A9="","",IFERROR(IF(OR($L9="BAIXADO",$L9="FURTADO"),0,INDEX(Listas!$J$2:$J$40,MATCH($B9,Listas!$I$2:$I$40,0))),""))} -> 0 | P9: {=IF($A9="","",IFERROR(_xlfn.XLOOKUP($A9,'Movimentação'!$B$7:$B$1006,'Movimentação'!$F$7:$F$1006,"",0,-1),""))} -> FURTO | Q9: =IF(COUNTIFS('Manutenção'!$B$7:$B$1006,$A9,'Manutenção'!$H$7:$H$1006,"EM CONSERTO")>0,1,0) -> 0
A10: PAR-04 | B10: PARAFUSADEIRA | C10: Parafusadeira | D10: BOSCH | E10: GSR 185 -LI | F10: 330 43 0279 | G10: 697.9 | H10: N | I10: 941194 | J10: {=IF($A10="","",IFERROR(_xlfn.XLOOKUP($A10,'Movimentação'!$B$7:$B$1006,'Movimentação'!$E$7:$E$1006,"",0,-1),""))} -> ALPHA ONE | K10: {=IF($A10="","",IFERROR(_xlfn.XLOOKUP($A10,'Movimentação'!$B$7:$B$1006,'Movimentação'!$G$7:$G$1006,"",0,-1),""))} -> EICES | L10: =IF($A10="","",IF($Q10=1,"MANUTENÇÃO",IF($P10="BAIXA","BAIXADO",IF($P10="FURTO","FURTADO",IF($J10<>"","EM OBRA","PENDENTE-PROCURAR"))))) -> BAIXADO | N10: {=IF($A10="","",IFERROR(IF(OR($L10="BAIXADO",$L10="FURTADO"),0,INDEX(Listas!$J$2:$J$40,MATCH($B10,Listas!$I$2:$I$40,0))),""))} -> 0 | P10: {=IF($A10="","",IFERROR(_xlfn.XLOOKUP($A10,'Movimentação'!$B$7:$B$1006,'Movimentação'!$F$7:$F$1006,"",0,-1),""))} -> BAIXA | Q10: =IF(COUNTIFS('Manutenção'!$B$7:$B$1006,$A10,'Manutenção'!$H$7:$H$1006,"EM CONSERTO")>0,1,0) -> 0
A11: PAR-05 | B11: PARAFUSADEIRA | C11: Parafusadeira | D11: BOSCH | E11: GSR 185 -LI | F11: 330 43 0273 | G11: 697.9 | H11: N | I11: 941194 | J11: {=IF($A11="","",IFERROR(_xlfn.XLOOKUP($A11,'Movimentação'!$B$7:$B$1006,'Movimentação'!$E$7:$E$1006,"",0,-1),""))} -> ASSISTENCIA TECNICA | K11: {=IF($A11="","",IFERROR(_xlfn.XLOOKUP($A11,'Movimentação'!$B$7:$B$1006,'Movimentação'!$G$7:$G$1006,"",0,-1),""))} -> EICES | L11: =IF($A11="","",IF($Q11=1,"MANUTENÇÃO",IF($P11="BAIXA","BAIXADO",IF($P11="FURTO","FURTADO",IF($J11<>"","EM OBRA","PENDENTE-PROCURAR"))))) -> BAIXADO | N11: {=IF($A11="","",IFERROR(IF(OR($L11="BAIXADO",$L11="FURTADO"),0,INDEX(Listas!$J$2:$J$40,MATCH($B11,Listas!$I$2:$I$40,0))),""))} -> 0 | P11: {=IF($A11="","",IFERROR(_xlfn.XLOOKUP($A11,'Movimentação'!$B$7:$B$1006,'Movimentação'!$F$7:$F$1006,"",0,-1),""))} -> BAIXA | Q11: =IF(COUNTIFS('Manutenção'!$B$7:$B$1006,$A11,'Manutenção'!$H$7:$H$1006,"EM CONSERTO")>0,1,0) -> 0
A12: PAR-5 | B12: PARAFUSADEIRA | C12: Parafusadeira | G12: 697.9 | H12: S | J12: {=IF($A12="","",IFERROR(_xlfn.XLOOKUP($A12,'Movimentação'!$B$7:$B$1006,'Movimentação'!$E$7:$E$1006,"",0,-1),""))} -> ASSISTENCIA TECNICA | K12: {=IF($A12="","",IFERROR(_xlfn.XLOOKUP($A12,'Movimentação'!$B$7:$B$1006,'Movimentação'!$G$7:$G$1006,"",0,-1),""))} -> EICES | L12: =IF($A12="","",IF($Q12=1,"MANUTENÇÃO",IF($P12="BAIXA","BAIXADO",IF($P12="FURTO","FURTADO",IF($J12<>"","EM OBRA","PENDENTE-PROCURAR"))))) -> BAIXADO | N12: {=IF($A12="","",IFERROR(IF(OR($L12="BAIXADO",$L12="FURTADO"),0,INDEX(Listas!$J$2:$J$40,MATCH($B12,Listas!$I$2:$I$40,0))),""))} -> 0 | P12: {=IF($A12="","",IFERROR(_xlfn.XLOOKUP($A12,'Movimentação'!$B$7:$B$1006,'Movimentação'!$F$7:$F$1006,"",0,-1),""))} -> BAIXA | Q12: =IF(COUNTIFS('Manutenção'!$B$7:$B$1006,$A12,'Manutenção'!$H$7:$H$1006,"EM CONSERTO")>0,1,0) -> 0
A13: PAR-06 | B13: PARAFUSADEIRA | C13: Parafusadeira | D13: BOSCH | E13: GSR 185 -LI | F13: 330 43 0281 | G13: 697.9 | H13: N | I13: 941194 | J13: {=IF($A13="","",IFERROR(_xlfn.XLOOKUP($A13,'Movimentação'!$B$7:$B$1006,'Movimentação'!$E$7:$E$1006,"",0,-1),""))} -> ASSISTENCIA TECNICA | K13: {=IF($A13="","",IFERROR(_xlfn.XLOOKUP($A13,'Movimentação'!$B$7:$B$1006,'Movimentação'!$G$7:$G$1006,"",0,-1),""))} -> EICES | L13: =IF($A13="","",IF($Q13=1,"MANUTENÇÃO",IF($P13="BAIXA","BAIXADO",IF($P13="FURTO","FURTADO",IF($J13<>"","EM OBRA","PENDENTE-PROCURAR"))))) -> BAIXADO | M13: em uso | N13: {=IF($A13="","",IFERROR(IF(OR($L13="BAIXADO",$L13="FURTADO"),0,INDEX(Listas!$J$2:$J$40,MATCH($B13,Listas!$I$2:$I$40,0))),""))} -> 0 | P13: {=IF($A13="","",IFERROR(_xlfn.XLOOKUP($A13,'Movimentação'!$B$7:$B$1006,'Movimentação'!$F$7:$F$1006,"",0,-1),""))} -> BAIXA | Q13: =IF(COUNTIFS('Manutenção'!$B$7:$B$1006,$A13,'Manutenção'!$H$7:$H$1006,"EM CONSERTO")>0,1,0) -> 0
A14: PAR-07 | B14: PARAFUSADEIRA | C14: Parafusadeira | D14: BOSCH | E14: 3601JF3EQ | F14: 3601JF3EQ (EICES-2) | G14: 697.9 | H14: S | I14: 1276 | J14: {=IF($A14="","",IFERROR(_xlfn.XLOOKUP($A14,'Movimentação'!$B$7:$B$1006,'Movimentação'!$E$7:$E$1006,"",0,-1),""))} -> TANABI | K14: {=IF($A14="","",IFERROR(_xlfn.XLOOKUP($A14,'Movimentação'!$B$7:$B$1006,'Movimentação'!$G$7:$G$1006,"",0,-1),""))} -> EICES | L14: =IF($A14="","",IF($Q14=1,"MANUTENÇÃO",IF($P14="BAIXA","BAIXADO",IF($P14="FURTO","FURTADO",IF($J14<>"","EM OBRA","PENDENTE-PROCURAR"))))) -> EM OBRA | N14: {=IF($A14="","",IFERROR(IF(OR($L14="BAIXADO",$L14="FURTADO"),0,INDEX(Listas!$J$2:$J$40,MATCH($B14,Listas!$I$2:$I$40,0))),""))} -> 200 | P14: {=IF($A14="","",IFERROR(_xlfn.XLOOKUP($A14,'Movimentação'!$B$7:$B$1006,'Movimentação'!$F$7:$F$1006,"",0,-1),""))} -> ENTRADA (NOVA) | Q14: =IF(COUNTIFS('Manutenção'!$B$7:$B$1006,$A14,'Manutenção'!$H$7:$H$1006,"EM CONSERTO")>0,1,0) -> 0
A15: PAR-08 | B15: PARAFUSADEIRA | C15: Parafusadeira | D15: BOSCH | E15: 3601JF3EQ | F15: 3601JF83E0 (EICES-1) | G15: 697.9 | H15: S | I15: 1276 | J15: {=IF($A15="","",IFERROR(_xlfn.XLOOKUP($A15,'Movimentação'!$B$7:$B$1006,'Movimentação'!$E$7:$E$1006,"",0,-1),""))} | K15: {=IF($A15="","",IFERROR(_xlfn.XLOOKUP($A15,'Movimentação'!$B$7:$B$1006,'Movimentação'!$G$7:$G$1006,"",0,-1),""))} | L15: =IF($A15="","",IF($Q15=1,"MANUTENÇÃO",IF($P15="BAIXA","BAIXADO",IF($P15="FURTO","FURTADO",IF($J15<>"","EM OBRA","PENDENTE-PROCURAR"))))) -> PENDENTE-PROCURAR | N15: {=IF($A15="","",IFERROR(IF(OR($L15="BAIXADO",$L15="FURTADO"),0,INDEX(Listas!$J$2:$J$40,MATCH($B15,Listas!$I$2:$I$40,0))),""))} -> 200 | P15: {=IF($A15="","",IFERROR(_xlfn.XLOOKUP($A15,'Movimentação'!$B$7:$B$1006,'Movimentação'!$F$7:$F$1006,"",0,-1),""))} | Q15: =IF(COUNTIFS('Manutenção'!$B$7:$B$1006,$A15,'Manutenção'!$H$7:$H$1006,"EM CONSERTO")>0,1,0) -> 0
A16: PAR-09 | B16: PARAFUSADEIRA | C16: Parafusadeira | D16: DEWALT | E16: DCD716 | F16: 2358 | G16: 779.01 | H16: N | I16: 1051559 | J16: {=IF($A16="","",IFERROR(_xlfn.XLOOKUP($A16,'Movimentação'!$B$7:$B$1006,'Movimentação'!$E$7:$E$1006,"",0,-1),""))} -> ASSISTENCIA TECNICA | K16: {=IF($A16="","",IFERROR(_xlfn.XLOOKUP($A16,'Movimentação'!$B$7:$B$1006,'Movimentação'!$G$7:$G$1006,"",0,-1),""))} -> EICES | L16: =IF($A16="","",IF($Q16=1,"MANUTENÇÃO",IF($P16="BAIXA","BAIXADO",IF($P16="FURTO","FURTADO",IF($J16<>"","EM OBRA","PENDENTE-PROCURAR"))))) -> BAIXADO | M16: sem carregador | N16: {=IF($A16="","",IFERROR(IF(OR($L16="BAIXADO",$L16="FURTADO"),0,INDEX(Listas!$J$2:$J$40,MATCH($B16,Listas!$I$2:$I$40,0))),""))} -> 0 | P16: {=IF($A16="","",IFERROR(_xlfn.XLOOKUP($A16,'Movimentação'!$B$7:$B$1006,'Movimentação'!$F$7:$F$1006,"",0,-1),""))} -> BAIXA | Q16: =IF(COUNTIFS('Manutenção'!$B$7:$B$1006,$A16,'Manutenção'!$H$7:$H$1006,"EM CONSERTO")>0,1,0) -> 0
A17: PAR-10 | B17: PARAFUSADEIRA | C17: Parafusadeira | D17: BOSCH | E17: GSB 180-LI | F17: 226200053 | G17: 806.67 | H17: N | J17: {=IF($A17="","",IFERROR(_xlfn.XLOOKUP($A17,'Movimentação'!$B$7:$B$1006,'Movimentação'!$E$7:$E$1006,"",0,-1),""))} | K17: {=IF($A17="","",IFERROR(_xlfn.XLOOKUP($A17,'Movimentação'!$B$7:$B$1006,'Movimentação'!$G$7:$G$1006,"",0,-1),""))} | L17: =IF($A17="","",IF($Q17=1,"MANUTENÇÃO",IF($P17="BAIXA","BAIXADO",IF($P17="FURTO","FURTADO",IF($J17<>"","EM OBRA","PENDENTE-PROCURAR"))))) -> PENDENTE-PROCURAR | N17: {=IF($A17="","",IFERROR(IF(OR($L17="BAIXADO",$L17="FURTADO"),0,INDEX(Listas!$J$2:$J$40,MATCH($B17,Listas!$I$2:$I$40,0))),""))} -> 200 | P17: {=IF($A17="","",IFERROR(_xlfn.XLOOKUP($A17,'Movimentação'!$B$7:$B$1006,'Movimentação'!$F$7:$F$1006,"",0,-1),""))} | Q17: =IF(COUNTIFS('Manutenção'!$B$7:$B$1006,$A17,'Manutenção'!$H$7:$H$1006,"EM CONSERTO")>0,1,0) -> 0
A18: PAR-11 | B18: PARAFUSADEIRA | C18: Parafusadeira | D18: NEWBEAT | E18: BRUSHLESS | F18: EW SI 0031 | G18: 697.9 | H18: S | J18: {=IF($A18="","",IFERROR(_xlfn.XLOOKUP($A18,'Movimentação'!$B$7:$B$1006,'Movimentação'!$E$7:$E$1006,"",0,-1),""))} -> MAURO | K18: {=IF($A18="","",IFERROR(_xlfn.XLOOKUP($A18,'Movimentação'!$B$7:$B$1006,'Movimentação'!$G$7:$G$1006,"",0,-1),""))} -> EICES | L18: =IF($A18="","",IF($Q18=1,"MANUTENÇÃO",IF($P18="BAIXA","BAIXADO",IF($P18="FURTO","FURTADO",IF($J18<>"","EM OBRA","PENDENTE-PROCURAR"))))) -> EM OBRA | N18: {=IF($A18="","",IFERROR(IF(OR($L18="BAIXADO",$L18="FURTADO"),0,INDEX(Listas!$J$2:$J$40,MATCH($B18,Listas!$I$2:$I$40,0))),""))} -> 200 | P18: {=IF($A18="","",IFERROR(_xlfn.XLOOKUP($A18,'Movimentação'!$B$7:$B$1006,'Movimentação'!$F$7:$F$1006,"",0,-1),""))} -> ENTRADA (NOVA) | Q18: =IF(COUNTIFS('Manutenção'!$B$7:$B$1006,$A18,'Manutenção'!$H$7:$H$1006,"EM CONSERTO")>0,1,0) -> 0
A19: PAR-12 | B19: PARAFUSADEIRA | C19: Parafusadeira | D19: NEWBEAT | E19: BRUSHLESS | F19: EW SI 0056 | G19: 697.9 | H19: S | J19: {=IF($A19="","",IFERROR(_xlfn.XLOOKUP($A19,'Movimentação'!$B$7:$B$1006,'Movimentação'!$E$7:$E$1006,"",0,-1),""))} -> ASSISTENCIA TECNICA | K19: {=IF($A19="","",IFERROR(_xlfn.XLOOKUP($A19,'Movimentação'!$B$7:$B$1006,'Movimentação'!$G$7:$G$1006,"",0,-1),""))} -> EICES | L19: =IF($A19="","",IF($Q19=1,"MANUTENÇÃO",IF($P19="BAIXA","BAIXADO",IF($P19="FURTO","FURTADO",IF($J19<>"","EM OBRA","PENDENTE-PROCURAR"))))) -> BAIXADO | N19: {=IF($A19="","",IFERROR(IF(OR($L19="BAIXADO",$L19="FURTADO"),0,INDEX(Listas!$J$2:$J$40,MATCH($B19,Listas!$I$2:$I$40,0))),""))} -> 0 | P19: {=IF($A19="","",IFERROR(_xlfn.XLOOKUP($A19,'Movimentação'!$B$7:$B$1006,'Movimentação'!$F$7:$F$1006,"",0,-1),""))} -> BAIXA | Q19: =IF(COUNTIFS('Manutenção'!$B$7:$B$1006,$A19,'Manutenção'!$H$7:$H$1006,"EM CONSERTO")>0,1,0) -> 0
A20: PAR-13 | B20: PARAFUSADEIRA | C20: Parafusadeira | D20: NEWBEAT | E20: BRUSHLESS | F20: EW SI 0057 | G20: 697.9 | H20: S | J20: {=IF($A20="","",IFERROR(_xlfn.XLOOKUP($A20,'Movimentação'!$B$7:$B$1006,'Movimentação'!$E$7:$E$1006,"",0,-1),""))} -> BALTAZAR | K20: {=IF($A20="","",IFERROR(_xlfn.XLOOKUP($A20,'Movimentação'!$B$7:$B$1006,'Movimentação'!$G$7:$G$1006,"",0,-1),""))} -> MARCIO | L20: =IF($A20="","",IF($Q20=1,"MANUTENÇÃO",IF($P20="BAIXA","BAIXADO",IF($P20="FURTO","FURTADO",IF($J20<>"","EM OBRA","PENDENTE-PROCURAR"))))) -> FURTADO | M20: em uso | N20: {=IF($A20="","",IFERROR(IF(OR($L20="BAIXADO",$L20="FURTADO"),0,INDEX(Listas!$J$2:$J$40,MATCH($B20,Listas!$I$2:$I$40,0))),""))} -> 0 | P20: {=IF($A20="","",IFERROR(_xlfn.XLOOKUP($A20,'Movimentação'!$B$7:$B$1006,'Movimentação'!$F$7:$F$1006,"",0,-1),""))} -> FURTO | Q20: =IF(COUNTIFS('Manutenção'!$B$7:$B$1006,$A20,'Manutenção'!$H$7:$H$1006,"EM CONSERTO")>0,1,0) -> 0
A21: PAR-14 | B21: PARAFUSADEIRA | C21: Parafusadeira | D21: NEWBEAT | E21: BRUSHLESS | F21: EW SI 0035 | G21: 697.9 | H21: S | J21: {=IF($A21="","",IFERROR(_xlfn.XLOOKUP($A21,'Movimentação'!$B$7:$B$1006,'Movimentação'!$E$7:$E$1006,"",0,-1),""))} -> JOA | K21: {=IF($A21="","",IFERROR(_xlfn.XLOOKUP($A21,'Movimentação'!$B$7:$B$1006,'Movimentação'!$G$7:$G$1006,"",0,-1),""))} -> GABRIEL | L21: =IF($A21="","",IF($Q21=1,"MANUTENÇÃO",IF($P21="BAIXA","BAIXADO",IF($P21="FURTO","FURTADO",IF($J21<>"","EM OBRA","PENDENTE-PROCURAR"))))) -> EM OBRA | N21: {=IF($A21="","",IFERROR(IF(OR($L21="BAIXADO",$L21="FURTADO"),0,INDEX(Listas!$J$2:$J$40,MATCH($B21,Listas!$I$2:$I$40,0))),""))} -> 200 | P21: {=IF($A21="","",IFERROR(_xlfn.XLOOKUP($A21,'Movimentação'!$B$7:$B$1006,'Movimentação'!$F$7:$F$1006,"",0,-1),""))} -> TRANSFERÊNCIA | Q21: =IF(COUNTIFS('Manutenção'!$B$7:$B$1006,$A21,'Manutenção'!$H$7:$H$1006,"EM CONSERTO")>0,1,0) -> 0
A22: PAR-15 | B22: PARAFUSADEIRA | C22: Parafusadeira | D22: NEWBEAT | E22: BRUSHLESS | F22: EW SI 0023 | G22: 697.9 | H22: S | J22: {=IF($A22="","",IFERROR(_xlfn.XLOOKUP($A22,'Movimentação'!$B$7:$B$1006,'Movimentação'!$E$7:$E$1006,"",0,-1),""))} -> ASSISTENCIA TECNICA | K22: {=IF($A22="","",IFERROR(_xlfn.XLOOKUP($A22,'Movimentação'!$B$7:$B$1006,'Movimentação'!$G$7:$G$1006,"",0,-1),""))} -> EICES | L22: =IF($A22="","",IF($Q22=1,"MANUTENÇÃO",IF($P22="BAIXA","BAIXADO",IF($P22="FURTO","FURTADO",IF($J22<>"","EM OBRA","PENDENTE-PROCURAR"))))) -> BAIXADO | N22: {=IF($A22="","",IFERROR(IF(OR($L22="BAIXADO",$L22="FURTADO"),0,INDEX(Listas!$J$2:$J$40,MATCH($B22,Listas!$I$2:$I$40,0))),""))} -> 0 | P22: {=IF($A22="","",IFERROR(_xlfn.XLOOKUP($A22,'Movimentação'!$B$7:$B$1006,'Movimentação'!$F$7:$F$1006,"",0,-1),""))} -> BAIXA | Q22: =IF(COUNTIFS('Manutenção'!$B$7:$B$1006,$A22,'Manutenção'!$H$7:$H$1006,"EM CONSERTO")>0,1,0) -> 0
A23: PAR-16 | B23: PARAFUSADEIRA | C23: Parafusadeira | D23: NEWBEAT | E23: BRUSHLESS | G23: 697.9 | H23: S | J23: {=IF($A23="","",IFERROR(_xlfn.XLOOKUP($A23,'Movimentação'!$B$7:$B$1006,'Movimentação'!$E$7:$E$1006,"",0,-1),""))} | K23: {=IF($A23="","",IFERROR(_xlfn.XLOOKUP($A23,'Movimentação'!$B$7:$B$1006,'Movimentação'!$G$7:$G$1006,"",0,-1),""))} | L23: =IF($A23="","",IF($Q23=1,"MANUTENÇÃO",IF($P23="BAIXA","BAIXADO",IF($P23="FURTO","FURTADO",IF($J23<>"","EM OBRA","PENDENTE-PROCURAR"))))) -> PENDENTE-PROCURAR | N23: {=IF($A23="","",IFERROR(IF(OR($L23="BAIXADO",$L23="FURTADO"),0,INDEX(Listas!$J$2:$J$40,MATCH($B23,Listas!$I$2:$I$40,0))),""))} -> 200 | P23: {=IF($A23="","",IFERROR(_xlfn.XLOOKUP($A23,'Movimentação'!$B$7:$B$1006,'Movimentação'!$F$7:$F$1006,"",0,-1),""))} | Q23: =IF(COUNTIFS('Manutenção'!$B$7:$B$1006,$A23,'Manutenção'!$H$7:$H$1006,"EM CONSERTO")>0,1,0) -> 0
A24: PAR-17 | B24: PARAFUSADEIRA | C24: Parafusadeira | D24: ARITA | E24: AR-M1370PRO | F24: DR130A01667 | G24: 697.9 | H24: S | J24: {=IF($A24="","",IFERROR(_xlfn.XLOOKUP($A24,'Movimentação'!$B$7:$B$1006,'Movimentação'!$E$7:$E$1006,"",0,-1),""))} -> PJM | K24: {=IF($A24="","",IFERROR(_xlfn.XLOOKUP($A24,'Movimentação'!$B$7:$B$1006,'Movimentação'!$G$7:$G$1006,"",0,-1),""))} -> EICES | L24: =IF($A24="","",IF($Q24=1,"MANUTENÇÃO",IF($P24="BAIXA","BAIXADO",IF($P24="FURTO","FURTADO",IF($J24<>"","EM OBRA","PENDENTE-PROCURAR"))))) -> EM OBRA | N24: {=IF($A24="","",IFERROR(IF(OR($L24="BAIXADO",$L24="FURTADO"),0,INDEX(Listas!$J$2:$J$40,MATCH($B24,Listas!$I$2:$I$40,0))),""))} -> 200 | P24: {=IF($A24="","",IFERROR(_xlfn.XLOOKUP($A24,'Movimentação'!$B$7:$B$1006,'Movimentação'!$F$7:$F$1006,"",0,-1),""))} -> ENTRADA (NOVA) | Q24: =IF(COUNTIFS('Manutenção'!$B$7:$B$1006,$A24,'Manutenção'!$H$7:$H$1006,"EM CONSERTO")>0,1,0) -> 0
A25: PAR-18 | B25: PARAFUSADEIRA | C25: Parafusadeira | D25: ARITA | E25: AR-M1370PRO | F25: DR13A001666 | G25: 697.9 | H25: S | J25: {=IF($A25="","",IFERROR(_xlfn.XLOOKUP($A25,'Movimentação'!$B$7:$B$1006,'Movimentação'!$E$7:$E$1006,"",0,-1),""))} -> ANGELICA | K25: THIAGO | L25: =IF($A25="","",IF($Q25=1,"MANUTENÇÃO",IF($P25="BAIXA","BAIXADO",IF($P25="FURTO","FURTADO",IF($J25<>"","EM OBRA","PENDENTE-PROCURAR"))))) -> EM OBRA | N25: {=IF($A25="","",IFERROR(IF(OR($L25="BAIXADO",$L25="FURTADO"),0,INDEX(Listas!$J$2:$J$40,MATCH($B25,Listas!$I$2:$I$40,0))),""))} -> 200 | P25: {=IF($A25="","",IFERROR(_xlfn.XLOOKUP($A25,'Movimentação'!$B$7:$B$1006,'Movimentação'!$F$7:$F$1006,"",0,-1),""))} -> RETORNO MANUTENÇÃO | Q25: =IF(COUNTIFS('Manutenção'!$B$7:$B$1006,$A25,'Manutenção'!$H$7:$H$1006,"EM CONSERTO")>0,1,0) -> 0
A26: PAR-19 | B26: PARAFUSADEIRA | C26: Parafusadeira | D26: ARITA | E26: AR-M1370PRO | F26: DR13A001599 | G26: 697.9 | H26: S | J26: {=IF($A26="","",IFERROR(_xlfn.XLOOKUP($A26,'Movimentação'!$B$7:$B$1006,'Movimentação'!$E$7:$E$1006,"",0,-1),""))} -> ORIÇANGA | K26: {=IF($A26="","",IFERROR(_xlfn.XLOOKUP($A26,'Movimentação'!$B$7:$B$1006,'Movimentação'!$G$7:$G$1006,"",0,-1),""))} -> EICES | L26: =IF($A26="","",IF($Q26=1,"MANUTENÇÃO",IF($P26="BAIXA","BAIXADO",IF($P26="FURTO","FURTADO",IF($J26<>"","EM OBRA","PENDENTE-PROCURAR"))))) -> EM OBRA | N26: {=IF($A26="","",IFERROR(IF(OR($L26="BAIXADO",$L26="FURTADO"),0,INDEX(Listas!$J$2:$J$40,MATCH($B26,Listas!$I$2:$I$40,0))),""))} -> 200 | P26: {=IF($A26="","",IFERROR(_xlfn.XLOOKUP($A26,'Movimentação'!$B$7:$B$1006,'Movimentação'!$F$7:$F$1006,"",0,-1),""))} -> ENTRADA (NOVA) | Q26: =IF(COUNTIFS('Manutenção'!$B$7:$B$1006,$A26,'Manutenção'!$H$7:$H$1006,"EM CONSERTO")>0,1,0) -> 0
A27: PAR-20 | B27: PARAFUSADEIRA | C27: Parafusadeira | D27: ARITA | E27: AR-M1370PRO | F27: DR13A001600 | G27: 697.9 | H27: S | J27: {=IF($A27="","",IFERROR(_xlfn.XLOOKUP($A27,'Movimentação'!$B$7:$B$1006,'Movimentação'!$E$7:$E$1006,"",0,-1),""))} -> SAMPA CONSOLAÇÃO | K27: {=IF($A27="","",IFERROR(_xlfn.XLOOKUP($A27,'Movimentação'!$B$7:$B$1006,'Movimentação'!$G$7:$G$1006,"",0,-1),""))} -> EICES | L27: =IF($A27="","",IF($Q27=1,"MANUTENÇÃO",IF($P27="BAIXA","BAIXADO",IF($P27="FURTO","FURTADO",IF($J27<>"","EM OBRA","PENDENTE-PROCURAR"))))) -> EM OBRA | N27: {=IF($A27="","",IFERROR(IF(OR($L27="BAIXADO",$L27="FURTADO"),0,INDEX(Listas!$J$2:$J$40,MATCH($B27,Listas!$I$2:$I$40,0))),""))} -> 200 | P27: {=IF($A27="","",IFERROR(_xlfn.XLOOKUP($A27,'Movimentação'!$B$7:$B$1006,'Movimentação'!$F$7:$F$1006,"",0,-1),""))} -> ENTRADA (NOVA) | Q27: =IF(COUNTIFS('Manutenção'!$B$7:$B$1006,$A27,'Manutenção'!$H$7:$H$1006,"EM CONSERTO")>0,1,0) -> 0
A28: PAR-21 | B28: PARAFUSADEIRA | C28: Parafusadeira | D28: ARITA | E28: AR-M1370PRO | F28: DR13A001823 | G28: 697.9 | H28: S | J28: {=IF($A28="","",IFERROR(_xlfn.XLOOKUP($A28,'Movimentação'!$B$7:$B$1006,'Movimentação'!$E$7:$E$1006,"",0,-1),""))} -> PJM | K28: {=IF($A28="","",IFERROR(_xlfn.XLOOKUP($A28,'Movimentação'!$B$7:$B$1006,'Movimentação'!$G$7:$G$1006,"",0,-1),""))} -> EICES | L28: =IF($A28="","",IF($Q28=1,"MANUTENÇÃO",IF($P28="BAIXA","BAIXADO",IF($P28="FURTO","FURTADO",IF($J28<>"","EM OBRA","PENDENTE-PROCURAR"))))) -> EM OBRA | N28: {=IF($A28="","",IFERROR(IF(OR($L28="BAIXADO",$L28="FURTADO"),0,INDEX(Listas!$J$2:$J$40,MATCH($B28,Listas!$I$2:$I$40,0))),""))} -> 200 | P28: {=IF($A28="","",IFERROR(_xlfn.XLOOKUP($A28,'Movimentação'!$B$7:$B$1006,'Movimentação'!$F$7:$F$1006,"",0,-1),""))} -> ENTRADA (NOVA) | Q28: =IF(COUNTIFS('Manutenção'!$B$7:$B$1006,$A28,'Manutenção'!$H$7:$H$1006,"EM CONSERTO")>0,1,0) -> 0
A29: FRP-01 | B29: ROMPEDOR | C29: Rompedor | D29: BOSCH | E29: GBH 2-28 D | F29: 329 000 519 | G29: 1162.19 | H29: N | I29: 952463 | J29: {=IF($A29="","",IFERROR(_xlfn.XLOOKUP($A29,'Movimentação'!$B$7:$B$1006,'Movimentação'!$E$7:$E$1006,"",0,-1),""))} -> ORIÇANGA | K29: {=IF($A29="","",IFERROR(_xlfn.XLOOKUP($A29,'Movimentação'!$B$7:$B$1006,'Movimentação'!$G$7:$G$1006,"",0,-1),""))} -> EICES | L29: =IF($A29="","",IF($Q29=1,"MANUTENÇÃO",IF($P29="BAIXA","BAIXADO",IF($P29="FURTO","FURTADO",IF($J29<>"","EM OBRA","PENDENTE-PROCURAR"))))) -> EM OBRA | M29: OBS NÃO ENCONTRADO 31/08 | N29: {=IF($A29="","",IFERROR(IF(OR($L29="BAIXADO",$L29="FURTADO"),0,INDEX(Listas!$J$2:$J$40,MATCH($B29,Listas!$I$2:$I$40,0))),""))} -> 200 | P29: {=IF($A29="","",IFERROR(_xlfn.XLOOKUP($A29,'Movimentação'!$B$7:$B$1006,'Movimentação'!$F$7:$F$1006,"",0,-1),""))} -> ENTRADA (NOVA) | Q29: =IF(COUNTIFS('Manutenção'!$B$7:$B$1006,$A29,'Manutenção'!$H$7:$H$1006,"EM CONSERTO")>0,1,0) -> 0
A30: FRP-02 | B30: ROMPEDOR | C30: Rompedor | D30: BOSCH | E30: GBH 2-28 D | F30: 3911BAU2E0 | G30: 903.9 | H30: N | I30: 1051559 | J30: ASSISTENCIA TECNICA | K30: {=IF($A30="","",IFERROR(_xlfn.XLOOKUP($A30,'Movimentação'!$B$7:$B$1006,'Movimentação'!$G$7:$G$1006,"",0,-1),""))} -> EICES | L30: =IF($A30="","",IF($Q30=1,"MANUTENÇÃO",IF($P30="BAIXA","BAIXADO",IF($P30="FURTO","FURTADO",IF($J30<>"","EM OBRA","PENDENTE-PROCURAR"))))) -> BAIXADO | N30: {=IF($A30="","",IFERROR(IF(OR($L30="BAIXADO",$L30="FURTADO"),0,INDEX(Listas!$J$2:$J$40,MATCH($B30,Listas!$I$2:$I$40,0))),""))} -> 0 | P30: {=IF($A30="","",IFERROR(_xlfn.XLOOKUP($A30,'Movimentação'!$B$7:$B$1006,'Movimentação'!$F$7:$F$1006,"",0,-1),""))} -> BAIXA | Q30: =IF(COUNTIFS('Manutenção'!$B$7:$B$1006,$A30,'Manutenção'!$H$7:$H$1006,"EM CONSERTO")>0,1,0) -> 0
A31: FRP-03 | B31: ROMPEDOR | C31: Rompedor | D31: BOSCH | E31: GBH 2-28 D | F31: 3611BA02E0 | G31: 903.9 | H31: N | I31: 1051559 | J31: {=IF($A31="","",IFERROR(_xlfn.XLOOKUP($A31,'Movimentação'!$B$7:$B$1006,'Movimentação'!$E$7:$E$1006,"",0,-1),""))} -> ASSISTENCIA TECNICA | K31: {=IF($A31="","",IFERROR(_xlfn.XLOOKUP($A31,'Movimentação'!$B$7:$B$1006,'Movimentação'!$G$7:$G$1006,"",0,-1),""))} -> EICES | L31: =IF($A31="","",IF($Q31=1,"MANUTENÇÃO",IF($P31="BAIXA","BAIXADO",IF($P31="FURTO","FURTADO",IF($J31<>"","EM OBRA","PENDENTE-PROCURAR"))))) -> BAIXADO | N31: {=IF($A31="","",IFERROR(IF(OR($L31="BAIXADO",$L31="FURTADO"),0,INDEX(Listas!$J$2:$J$40,MATCH($B31,Listas!$I$2:$I$40,0))),""))} -> 0 | P31: {=IF($A31="","",IFERROR(_xlfn.XLOOKUP($A31,'Movimentação'!$B$7:$B$1006,'Movimentação'!$F$7:$F$1006,"",0,-1),""))} -> BAIXA | Q31: =IF(COUNTIFS('Manutenção'!$B$7:$B$1006,$A31,'Manutenção'!$H$7:$H$1006,"EM CONSERTO")>0,1,0) -> 0
A32: FRP-04 | B32: ROMPEDOR | C32: Rompedor | F32: 609361800 | G32: 903.9 | H32: S | J32: {=IF($A32="","",IFERROR(_xlfn.XLOOKUP($A32,'Movimentação'!$B$7:$B$1006,'Movimentação'!$E$7:$E$1006,"",0,-1),""))} | K32: {=IF($A32="","",IFERROR(_xlfn.XLOOKUP($A32,'Movimentação'!$B$7:$B$1006,'Movimentação'!$G$7:$G$1006,"",0,-1),""))} | L32: =IF($A32="","",IF($Q32=1,"MANUTENÇÃO",IF($P32="BAIXA","BAIXADO",IF($P32="FURTO","FURTADO",IF($J32<>"","EM OBRA","PENDENTE-PROCURAR"))))) -> PENDENTE-PROCURAR | N32: {=IF($A32="","",IFERROR(IF(OR($L32="BAIXADO",$L32="FURTADO"),0,INDEX(Listas!$J$2:$J$40,MATCH($B32,Listas!$I$2:$I$40,0))),""))} -> 200 | P32: {=IF($A32="","",IFERROR(_xlfn.XLOOKUP($A32,'Movimentação'!$B$7:$B$1006,'Movimentação'!$F$7:$F$1006,"",0,-1),""))} | Q32: =IF(COUNTIFS('Manutenção'!$B$7:$B$1006,$A32,'Manutenção'!$H$7:$H$1006,"EM CONSERTO")>0,1,0) -> 0
A33: FRP-05 | B33: ROMPEDOR | C33: Rompedor | D33: THAF | E33: H26F-3 | F33: 202400041 | G33: 903.9 | H33: S | J33: {=IF($A33="","",IFERROR(_xlfn.XLOOKUP($A33,'Movimentação'!$B$7:$B$1006,'Movimentação'!$E$7:$E$1006,"",0,-1),""))} -> TANABI | K33: {=IF($A33="","",IFERROR(_xlfn.XLOOKUP($A33,'Movimentação'!$B$7:$B$1006,'Movimentação'!$G$7:$G$1006,"",0,-1),""))} -> EICES | L33: =IF($A33="","",IF($Q33=1,"MANUTENÇÃO",IF($P33="BAIXA","BAIXADO",IF($P33="FURTO","FURTADO",IF($J33<>"","EM OBRA","PENDENTE-PROCURAR"))))) -> EM OBRA | N33: {=IF($A33="","",IFERROR(IF(OR($L33="BAIXADO",$L33="FURTADO"),0,INDEX(Listas!$J$2:$J$40,MATCH($B33,Listas!$I$2:$I$40,0))),""))} -> 200 | P33: {=IF($A33="","",IFERROR(_xlfn.XLOOKUP($A33,'Movimentação'!$B$7:$B$1006,'Movimentação'!$F$7:$F$1006,"",0,-1),""))} -> ENTRADA (NOVA) | Q33: =IF(COUNTIFS('Manutenção'!$B$7:$B$1006,$A33,'Manutenção'!$H$7:$H$1006,"EM CONSERTO")>0,1,0) -> 0
A34: FRP-06 | B34: ROMPEDOR | C34: Rompedor | D34: THAF | E34: H26F-3 | F34: 202400138 | G34: 903.9 | H34: S | J34: {=IF($A34="","",IFERROR(_xlfn.XLOOKUP($A34,'Movimentação'!$B$7:$B$1006,'Movimentação'!$E$7:$E$1006,"",0,-1),""))} -> SAMPA CONSOLAÇÃO | K34: {=IF($A34="","",IFERROR(_xlfn.XLOOKUP($A34,'Movimentação'!$B$7:$B$1006,'Movimentação'!$G$7:$G$1006,"",0,-1),""))} -> TIAGO | L34: =IF($A34="","",IF($Q34=1,"MANUTENÇÃO",IF($P34="BAIXA","BAIXADO",IF($P34="FURTO","FURTADO",IF($J34<>"","EM OBRA","PENDENTE-PROCURAR"))))) -> EM OBRA | N34: {=IF($A34="","",IFERROR(IF(OR($L34="BAIXADO",$L34="FURTADO"),0,INDEX(Listas!$J$2:$J$40,MATCH($B34,Listas!$I$2:$I$40,0))),""))} -> 200 | P34: {=IF($A34="","",IFERROR(_xlfn.XLOOKUP($A34,'Movimentação'!$B$7:$B$1006,'Movimentação'!$F$7:$F$1006,"",0,-1),""))} -> RETORNO MANUTENÇÃO | Q34: =IF(COUNTIFS('Manutenção'!$B$7:$B$1006,$A34,'Manutenção'!$H$7:$H$1006,"EM CONSERTO")>0,1,0) -> 0
A35: FRP-07 | B35: ROMPEDOR | C35: Rompedor | D35: THAF | E35: H26F-3 | F35: 202400850 | G35: 903.9 | H35: S | J35: {=IF($A35="","",IFERROR(_xlfn.XLOOKUP($A35,'Movimentação'!$B$7:$B$1006,'Movimentação'!$E$7:$E$1006,"",0,-1),""))} -> ALPHA ONE | K35: {=IF($A35="","",IFERROR(_xlfn.XLOOKUP($A35,'Movimentação'!$B$7:$B$1006,'Movimentação'!$G$7:$G$1006,"",0,-1),""))} -> EICES | L35: =IF($A35="","",IF($Q35=1,"MANUTENÇÃO",IF($P35="BAIXA","BAIXADO",IF($P35="FURTO","FURTADO",IF($J35<>"","EM OBRA","PENDENTE-PROCURAR"))))) -> BAIXADO | N35: {=IF($A35="","",IFERROR(IF(OR($L35="BAIXADO",$L35="FURTADO"),0,INDEX(Listas!$J$2:$J$40,MATCH($B35,Listas!$I$2:$I$40,0))),""))} -> 0 | P35: {=IF($A35="","",IFERROR(_xlfn.XLOOKUP($A35,'Movimentação'!$B$7:$B$1006,'Movimentação'!$F$7:$F$1006,"",0,-1),""))} -> BAIXA | Q35: =IF(COUNTIFS('Manutenção'!$B$7:$B$1006,$A35,'Manutenção'!$H$7:$H$1006,"EM CONSERTO")>0,1,0) -> 0
A36: FRP-08 | B36: ROMPEDOR | C36: Rompedor | D36: THAF | E36: H26F-3 | G36: 903.9 | H36: S | J36: {=IF($A36="","",IFERROR(_xlfn.XLOOKUP($A36,'Movimentação'!$B$7:$B$1006,'Movimentação'!$E$7:$E$1006,"",0,-1),""))} -> MAURO | K36: {=IF($A36="","",IFERROR(_xlfn.XLOOKUP($A36,'Movimentação'!$B$7:$B$1006,'Movimentação'!$G$7:$G$1006,"",0,-1),""))} -> EICES | L36: =IF($A36="","",IF($Q36=1,"MANUTENÇÃO",IF($P36="BAIXA","BAIXADO",IF($P36="FURTO","FURTADO",IF($J36<>"","EM OBRA","PENDENTE-PROCURAR"))))) -> EM OBRA | N36: {=IF($A36="","",IFERROR(IF(OR($L36="BAIXADO",$L36="FURTADO"),0,INDEX(Listas!$J$2:$J$40,MATCH($B36,Listas!$I$2:$I$40,0))),""))} -> 200 | P36: {=IF($A36="","",IFERROR(_xlfn.XLOOKUP($A36,'Movimentação'!$B$7:$B$1006,'Movimentação'!$F$7:$F$1006,"",0,-1),""))} -> ENTRADA (NOVA) | Q36: =IF(COUNTIFS('Manutenção'!$B$7:$B$1006,$A36,'Manutenção'!$H$7:$H$1006,"EM CONSERTO")>0,1,0) -> 0
A37: FRP-09 | B37: ROMPEDOR | C37: Rompedor | D37: THAF | E37: H26F-3 | F37: 202401394 | G37: 903.9 | H37: S | J37: {=IF($A37="","",IFERROR(_xlfn.XLOOKUP($A37,'Movimentação'!$B$7:$B$1006,'Movimentação'!$E$7:$E$1006,"",0,-1),""))} -> MANUTENÇÃO | K37: {=IF($A37="","",IFERROR(_xlfn.XLOOKUP($A37,'Movimentação'!$B$7:$B$1006,'Movimentação'!$G$7:$G$1006,"",0,-1),""))} -> LAÉRCIO | L37: =IF($A37="","",IF($Q37=1,"MANUTENÇÃO",IF($P37="BAIXA","BAIXADO",IF($P37="FURTO","FURTADO",IF($J37<>"","EM OBRA","PENDENTE-PROCURAR"))))) -> EM OBRA | N37: {=IF($A37="","",IFERROR(IF(OR($L37="BAIXADO",$L37="FURTADO"),0,INDEX(Listas!$J$2:$J$40,MATCH($B37,Listas!$I$2:$I$40,0))),""))} -> 200 | P37: {=IF($A37="","",IFERROR(_xlfn.XLOOKUP($A37,'Movimentação'!$B$7:$B$1006,'Movimentação'!$F$7:$F$1006,"",0,-1),""))} -> ENVIO P/ MANUTENÇÃO | Q37: =IF(COUNTIFS('Manutenção'!$B$7:$B$1006,$A37,'Manutenção'!$H$7:$H$1006,"EM CONSERTO")>0,1,0) -> 0
A38: FRP-10 | B38: ROMPEDOR | C38: Rompedor | D38: THAF | E38: H26F-3 | F38: 202402289 | G38: 903.9 | H38: S | J38: {=IF($A38="","",IFERROR(_xlfn.XLOOKUP($A38,'Movimentação'!$B$7:$B$1006,'Movimentação'!$E$7:$E$1006,"",0,-1),""))} -> JOA | K38: {=IF($A38="","",IFERROR(_xlfn.XLOOKUP($A38,'Movimentação'!$B$7:$B$1006,'Movimentação'!$G$7:$G$1006,"",0,-1),""))} -> EICES | L38: =IF($A38="","",IF($Q38=1,"MANUTENÇÃO",IF($P38="BAIXA","BAIXADO",IF($P38="FURTO","FURTADO",IF($J38<>"","EM OBRA","PENDENTE-PROCURAR"))))) -> EM OBRA | N38: {=IF($A38="","",IFERROR(IF(OR($L38="BAIXADO",$L38="FURTADO"),0,INDEX(Listas!$J$2:$J$40,MATCH($B38,Listas!$I$2:$I$40,0))),""))} -> 200 | P38: {=IF($A38="","",IFERROR(_xlfn.XLOOKUP($A38,'Movimentação'!$B$7:$B$1006,'Movimentação'!$F$7:$F$1006,"",0,-1),""))} -> ENTRADA (NOVA) | Q38: =IF(COUNTIFS('Manutenção'!$B$7:$B$1006,$A38,'Manutenção'!$H$7:$H$1006,"EM CONSERTO")>0,1,0) -> 0
A39: FRP-11 | B39: ROMPEDOR | C39: Rompedor | D39: THAF | E39: H26F-3 | F39: 202402281 | G39: 903.9 | H39: S | J39: {=IF($A39="","",IFERROR(_xlfn.XLOOKUP($A39,'Movimentação'!$B$7:$B$1006,'Movimentação'!$E$7:$E$1006,"",0,-1),""))} -> PJM | K39: {=IF($A39="","",IFERROR(_xlfn.XLOOKUP($A39,'Movimentação'!$B$7:$B$1006,'Movimentação'!$G$7:$G$1006,"",0,-1),""))} -> EICES | L39: =IF($A39="","",IF($Q39=1,"MANUTENÇÃO",IF($P39="BAIXA","BAIXADO",IF($P39="FURTO","FURTADO",IF($J39<>"","EM OBRA","PENDENTE-PROCURAR"))))) -> EM OBRA | N39: {=IF($A39="","",IFERROR(IF(OR($L39="BAIXADO",$L39="FURTADO"),0,INDEX(Listas!$J$2:$J$40,MATCH($B39,Listas!$I$2:$I$40,0))),""))} -> 200 | P39: {=IF($A39="","",IFERROR(_xlfn.XLOOKUP($A39,'Movimentação'!$B$7:$B$1006,'Movimentação'!$F$7:$F$1006,"",0,-1),""))} -> ENTRADA (NOVA) | Q39: =IF(COUNTIFS('Manutenção'!$B$7:$B$1006,$A39,'Manutenção'!$H$7:$H$1006,"EM CONSERTO")>0,1,0) -> 0
A40: FRP-12 | B40: ROMPEDOR | C40: Rompedor | D40: THAF | E40: H26F-3 | F40: 202402285 | G40: 903.9 | H40: S | J40: {=IF($A40="","",IFERROR(_xlfn.XLOOKUP($A40,'Movimentação'!$B$7:$B$1006,'Movimentação'!$E$7:$E$1006,"",0,-1),""))} -> SAMPA CONSOLAÇÃO | K40: {=IF($A40="","",IFERROR(_xlfn.XLOOKUP($A40,'Movimentação'!$B$7:$B$1006,'Movimentação'!$G$7:$G$1006,"",0,-1),""))} -> EICES | L40: =IF($A40="","",IF($Q40=1,"MANUTENÇÃO",IF($P40="BAIXA","BAIXADO",IF($P40="FURTO","FURTADO",IF($J40<>"","EM OBRA","PENDENTE-PROCURAR"))))) -> EM OBRA | N40: {=IF($A40="","",IFERROR(IF(OR($L40="BAIXADO",$L40="FURTADO"),0,INDEX(Listas!$J$2:$J$40,MATCH($B40,Listas!$I$2:$I$40,0))),""))} -> 200 | P40: {=IF($A40="","",IFERROR(_xlfn.XLOOKUP($A40,'Movimentação'!$B$7:$B$1006,'Movimentação'!$F$7:$F$1006,"",0,-1),""))} -> ENTRADA (NOVA) | Q40: =IF(COUNTIFS('Manutenção'!$B$7:$B$1006,$A40,'Manutenção'!$H$7:$H$1006,"EM CONSERTO")>0,1,0) -> 0
A41: FRP-13 | B41: ROMPEDOR | C41: Rompedor | D41: THAF | E41: H26F-3 | F41: 202402283 | G41: 903.9 | H41: S | J41: {=IF($A41="","",IFERROR(_xlfn.XLOOKUP($A41,'Movimentação'!$B$7:$B$1006,'Movimentação'!$E$7:$E$1006,"",0,-1),""))} | K41: {=IF($A41="","",IFERROR(_xlfn.XLOOKUP($A41,'Movimentação'!$B$7:$B$1006,'Movimentação'!$G$7:$G$1006,"",0,-1),""))} | L41: =IF($A41="","",IF($Q41=1,"MANUTENÇÃO",IF($P41="BAIXA","BAIXADO",IF($P41="FURTO","FURTADO",IF($J41<>"","EM OBRA","PENDENTE-PROCURAR"))))) -> PENDENTE-PROCURAR | N41: {=IF($A41="","",IFERROR(IF(OR($L41="BAIXADO",$L41="FURTADO"),0,INDEX(Listas!$J$2:$J$40,MATCH($B41,Listas!$I$2:$I$40,0))),""))} -> 200 | P41: {=IF($A41="","",IFERROR(_xlfn.XLOOKUP($A41,'Movimentação'!$B$7:$B$1006,'Movimentação'!$F$7:$F$1006,"",0,-1),""))} | Q41: =IF(COUNTIFS('Manutenção'!$B$7:$B$1006,$A41,'Manutenção'!$H$7:$H$1006,"EM CONSERTO")>0,1,0) -> 0
A42: FRP-14 | B42: ROMPEDOR | C42: Rompedor | D42: THAF | E42: H26F-3 | F42: 202402282 | G42: 903.9 | H42: S | J42: {=IF($A42="","",IFERROR(_xlfn.XLOOKUP($A42,'Movimentação'!$B$7:$B$1006,'Movimentação'!$E$7:$E$1006,"",0,-1),""))} -> MANUTENÇÃO | K42: {=IF($A42="","",IFERROR(_xlfn.XLOOKUP($A42,'Movimentação'!$B$7:$B$1006,'Movimentação'!$G$7:$G$1006,"",0,-1),""))} -> LAÉRCIO | L42: =IF($A42="","",IF($Q42=1,"MANUTENÇÃO",IF($P42="BAIXA","BAIXADO",IF($P42="FURTO","FURTADO",IF($J42<>"","EM OBRA","PENDENTE-PROCURAR"))))) -> MANUTENÇÃO | N42: {=IF($A42="","",IFERROR(IF(OR($L42="BAIXADO",$L42="FURTADO"),0,INDEX(Listas!$J$2:$J$40,MATCH($B42,Listas!$I$2:$I$40,0))),""))} -> 200 | P42: {=IF($A42="","",IFERROR(_xlfn.XLOOKUP($A42,'Movimentação'!$B$7:$B$1006,'Movimentação'!$F$7:$F$1006,"",0,-1),""))} -> ENVIO P/ MANUTENÇÃO | Q42: =IF(COUNTIFS('Manutenção'!$B$7:$B$1006,$A42,'Manutenção'!$H$7:$H$1006,"EM CONSERTO")>0,1,0) -> 1
A43: ESL-01 | B43: ESMERILHADEIRA | C43: Esmerilhadeira | D43: BOSCH | E43: GWS 850 | F43: 332 50 1821 | G43: 284.11 | H43: N | I43: 952463 | J43: {=IF($A43="","",IFERROR(_xlfn.XLOOKUP($A43,'Movimentação'!$B$7:$B$1006,'Movimentação'!$E$7:$E$1006,"",0,-1),""))} -> ASSISTENCIA TECNICA | K43: {=IF($A43="","",IFERROR(_xlfn.XLOOKUP($A43,'Movimentação'!$B$7:$B$1006,'Movimentação'!$G$7:$G$1006,"",0,-1),""))} -> EICES | L43: =IF($A43="","",IF($Q43=1,"MANUTENÇÃO",IF($P43="BAIXA","BAIXADO",IF($P43="FURTO","FURTADO",IF($J43<>"","EM OBRA","PENDENTE-PROCURAR"))))) -> BAIXADO | N43: {=IF($A43="","",IFERROR(IF(OR($L43="BAIXADO",$L43="FURTADO"),0,INDEX(Listas!$J$2:$J$40,MATCH($B43,Listas!$I$2:$I$40,0))),""))} -> 0 | P43: {=IF($A43="","",IFERROR(_xlfn.XLOOKUP($A43,'Movimentação'!$B$7:$B$1006,'Movimentação'!$F$7:$F$1006,"",0,-1),""))} -> BAIXA | Q43: =IF(COUNTIFS('Manutenção'!$B$7:$B$1006,$A43,'Manutenção'!$H$7:$H$1006,"EM CONSERTO")>0,1,0) -> 0
A44: ESL-02 | B44: ESMERILHADEIRA | C44: Esmerilhadeira | D44: BOSCH | E44: GWS 850 | F44: 332 50 1820 | G44: 284.11 | H44: N | I44: 952464 | J44: {=IF($A44="","",IFERROR(_xlfn.XLOOKUP($A44,'Movimentação'!$B$7:$B$1006,'Movimentação'!$E$7:$E$1006,"",0,-1),""))} -> MAURO | K44: {=IF($A44="","",IFERROR(_xlfn.XLOOKUP($A44,'Movimentação'!$B$7:$B$1006,'Movimentação'!$G$7:$G$1006,"",0,-1),""))} -> EICES | L44: =IF($A44="","",IF($Q44=1,"MANUTENÇÃO",IF($P44="BAIXA","BAIXADO",IF($P44="FURTO","FURTADO",IF($J44<>"","EM OBRA","PENDENTE-PROCURAR"))))) -> EM OBRA | N44: {=IF($A44="","",IFERROR(IF(OR($L44="BAIXADO",$L44="FURTADO"),0,INDEX(Listas!$J$2:$J$40,MATCH($B44,Listas!$I$2:$I$40,0))),""))} -> 200 | P44: {=IF($A44="","",IFERROR(_xlfn.XLOOKUP($A44,'Movimentação'!$B$7:$B$1006,'Movimentação'!$F$7:$F$1006,"",0,-1),""))} -> ENTRADA (NOVA) | Q44: =IF(COUNTIFS('Manutenção'!$B$7:$B$1006,$A44,'Manutenção'!$H$7:$H$1006,"EM CONSERTO")>0,1,0) -> 0
A45: ESL-03 | B45: ESMERILHADEIRA | C45: Esmerilhadeira | D45: BOSCH | E45: GWS 850 | F45: 332 50 1877 | G45: 284.11 | H45: N | I45: 952465 | J45: {=IF($A45="","",IFERROR(_xlfn.XLOOKUP($A45,'Movimentação'!$B$7:$B$1006,'Movimentação'!$E$7:$E$1006,"",0,-1),""))} -> ASSISTENCIA TECNICA | K45: {=IF($A45="","",IFERROR(_xlfn.XLOOKUP($A45,'Movimentação'!$B$7:$B$1006,'Movimentação'!$G$7:$G$1006,"",0,-1),""))} -> GABRIEL | L45: =IF($A45="","",IF($Q45=1,"MANUTENÇÃO",IF($P45="BAIXA","BAIXADO",IF($P45="FURTO","FURTADO",IF($J45<>"","EM OBRA","PENDENTE-PROCURAR"))))) -> BAIXADO | N45: {=IF($A45="","",IFERROR(IF(OR($L45="BAIXADO",$L45="FURTADO"),0,INDEX(Listas!$J$2:$J$40,MATCH($B45,Listas!$I$2:$I$40,0))),""))} -> 0 | P45: {=IF($A45="","",IFERROR(_xlfn.XLOOKUP($A45,'Movimentação'!$B$7:$B$1006,'Movimentação'!$F$7:$F$1006,"",0,-1),""))} -> BAIXA | Q45: =IF(COUNTIFS('Manutenção'!$B$7:$B$1006,$A45,'Manutenção'!$H$7:$H$1006,"EM CONSERTO")>0,1,0) -> 0
A46: ESL-04 | B46: ESMERILHADEIRA | C46: Esmerilhadeira | D46: BOSCH | E46: GWS 850 | F46: 333 50 1874 | G46: 284.11 | H46: N | I46: 952466 | J46: {=IF($A46="","",IFERROR(_xlfn.XLOOKUP($A46,'Movimentação'!$B$7:$B$1006,'Movimentação'!$E$7:$E$1006,"",0,-1),""))} -> ARENGA (TRISUL) | K46: {=IF($A46="","",IFERROR(_xlfn.XLOOKUP($A46,'Movimentação'!$B$7:$B$1006,'Movimentação'!$G$7:$G$1006,"",0,-1),""))} -> EICES | L46: =IF($A46="","",IF($Q46=1,"MANUTENÇÃO",IF($P46="BAIXA","BAIXADO",IF($P46="FURTO","FURTADO",IF($J46<>"","EM OBRA","PENDENTE-PROCURAR"))))) -> EM OBRA | N46: {=IF($A46="","",IFERROR(IF(OR($L46="BAIXADO",$L46="FURTADO"),0,INDEX(Listas!$J$2:$J$40,MATCH($B46,Listas!$I$2:$I$40,0))),""))} -> 200 | P46: {=IF($A46="","",IFERROR(_xlfn.XLOOKUP($A46,'Movimentação'!$B$7:$B$1006,'Movimentação'!$F$7:$F$1006,"",0,-1),""))} -> ENTRADA (NOVA) | Q46: =IF(COUNTIFS('Manutenção'!$B$7:$B$1006,$A46,'Manutenção'!$H$7:$H$1006,"EM CONSERTO")>0,1,0) -> 0
A47: ESL-05 | B47: ESMERILHADEIRA | C47: Esmerilhadeira | D47: BOSCH | E47: GWS 850 | F47: 334 50 1093 | G47: 284.11 | H47: N | I47: 952467 | J47: {=IF($A47="","",IFERROR(_xlfn.XLOOKUP($A47,'Movimentação'!$B$7:$B$1006,'Movimentação'!$E$7:$E$1006,"",0,-1),""))} | K47: {=IF($A47="","",IFERROR(_xlfn.XLOOKUP($A47,'Movimentação'!$B$7:$B$1006,'Movimentação'!$G$7:$G$1006,"",0,-1),""))} | L47: =IF($A47="","",IF($Q47=1,"MANUTENÇÃO",IF($P47="BAIXA","BAIXADO",IF($P47="FURTO","FURTADO",IF($J47<>"","EM OBRA","PENDENTE-PROCURAR"))))) -> PENDENTE-PROCURAR | N47: {=IF($A47="","",IFERROR(IF(OR($L47="BAIXADO",$L47="FURTADO"),0,INDEX(Listas!$J$2:$J$40,MATCH($B47,Listas!$I$2:$I$40,0))),""))} -> 200 | P47: {=IF($A47="","",IFERROR(_xlfn.XLOOKUP($A47,'Movimentação'!$B$7:$B$1006,'Movimentação'!$F$7:$F$1006,"",0,-1),""))} | Q47: =IF(COUNTIFS('Manutenção'!$B$7:$B$1006,$A47,'Manutenção'!$H$7:$H$1006,"EM CONSERTO")>0,1,0) -> 0
A48: ESL-06 | B48: ESMERILHADEIRA | C48: Esmerilhadeira | D48: BOSCH | F48: 327 033 774 | G48: 300 | H48: N | I48: 1275 | J48: {=IF($A48="","",IFERROR(_xlfn.XLOOKUP($A48,'Movimentação'!$B$7:$B$1006,'Movimentação'!$E$7:$E$1006,"",0,-1),""))} | K48: {=IF($A48="","",IFERROR(_xlfn.XLOOKUP($A48,'Movimentação'!$B$7:$B$1006,'Movimentação'!$G$7:$G$1006,"",0,-1),""))} | L48: =IF($A48="","",IF($Q48=1,"MANUTENÇÃO",IF($P48="BAIXA","BAIXADO",IF($P48="FURTO","FURTADO",IF($J48<>"","EM OBRA","PENDENTE-PROCURAR"))))) -> PENDENTE-PROCURAR | N48: {=IF($A48="","",IFERROR(IF(OR($L48="BAIXADO",$L48="FURTADO"),0,INDEX(Listas!$J$2:$J$40,MATCH($B48,Listas!$I$2:$I$40,0))),""))} -> 200 | P48: {=IF($A48="","",IFERROR(_xlfn.XLOOKUP($A48,'Movimentação'!$B$7:$B$1006,'Movimentação'!$F$7:$F$1006,"",0,-1),""))} | Q48: =IF(COUNTIFS('Manutenção'!$B$7:$B$1006,$A48,'Manutenção'!$H$7:$H$1006,"EM CONSERTO")>0,1,0) -> 0
A49: ESL-07 | B49: ESMERILHADEIRA | C49: Esmerilhadeira | D49: BOSCH | F49: 36601C775E0 | G49: 380 | H49: N | I49: 1276 | J49: {=IF($A49="","",IFERROR(_xlfn.XLOOKUP($A49,'Movimentação'!$B$7:$B$1006,'Movimentação'!$E$7:$E$1006,"",0,-1),""))} -> ANGELICA | K49: THIAGO | L49: =IF($A49="","",IF($Q49=1,"MANUTENÇÃO",IF($P49="BAIXA","BAIXADO",IF($P49="FURTO","FURTADO",IF($J49<>"","EM OBRA","PENDENTE-PROCURAR"))))) -> EM OBRA | N49: {=IF($A49="","",IFERROR(IF(OR($L49="BAIXADO",$L49="FURTADO"),0,INDEX(Listas!$J$2:$J$40,MATCH($B49,Listas!$I$2:$I$40,0))),""))} -> 200 | P49: {=IF($A49="","",IFERROR(_xlfn.XLOOKUP($A49,'Movimentação'!$B$7:$B$1006,'Movimentação'!$F$7:$F$1006,"",0,-1),""))} -> ENTRADA (NOVA) | Q49: =IF(COUNTIFS('Manutenção'!$B$7:$B$1006,$A49,'Manutenção'!$H$7:$H$1006,"EM CONSERTO")>0,1,0) -> 0
A50: ESL-08 | B50: ESMERILHADEIRA | C50: Esmerilhadeira | D50: MAKITA | E50: M9510B | F50: M9510 | G50: 354.44 | H50: N | I50: 50816 | J50: {=IF($A50="","",IFERROR(_xlfn.XLOOKUP($A50,'Movimentação'!$B$7:$B$1006,'Movimentação'!$E$7:$E$1006,"",0,-1),""))} | K50: {=IF($A50="","",IFERROR(_xlfn.XLOOKUP($A50,'Movimentação'!$B$7:$B$1006,'Movimentação'!$G$7:$G$1006,"",0,-1),""))} | L50: =IF($A50="","",IF($Q50=1,"MANUTENÇÃO",IF($P50="BAIXA","BAIXADO",IF($P50="FURTO","FURTADO",IF($J50<>"","EM OBRA","PENDENTE-PROCURAR"))))) -> PENDENTE-PROCURAR | N50: {=IF($A50="","",IFERROR(IF(OR($L50="BAIXADO",$L50="FURTADO"),0,INDEX(Listas!$J$2:$J$40,MATCH($B50,Listas!$I$2:$I$40,0))),""))} -> 200 | P50: {=IF($A50="","",IFERROR(_xlfn.XLOOKUP($A50,'Movimentação'!$B$7:$B$1006,'Movimentação'!$F$7:$F$1006,"",0,-1),""))} | Q50: =IF(COUNTIFS('Manutenção'!$B$7:$B$1006,$A50,'Manutenção'!$H$7:$H$1006,"EM CONSERTO")>0,1,0) -> 0
A51: ESL-09 | B51: ESMERILHADEIRA | C51: Esmerilhadeira | D51: BOSCH | E51: GWS850 | F51: GWS850 | G51: 300 | H51: N | J51: {=IF($A51="","",IFERROR(_xlfn.XLOOKUP($A51,'Movimentação'!$B$7:$B$1006,'Movimentação'!$E$7:$E$1006,"",0,-1),""))} | K51: {=IF($A51="","",IFERROR(_xlfn.XLOOKUP($A51,'Movimentação'!$B$7:$B$1006,'Movimentação'!$G$7:$G$1006,"",0,-1),""))} | L51: =IF($A51="","",IF($Q51=1,"MANUTENÇÃO",IF($P51="BAIXA","BAIXADO",IF($P51="FURTO","FURTADO",IF($J51<>"","EM OBRA","PENDENTE-PROCURAR"))))) -> PENDENTE-PROCURAR | N51: {=IF($A51="","",IFERROR(IF(OR($L51="BAIXADO",$L51="FURTADO"),0,INDEX(Listas!$J$2:$J$40,MATCH($B51,Listas!$I$2:$I$40,0))),""))} -> 200 | P51: {=IF($A51="","",IFERROR(_xlfn.XLOOKUP($A51,'Movimentação'!$B$7:$B$1006,'Movimentação'!$F$7:$F$1006,"",0,-1),""))} | Q51: =IF(COUNTIFS('Manutenção'!$B$7:$B$1006,$A51,'Manutenção'!$H$7:$H$1006,"EM CONSERTO")>0,1,0) -> 0
A52: MSE-01 | B52: SERRA MÁRMORE | C52: Serra Mármore | D52: BOSCH | E52: GDC 15 | F52: 327 281886 | G52: 319.85 | H52: N | I52: 941194 | J52: {=IF($A52="","",IFERROR(_xlfn.XLOOKUP($A52,'Movimentação'!$B$7:$B$1006,'Movimentação'!$E$7:$E$1006,"",0,-1),""))} -> ASSISTENCIA TECNICA | K52: {=IF($A52="","",IFERROR(_xlfn.XLOOKUP($A52,'Movimentação'!$B$7:$B$1006,'Movimentação'!$G$7:$G$1006,"",0,-1),""))} -> EICES | L52: =IF($A52="","",IF($Q52=1,"MANUTENÇÃO",IF($P52="BAIXA","BAIXADO",IF($P52="FURTO","FURTADO",IF($J52<>"","EM OBRA","PENDENTE-PROCURAR"))))) -> BAIXADO | N52: {=IF($A52="","",IFERROR(IF(OR($L52="BAIXADO",$L52="FURTADO"),0,INDEX(Listas!$J$2:$J$40,MATCH($B52,Listas!$I$2:$I$40,0))),""))} -> 0 | P52: {=IF($A52="","",IFERROR(_xlfn.XLOOKUP($A52,'Movimentação'!$B$7:$B$1006,'Movimentação'!$F$7:$F$1006,"",0,-1),""))} -> BAIXA | Q52: =IF(COUNTIFS('Manutenção'!$B$7:$B$1006,$A52,'Manutenção'!$H$7:$H$1006,"EM CONSERTO")>0,1,0) -> 0
A53: MSE-02 | B53: SERRA MÁRMORE | C53: Serra Mármore | D53: BOSCH | E53: GDC 15 | F53: 327 281882 | G53: 319.85 | H53: N | I53: 941194 | J53: ASSISTENCIA TECNICA | K53: {=IF($A53="","",IFERROR(_xlfn.XLOOKUP($A53,'Movimentação'!$B$7:$B$1006,'Movimentação'!$G$7:$G$1006,"",0,-1),""))} -> EICES | L53: =IF($A53="","",IF($Q53=1,"MANUTENÇÃO",IF($P53="BAIXA","BAIXADO",IF($P53="FURTO","FURTADO",IF($J53<>"","EM OBRA","PENDENTE-PROCURAR"))))) -> BAIXADO | N53: {=IF($A53="","",IFERROR(IF(OR($L53="BAIXADO",$L53="FURTADO"),0,INDEX(Listas!$J$2:$J$40,MATCH($B53,Listas!$I$2:$I$40,0))),""))} -> 0 | P53: {=IF($A53="","",IFERROR(_xlfn.XLOOKUP($A53,'Movimentação'!$B$7:$B$1006,'Movimentação'!$F$7:$F$1006,"",0,-1),""))} -> BAIXA | Q53: =IF(COUNTIFS('Manutenção'!$B$7:$B$1006,$A53,'Manutenção'!$H$7:$H$1006,"EM CONSERTO")>0,1,0) -> 0
A54: MSE-03 | B54: SERRA MÁRMORE | C54: Serra Mármore | D54: BOSCH | E54: GDC 15 | F54: 327 281896 | G54: 319.85 | H54: N | I54: 941194 | J54: ASSISTENCIA TECNICA | K54: {=IF($A54="","",IFERROR(_xlfn.XLOOKUP($A54,'Movimentação'!$B$7:$B$1006,'Movimentação'!$G$7:$G$1006,"",0,-1),""))} -> EICES | L54: =IF($A54="","",IF($Q54=1,"MANUTENÇÃO",IF($P54="BAIXA","BAIXADO",IF($P54="FURTO","FURTADO",IF($J54<>"","EM OBRA","PENDENTE-PROCURAR"))))) -> BAIXADO | N54: {=IF($A54="","",IFERROR(IF(OR($L54="BAIXADO",$L54="FURTADO"),0,INDEX(Listas!$J$2:$J$40,MATCH($B54,Listas!$I$2:$I$40,0))),""))} -> 0 | P54: {=IF($A54="","",IFERROR(_xlfn.XLOOKUP($A54,'Movimentação'!$B$7:$B$1006,'Movimentação'!$F$7:$F$1006,"",0,-1),""))} -> BAIXA | Q54: =IF(COUNTIFS('Manutenção'!$B$7:$B$1006,$A54,'Manutenção'!$H$7:$H$1006,"EM CONSERTO")>0,1,0) -> 0
A55: MSE-04 | B55: SERRA MÁRMORE | C55: Serra Mármore | D55: BOSCH | E55: GDC 15 | F55: 327 281872 | G55: 319.85 | H55: N | I55: 941194 | J55: {=IF($A55="","",IFERROR(_xlfn.XLOOKUP($A55,'Movimentação'!$B$7:$B$1006,'Movimentação'!$E$7:$E$1006,"",0,-1),""))} -> ORIÇANGA | K55: {=IF($A55="","",IFERROR(_xlfn.XLOOKUP($A55,'Movimentação'!$B$7:$B$1006,'Movimentação'!$G$7:$G$1006,"",0,-1),""))} -> LEONARDO | L55: =IF($A55="","",IF($Q55=1,"MANUTENÇÃO",IF($P55="BAIXA","BAIXADO",IF($P55="FURTO","FURTADO",IF($J55<>"","EM OBRA","PENDENTE-PROCURAR"))))) -> EM OBRA | N55: {=IF($A55="","",IFERROR(IF(OR($L55="BAIXADO",$L55="FURTADO"),0,INDEX(Listas!$J$2:$J$40,MATCH($B55,Listas!$I$2:$I$40,0))),""))} -> 300 | P55: {=IF($A55="","",IFERROR(_xlfn.XLOOKUP($A55,'Movimentação'!$B$7:$B$1006,'Movimentação'!$F$7:$F$1006,"",0,-1),""))} -> TRANSFERÊNCIA | Q55: =IF(COUNTIFS('Manutenção'!$B$7:$B$1006,$A55,'Manutenção'!$H$7:$H$1006,"EM CONSERTO")>0,1,0) -> 0
A56: MSE-05 | B56: SERRA MÁRMORE | C56: Serra Mármore | D56: BOSCH | E56: GDC 15 | F56: 327 281851 | G56: 319.85 | H56: N | I56: 941194 | K56: {=IF($A56="","",IFERROR(_xlfn.XLOOKUP($A56,'Movimentação'!$B$7:$B$1006,'Movimentação'!$G$7:$G$1006,"",0,-1),""))} -> EICES | L56: PENDENTE-PROCURAR | N56: {=IF($A56="","",IFERROR(IF(OR($L56="BAIXADO",$L56="FURTADO"),0,INDEX(Listas!$J$2:$J$40,MATCH($B56,Listas!$I$2:$I$40,0))),""))} -> 300 | P56: {=IF($A56="","",IFERROR(_xlfn.XLOOKUP($A56,'Movimentação'!$B$7:$B$1006,'Movimentação'!$F$7:$F$1006,"",0,-1),""))} -> ENTRADA (NOVA) | Q56: =IF(COUNTIFS('Manutenção'!$B$7:$B$1006,$A56,'Manutenção'!$H$7:$H$1006,"EM CONSERTO")>0,1,0) -> 0
A57: MSE-06 | B57: SERRA MÁRMORE | C57: Serra Mármore | D57: MAKITA | E57: 4100NH3 | F57: 1603340 | G57: 319.85 | H57: N | I57: 941194 | J57: {=IF($A57="","",IFERROR(_xlfn.XLOOKUP($A57,'Movimentação'!$B$7:$B$1006,'Movimentação'!$E$7:$E$1006,"",0,-1),""))} -> SAMPA CONSOLAÇÃO | K57: {=IF($A57="","",IFERROR(_xlfn.XLOOKUP($A57,'Movimentação'!$B$7:$B$1006,'Movimentação'!$G$7:$G$1006,"",0,-1),""))} -> EICES | L57: =IF($A57="","",IF($Q57=1,"MANUTENÇÃO",IF($P57="BAIXA","BAIXADO",IF($P57="FURTO","FURTADO",IF($J57<>"","EM OBRA","PENDENTE-PROCURAR"))))) -> EM OBRA | N57: {=IF($A57="","",IFERROR(IF(OR($L57="BAIXADO",$L57="FURTADO"),0,INDEX(Listas!$J$2:$J$40,MATCH($B57,Listas!$I$2:$I$40,0))),""))} -> 300 | P57: {=IF($A57="","",IFERROR(_xlfn.XLOOKUP($A57,'Movimentação'!$B$7:$B$1006,'Movimentação'!$F$7:$F$1006,"",0,-1),""))} -> ENTRADA (NOVA) | Q57: =IF(COUNTIFS('Manutenção'!$B$7:$B$1006,$A57,'Manutenção'!$H$7:$H$1006,"EM CONSERTO")>0,1,0) -> 0
A58: MSE-07 | B58: SERRA MÁRMORE | C58: Serra Mármore | D58: DEWALT | E58: DW862 | F58: 85007 / MSE-09 | G58: 319.85 | H58: S | J58: {=IF($A58="","",IFERROR(_xlfn.XLOOKUP($A58,'Movimentação'!$B$7:$B$1006,'Movimentação'!$E$7:$E$1006,"",0,-1),""))} -> MAURO | K58: {=IF($A58="","",IFERROR(_xlfn.XLOOKUP($A58,'Movimentação'!$B$7:$B$1006,'Movimentação'!$G$7:$G$1006,"",0,-1),""))} -> EICES | L58: =IF($A58="","",IF($Q58=1,"MANUTENÇÃO",IF($P58="BAIXA","BAIXADO",IF($P58="FURTO","FURTADO",IF($J58<>"","EM OBRA","PENDENTE-PROCURAR"))))) -> EM OBRA | N58: {=IF($A58="","",IFERROR(IF(OR($L58="BAIXADO",$L58="FURTADO"),0,INDEX(Listas!$J$2:$J$40,MATCH($B58,Listas!$I$2:$I$40,0))),""))} -> 300 | P58: {=IF($A58="","",IFERROR(_xlfn.XLOOKUP($A58,'Movimentação'!$B$7:$B$1006,'Movimentação'!$F$7:$F$1006,"",0,-1),""))} -> ENTRADA (NOVA) | Q58: =IF(COUNTIFS('Manutenção'!$B$7:$B$1006,$A58,'Manutenção'!$H$7:$H$1006,"EM CONSERTO")>0,1,0) -> 0
A59: MSE-08 | B59: SERRA MÁRMORE | C59: Serra Mármore | D59: DEWALT | E59: DW862 | F59: 85070 | G59: 319.85 | H59: S | J59: {=IF($A59="","",IFERROR(_xlfn.XLOOKUP($A59,'Movimentação'!$B$7:$B$1006,'Movimentação'!$E$7:$E$1006,"",0,-1),""))} | K59: {=IF($A59="","",IFERROR(_xlfn.XLOOKUP($A59,'Movimentação'!$B$7:$B$1006,'Movimentação'!$G$7:$G$1006,"",0,-1),""))} | L59: =IF($A59="","",IF($Q59=1,"MANUTENÇÃO",IF($P59="BAIXA","BAIXADO",IF($P59="FURTO","FURTADO",IF($J59<>"","EM OBRA","PENDENTE-PROCURAR"))))) -> PENDENTE-PROCURAR | N59: {=IF($A59="","",IFERROR(IF(OR($L59="BAIXADO",$L59="FURTADO"),0,INDEX(Listas!$J$2:$J$40,MATCH($B59,Listas!$I$2:$I$40,0))),""))} -> 300 | P59: {=IF($A59="","",IFERROR(_xlfn.XLOOKUP($A59,'Movimentação'!$B$7:$B$1006,'Movimentação'!$F$7:$F$1006,"",0,-1),""))} | Q59: =IF(COUNTIFS('Manutenção'!$B$7:$B$1006,$A59,'Manutenção'!$H$7:$H$1006,"EM CONSERTO")>0,1,0) -> 0
A60: CMA-01 | B60: MARTELETE 5KG | C60: Martelete 5Kg | D60: BOSCH | E60: GBH 5-40 D | F60: 330 003 672 | G60: 2915.42 | H60: N | I60: 952463 | J60: {=IF($A60="","",IFERROR(_xlfn.XLOOKUP($A60,'Movimentação'!$B$7:$B$1006,'Movimentação'!$E$7:$E$1006,"",0,-1),""))} -> MAURO | K60: TAYANE | L60: =IF($A60="","",IF($Q60=1,"MANUTENÇÃO",IF($P60="BAIXA","BAIXADO",IF($P60="FURTO","FURTADO",IF($J60<>"","EM OBRA","PENDENTE-PROCURAR"))))) -> EM OBRA | N60: {=IF($A60="","",IFERROR(IF(OR($L60="BAIXADO",$L60="FURTADO"),0,INDEX(Listas!$J$2:$J$40,MATCH($B60,Listas!$I$2:$I$40,0))),""))} -> 350 | P60: {=IF($A60="","",IFERROR(_xlfn.XLOOKUP($A60,'Movimentação'!$B$7:$B$1006,'Movimentação'!$F$7:$F$1006,"",0,-1),""))} -> ENTRADA (NOVA) | Q60: =IF(COUNTIFS('Manutenção'!$B$7:$B$1006,$A60,'Manutenção'!$H$7:$H$1006,"EM CONSERTO")>0,1,0) -> 0
A61: CMA-02 | B61: MARTELETE 5KG | C61: Martelete 5Kg | D61: EINHELL | E61: CONCRETE BREAKER | F61: 67VKQ81 | G61: 2915.42 | H61: S | I61: 67VKQ81 | J61: {=IF($A61="","",IFERROR(_xlfn.XLOOKUP($A61,'Movimentação'!$B$7:$B$1006,'Movimentação'!$E$7:$E$1006,"",0,-1),""))} -> MAURO | K61: TAYANE | L61: =IF($A61="","",IF($Q61=1,"MANUTENÇÃO",IF($P61="BAIXA","BAIXADO",IF($P61="FURTO","FURTADO",IF($J61<>"","EM OBRA","PENDENTE-PROCURAR"))))) -> EM OBRA | M61: aferida indica MARTELETE 10KG | N61: {=IF($A61="","",IFERROR(IF(OR($L61="BAIXADO",$L61="FURTADO"),0,INDEX(Listas!$J$2:$J$40,MATCH($B61,Listas!$I$2:$I$40,0))),""))} -> 350 | P61: {=IF($A61="","",IFERROR(_xlfn.XLOOKUP($A61,'Movimentação'!$B$7:$B$1006,'Movimentação'!$F$7:$F$1006,"",0,-1),""))} -> ENTRADA (NOVA) | Q61: =IF(COUNTIFS('Manutenção'!$B$7:$B$1006,$A61,'Manutenção'!$H$7:$H$1006,"EM CONSERTO")>0,1,0) -> 0
A62: CMA-03 | B62: MARTELETE 5KG | C62: Martelete 5Kg | D62: EINHELL | E62: CONCRETE BREAKER | F62: 67VKLFL | G62: 2915.42 | H62: S | I62: 67VKLFL | J62: {=IF($A62="","",IFERROR(_xlfn.XLOOKUP($A62,'Movimentação'!$B$7:$B$1006,'Movimentação'!$E$7:$E$1006,"",0,-1),""))} -> ANGELICA | K62: THIAGO | L62: =IF($A62="","",IF($Q62=1,"MANUTENÇÃO",IF($P62="BAIXA","BAIXADO",IF($P62="FURTO","FURTADO",IF($J62<>"","EM OBRA","PENDENTE-PROCURAR"))))) -> EM OBRA | N62: {=IF($A62="","",IFERROR(IF(OR($L62="BAIXADO",$L62="FURTADO"),0,INDEX(Listas!$J$2:$J$40,MATCH($B62,Listas!$I$2:$I$40,0))),""))} -> 350 | P62: {=IF($A62="","",IFERROR(_xlfn.XLOOKUP($A62,'Movimentação'!$B$7:$B$1006,'Movimentação'!$F$7:$F$1006,"",0,-1),""))} -> TRANSFERÊNCIA | Q62: =IF(COUNTIFS('Manutenção'!$B$7:$B$1006,$A62,'Manutenção'!$H$7:$H$1006,"EM CONSERTO")>0,1,0) -> 0
A63: CMA-04 | B63: MARTELETE 5KG | C63: Martelete 5Kg | D63: EINHELL | E63: CONCRETE BREAKER | F63: 67VKQ2Z | G63: 2915.42 | H63: S | I63: 67VKQ2Z | J63: {=IF($A63="","",IFERROR(_xlfn.XLOOKUP($A63,'Movimentação'!$B$7:$B$1006,'Movimentação'!$E$7:$E$1006,"",0,-1),""))} -> ALTIER | K63: JOANDERSON | L63: =IF($A63="","",IF($Q63=1,"MANUTENÇÃO",IF($P63="BAIXA","BAIXADO",IF($P63="FURTO","FURTADO",IF($J63<>"","EM OBRA","PENDENTE-PROCURAR"))))) -> EM OBRA | M63: aferida indica MARTELETE 10KG | N63: {=IF($A63="","",IFERROR(IF(OR($L63="BAIXADO",$L63="FURTADO"),0,INDEX(Listas!$J$2:$J$40,MATCH($B63,Listas!$I$2:$I$40,0))),""))} -> 350 | P63: {=IF($A63="","",IFERROR(_xlfn.XLOOKUP($A63,'Movimentação'!$B$7:$B$1006,'Movimentação'!$F$7:$F$1006,"",0,-1),""))} -> ENTRADA (NOVA) | Q63: =IF(COUNTIFS('Manutenção'!$B$7:$B$1006,$A63,'Manutenção'!$H$7:$H$1006,"EM CONSERTO")>0,1,0) -> 0
A64: CMA-05 | B64: MARTELETE 5KG | C64: Martelete 5Kg | D64: HILTI | E64: TE500 | F64: 02-006 4 116-CP-12 | G64: 2915.42 | H64: S | J64: ESCRITÓRIO | K64: {=IF($A64="","",IFERROR(_xlfn.XLOOKUP($A64,'Movimentação'!$B$7:$B$1006,'Movimentação'!$G$7:$G$1006,"",0,-1),""))} -> LAÉRCIO | L64: =IF($A64="","",IF($Q64=1,"MANUTENÇÃO",IF($P64="BAIXA","BAIXADO",IF($P64="FURTO","FURTADO",IF($J64<>"","EM OBRA","PENDENTE-PROCURAR"))))) -> BAIXADO | N64: {=IF($A64="","",IFERROR(IF(OR($L64="BAIXADO",$L64="FURTADO"),0,INDEX(Listas!$J$2:$J$40,MATCH($B64,Listas!$I$2:$I$40,0))),""))} -> 0 | P64: {=IF($A64="","",IFERROR(_xlfn.XLOOKUP($A64,'Movimentação'!$B$7:$B$1006,'Movimentação'!$F$7:$F$1006,"",0,-1),""))} -> BAIXA | Q64: =IF(COUNTIFS('Manutenção'!$B$7:$B$1006,$A64,'Manutenção'!$H$7:$H$1006,"EM CONSERTO")>0,1,0) -> 0
A65: MDA-01 | B65: MARTELETE 10KG | C65: Martelete 10Kg | D65: BOSCH | E65: GSH 11 VC | F65: 329 000 028 | G65: 850 | H65: S | I65: 952463 | J65: {=IF($A65="","",IFERROR(_xlfn.XLOOKUP($A65,'Movimentação'!$B$7:$B$1006,'Movimentação'!$E$7:$E$1006,"",0,-1),""))} -> BALTAZAR | K65: GEORGE | L65: =IF($A65="","",IF($Q65=1,"MANUTENÇÃO",IF($P65="BAIXA","BAIXADO",IF($P65="FURTO","FURTADO",IF($J65<>"","EM OBRA","PENDENTE-PROCURAR"))))) -> EM OBRA | N65: {=IF($A65="","",IFERROR(IF(OR($L65="BAIXADO",$L65="FURTADO"),0,INDEX(Listas!$J$2:$J$40,MATCH($B65,Listas!$I$2:$I$40,0))),""))} -> 400 | P65: {=IF($A65="","",IFERROR(_xlfn.XLOOKUP($A65,'Movimentação'!$B$7:$B$1006,'Movimentação'!$F$7:$F$1006,"",0,-1),""))} -> TRANSFERÊNCIA | Q65: =IF(COUNTIFS('Manutenção'!$B$7:$B$1006,$A65,'Manutenção'!$H$7:$H$1006,"EM CONSERTO")>0,1,0) -> 0
A66: LAS-01 | B66: LASER | C66: Laser | D66: BOSCH | E66: 0601063XG0-000 | F66: 2227001737 | G66: 720 | H66: N | I66: 1069616 | J66: {=IF($A66="","",IFERROR(_xlfn.XLOOKUP($A66,'Movimentação'!$B$7:$B$1006,'Movimentação'!$E$7:$E$1006,"",0,-1),""))} -> ALPHA ONE | K66: {=IF($A66="","",IFERROR(_xlfn.XLOOKUP($A66,'Movimentação'!$B$7:$B$1006,'Movimentação'!$G$7:$G$1006,"",0,-1),""))} -> EICES | L66: =IF($A66="","",IF($Q66=1,"MANUTENÇÃO",IF($P66="BAIXA","BAIXADO",IF($P66="FURTO","FURTADO",IF($J66<>"","EM OBRA","PENDENTE-PROCURAR"))))) -> BAIXADO | N66: {=IF($A66="","",IFERROR(IF(OR($L66="BAIXADO",$L66="FURTADO"),0,INDEX(Listas!$J$2:$J$40,MATCH($B66,Listas!$I$2:$I$40,0))),""))} -> 0 | P66: {=IF($A66="","",IFERROR(_xlfn.XLOOKUP($A66,'Movimentação'!$B$7:$B$1006,'Movimentação'!$F$7:$F$1006,"",0,-1),""))} -> BAIXA | Q66: =IF(COUNTIFS('Manutenção'!$B$7:$B$1006,$A66,'Manutenção'!$H$7:$H$1006,"EM CONSERTO")>0,1,0) -> 0
A67: LAS-02 | B67: LASER | C67: Laser | D67: BOSCH | E67: 0601063XG0-000 | F67: 225000803 | G67: 648.9 | H67: N | I67: 601494 | J67: {=IF($A67="","",IFERROR(_xlfn.XLOOKUP($A67,'Movimentação'!$B$7:$B$1006,'Movimentação'!$E$7:$E$1006,"",0,-1),""))} | K67: {=IF($A67="","",IFERROR(_xlfn.XLOOKUP($A67,'Movimentação'!$B$7:$B$1006,'Movimentação'!$G$7:$G$1006,"",0,-1),""))} | L67: =IF($A67="","",IF($Q67=1,"MANUTENÇÃO",IF($P67="BAIXA","BAIXADO",IF($P67="FURTO","FURTADO",IF($J67<>"","EM OBRA","PENDENTE-PROCURAR"))))) -> PENDENTE-PROCURAR | N67: {=IF($A67="","",IFERROR(IF(OR($L67="BAIXADO",$L67="FURTADO"),0,INDEX(Listas!$J$2:$J$40,MATCH($B67,Listas!$I$2:$I$40,0))),""))} -> 200 | P67: {=IF($A67="","",IFERROR(_xlfn.XLOOKUP($A67,'Movimentação'!$B$7:$B$1006,'Movimentação'!$F$7:$F$1006,"",0,-1),""))} | Q67: =IF(COUNTIFS('Manutenção'!$B$7:$B$1006,$A67,'Manutenção'!$H$7:$H$1006,"EM CONSERTO")>0,1,0) -> 0
A68: LAS-03 | B68: LASER | C68: Laser | D68: BOSCH | E68: 0601063XG0-000 | G68: 979.9 | H68: N | I68: 50816 | J68: {=IF($A68="","",IFERROR(_xlfn.XLOOKUP($A68,'Movimentação'!$B$7:$B$1006,'Movimentação'!$E$7:$E$1006,"",0,-1),""))} | K68: {=IF($A68="","",IFERROR(_xlfn.XLOOKUP($A68,'Movimentação'!$B$7:$B$1006,'Movimentação'!$G$7:$G$1006,"",0,-1),""))} | L68: =IF($A68="","",IF($Q68=1,"MANUTENÇÃO",IF($P68="BAIXA","BAIXADO",IF($P68="FURTO","FURTADO",IF($J68<>"","EM OBRA","PENDENTE-PROCURAR"))))) -> PENDENTE-PROCURAR | N68: {=IF($A68="","",IFERROR(IF(OR($L68="BAIXADO",$L68="FURTADO"),0,INDEX(Listas!$J$2:$J$40,MATCH($B68,Listas!$I$2:$I$40,0))),""))} -> 200 | P68: {=IF($A68="","",IFERROR(_xlfn.XLOOKUP($A68,'Movimentação'!$B$7:$B$1006,'Movimentação'!$F$7:$F$1006,"",0,-1),""))} | Q68: =IF(COUNTIFS('Manutenção'!$B$7:$B$1006,$A68,'Manutenção'!$H$7:$H$1006,"EM CONSERTO")>0,1,0) -> 0
A69: LAS-04 | B69: LASER | C69: Laser | D69: DEWALT | E69: DW088K | F69: 902349 DW088 | G69: 834 | H69: N | I69: 50816 | J69: {=IF($A69="","",IFERROR(_xlfn.XLOOKUP($A69,'Movimentação'!$B$7:$B$1006,'Movimentação'!$E$7:$E$1006,"",0,-1),""))} -> ESCRITÓRIO | K69: {=IF($A69="","",IFERROR(_xlfn.XLOOKUP($A69,'Movimentação'!$B$7:$B$1006,'Movimentação'!$G$7:$G$1006,"",0,-1),""))} -> EICES | L69: =IF($A69="","",IF($Q69=1,"MANUTENÇÃO",IF($P69="BAIXA","BAIXADO",IF($P69="FURTO","FURTADO",IF($J69<>"","EM OBRA","PENDENTE-PROCURAR"))))) -> EM OBRA | N69: {=IF($A69="","",IFERROR(IF(OR($L69="BAIXADO",$L69="FURTADO"),0,INDEX(Listas!$J$2:$J$40,MATCH($B69,Listas!$I$2:$I$40,0))),""))} -> 200 | P69: {=IF($A69="","",IFERROR(_xlfn.XLOOKUP($A69,'Movimentação'!$B$7:$B$1006,'Movimentação'!$F$7:$F$1006,"",0,-1),""))} -> ENTRADA (NOVA) | Q69: =IF(COUNTIFS('Manutenção'!$B$7:$B$1006,$A69,'Manutenção'!$H$7:$H$1006,"EM CONSERTO")>0,1,0) -> 0
A70: LAS-05 | B70: LASER | C70: Laser | D70: BOSCH | E70: - | F70: 232005979 | G70: 835 | H70: N | J70: {=IF($A70="","",IFERROR(_xlfn.XLOOKUP($A70,'Movimentação'!$B$7:$B$1006,'Movimentação'!$E$7:$E$1006,"",0,-1),""))} -> ORIÇANGA | K70: LEONARDO | L70: =IF($A70="","",IF($Q70=1,"MANUTENÇÃO",IF($P70="BAIXA","BAIXADO",IF($P70="FURTO","FURTADO",IF($J70<>"","EM OBRA","PENDENTE-PROCURAR"))))) -> EM OBRA | N70: {=IF($A70="","",IFERROR(IF(OR($L70="BAIXADO",$L70="FURTADO"),0,INDEX(Listas!$J$2:$J$40,MATCH($B70,Listas!$I$2:$I$40,0))),""))} -> 200 | P70: {=IF($A70="","",IFERROR(_xlfn.XLOOKUP($A70,'Movimentação'!$B$7:$B$1006,'Movimentação'!$F$7:$F$1006,"",0,-1),""))} -> ENTRADA (NOVA) | Q70: =IF(COUNTIFS('Manutenção'!$B$7:$B$1006,$A70,'Manutenção'!$H$7:$H$1006,"EM CONSERTO")>0,1,0) -> 0
A71: LAS-06 | B71: LASER | C71: Laser | D71: BOSCH | E71: - | F71: 422006889 | G71: 835 | H71: N | J71: {=IF($A71="","",IFERROR(_xlfn.XLOOKUP($A71,'Movimentação'!$B$7:$B$1006,'Movimentação'!$E$7:$E$1006,"",0,-1),""))} -> PJM | K71: {=IF($A71="","",IFERROR(_xlfn.XLOOKUP($A71,'Movimentação'!$B$7:$B$1006,'Movimentação'!$G$7:$G$1006,"",0,-1),""))} -> EICES | L71: FURTADO | N71: {=IF($A71="","",IFERROR(IF(OR($L71="BAIXADO",$L71="FURTADO"),0,INDEX(Listas!$J$2:$J$40,MATCH($B71,Listas!$I$2:$I$40,0))),""))} -> 0 | P71: {=IF($A71="","",IFERROR(_xlfn.XLOOKUP($A71,'Movimentação'!$B$7:$B$1006,'Movimentação'!$F$7:$F$1006,"",0,-1),""))} -> ENTRADA (NOVA) | Q71: =IF(COUNTIFS('Manutenção'!$B$7:$B$1006,$A71,'Manutenção'!$H$7:$H$1006,"EM CONSERTO")>0,1,0) -> 0
A72: LAS-07 | B72: LASER | C72: Laser | D72: DEWALT | E72: DW088CG-LA | F72: 69977 | G72: 770.52 | H72: N | J72: {=IF($A72="","",IFERROR(_xlfn.XLOOKUP($A72,'Movimentação'!$B$7:$B$1006,'Movimentação'!$E$7:$E$1006,"",0,-1),""))} -> SAMPA CONSOLAÇÃO | K72: {=IF($A72="","",IFERROR(_xlfn.XLOOKUP($A72,'Movimentação'!$B$7:$B$1006,'Movimentação'!$G$7:$G$1006,"",0,-1),""))} -> EICES | L72: =IF($A72="","",IF($Q72=1,"MANUTENÇÃO",IF($P72="BAIXA","BAIXADO",IF($P72="FURTO","FURTADO",IF($J72<>"","EM OBRA","PENDENTE-PROCURAR"))))) -> EM OBRA | N72: {=IF($A72="","",IFERROR(IF(OR($L72="BAIXADO",$L72="FURTADO"),0,INDEX(Listas!$J$2:$J$40,MATCH($B72,Listas!$I$2:$I$40,0))),""))} -> 200 | P72: {=IF($A72="","",IFERROR(_xlfn.XLOOKUP($A72,'Movimentação'!$B$7:$B$1006,'Movimentação'!$F$7:$F$1006,"",0,-1),""))} -> ENTRADA (NOVA) | Q72: =IF(COUNTIFS('Manutenção'!$B$7:$B$1006,$A72,'Manutenção'!$H$7:$H$1006,"EM CONSERTO")>0,1,0) -> 0
A73: LAS-08 | B73: LASER | C73: Laser | D73: DEWALT | E73: DW088CG-LA | F73: 72208 | G73: 770.52 | H73: N | J73: {=IF($A73="","",IFERROR(_xlfn.XLOOKUP($A73,'Movimentação'!$B$7:$B$1006,'Movimentação'!$E$7:$E$1006,"",0,-1),""))} -> ASSISTENCIA TECNICA | K73: {=IF($A73="","",IFERROR(_xlfn.XLOOKUP($A73,'Movimentação'!$B$7:$B$1006,'Movimentação'!$G$7:$G$1006,"",0,-1),""))} -> JOANDERSON | L73: =IF($A73="","",IF($Q73=1,"MANUTENÇÃO",IF($P73="BAIXA","BAIXADO",IF($P73="FURTO","FURTADO",IF($J73<>"","EM OBRA","PENDENTE-PROCURAR"))))) -> FURTADO | N73: {=IF($A73="","",IFERROR(IF(OR($L73="BAIXADO",$L73="FURTADO"),0,INDEX(Listas!$J$2:$J$40,MATCH($B73,Listas!$I$2:$I$40,0))),""))} -> 0 | P73: {=IF($A73="","",IFERROR(_xlfn.XLOOKUP($A73,'Movimentação'!$B$7:$B$1006,'Movimentação'!$F$7:$F$1006,"",0,-1),""))} -> FURTO | Q73: =IF(COUNTIFS('Manutenção'!$B$7:$B$1006,$A73,'Manutenção'!$H$7:$H$1006,"EM CONSERTO")>0,1,0) -> 0
A74: LAS-09 | B74: LASER | C74: Laser | D74: DEWALT | E74: DW088CG-LA | F74: 69978 | G74: 770.52 | H74: N | J74: {=IF($A74="","",IFERROR(_xlfn.XLOOKUP($A74,'Movimentação'!$B$7:$B$1006,'Movimentação'!$E$7:$E$1006,"",0,-1),""))} -> ASSISTENCIA TECNICA | K74: {=IF($A74="","",IFERROR(_xlfn.XLOOKUP($A74,'Movimentação'!$B$7:$B$1006,'Movimentação'!$G$7:$G$1006,"",0,-1),""))} -> EICES | L74: =IF($A74="","",IF($Q74=1,"MANUTENÇÃO",IF($P74="BAIXA","BAIXADO",IF($P74="FURTO","FURTADO",IF($J74<>"","EM OBRA","PENDENTE-PROCURAR"))))) -> BAIXADO | N74: {=IF($A74="","",IFERROR(IF(OR($L74="BAIXADO",$L74="FURTADO"),0,INDEX(Listas!$J$2:$J$40,MATCH($B74,Listas!$I$2:$I$40,0))),""))} -> 0 | P74: {=IF($A74="","",IFERROR(_xlfn.XLOOKUP($A74,'Movimentação'!$B$7:$B$1006,'Movimentação'!$F$7:$F$1006,"",0,-1),""))} -> BAIXA | Q74: =IF(COUNTIFS('Manutenção'!$B$7:$B$1006,$A74,'Manutenção'!$H$7:$H$1006,"EM CONSERTO")>0,1,0) -> 0
A75: LAS-10 | B75: LASER | C75: Laser | D75: DEWALT | E75: DW088CG-LA | F75: 72207 | G75: 770.52 | H75: N | J75: {=IF($A75="","",IFERROR(_xlfn.XLOOKUP($A75,'Movimentação'!$B$7:$B$1006,'Movimentação'!$E$7:$E$1006,"",0,-1),""))} -> MAURO | K75: {=IF($A75="","",IFERROR(_xlfn.XLOOKUP($A75,'Movimentação'!$B$7:$B$1006,'Movimentação'!$G$7:$G$1006,"",0,-1),""))} -> EICES | L75: =IF($A75="","",IF($Q75=1,"MANUTENÇÃO",IF($P75="BAIXA","BAIXADO",IF($P75="FURTO","FURTADO",IF($J75<>"","EM OBRA","PENDENTE-PROCURAR"))))) -> EM OBRA | N75: {=IF($A75="","",IFERROR(IF(OR($L75="BAIXADO",$L75="FURTADO"),0,INDEX(Listas!$J$2:$J$40,MATCH($B75,Listas!$I$2:$I$40,0))),""))} -> 200 | P75: {=IF($A75="","",IFERROR(_xlfn.XLOOKUP($A75,'Movimentação'!$B$7:$B$1006,'Movimentação'!$F$7:$F$1006,"",0,-1),""))} -> ENTRADA (NOVA) | Q75: =IF(COUNTIFS('Manutenção'!$B$7:$B$1006,$A75,'Manutenção'!$H$7:$H$1006,"EM CONSERTO")>0,1,0) -> 0
A76: PEZ-01 | B76: PERFURATRIZ | C76: Perfuratriz | D76: PLASTICON | E76: DIAMANTADA MANUAL | F76: 2022- 0000962 | G76: 2554 | H76: N | I76: 8869 | J76: {=IF($A76="","",IFERROR(_xlfn.XLOOKUP($A76,'Movimentação'!$B$7:$B$1006,'Movimentação'!$E$7:$E$1006,"",0,-1),""))} -> ASSISTENCIA TECNICA | K76: {=IF($A76="","",IFERROR(_xlfn.XLOOKUP($A76,'Movimentação'!$B$7:$B$1006,'Movimentação'!$G$7:$G$1006,"",0,-1),""))} -> EICES | L76: =IF($A76="","",IF($Q76=1,"MANUTENÇÃO",IF($P76="BAIXA","BAIXADO",IF($P76="FURTO","FURTADO",IF($J76<>"","EM OBRA","PENDENTE-PROCURAR"))))) -> BAIXADO | N76: {=IF($A76="","",IFERROR(IF(OR($L76="BAIXADO",$L76="FURTADO"),0,INDEX(Listas!$J$2:$J$40,MATCH($B76,Listas!$I$2:$I$40,0))),""))} -> 0 | P76: {=IF($A76="","",IFERROR(_xlfn.XLOOKUP($A76,'Movimentação'!$B$7:$B$1006,'Movimentação'!$F$7:$F$1006,"",0,-1),""))} -> BAIXA | Q76: =IF(COUNTIFS('Manutenção'!$B$7:$B$1006,$A76,'Manutenção'!$H$7:$H$1006,"EM CONSERTO")>0,1,0) -> 0
A77: PEZ-09 | B77: PERFURATRIZ | C77: Perfuratriz | D77: ARITA | E77: ENGINEERING DRILL 9130 | F77: 202504 00161 | G77: 2554 | H77: S | I77: 161 | J77: {=IF($A77="","",IFERROR(_xlfn.XLOOKUP($A77,'Movimentação'!$B$7:$B$1006,'Movimentação'!$E$7:$E$1006,"",0,-1),""))} -> ALTIER | K77: {=IF($A77="","",IFERROR(_xlfn.XLOOKUP($A77,'Movimentação'!$B$7:$B$1006,'Movimentação'!$G$7:$G$1006,"",0,-1),""))} -> EICES | L77: =IF($A77="","",IF($Q77=1,"MANUTENÇÃO",IF($P77="BAIXA","BAIXADO",IF($P77="FURTO","FURTADO",IF($J77<>"","EM OBRA","PENDENTE-PROCURAR"))))) -> EM OBRA | N77: {=IF($A77="","",IFERROR(IF(OR($L77="BAIXADO",$L77="FURTADO"),0,INDEX(Listas!$J$2:$J$40,MATCH($B77,Listas!$I$2:$I$40,0))),""))} -> 300 | P77: {=IF($A77="","",IFERROR(_xlfn.XLOOKUP($A77,'Movimentação'!$B$7:$B$1006,'Movimentação'!$F$7:$F$1006,"",0,-1),""))} -> ENTRADA (NOVA) | Q77: =IF(COUNTIFS('Manutenção'!$B$7:$B$1006,$A77,'Manutenção'!$H$7:$H$1006,"EM CONSERTO")>0,1,0) -> 0
A78: PEZ-03 | B78: PERFURATRIZ | C78: Perfuratriz | D78: PLASTICON | E78: DIAMANTADA MANUAL | F78: 2022-0000970 | G78: 2517.47 | H78: N | I78: 8912 | J78: {=IF($A78="","",IFERROR(_xlfn.XLOOKUP($A78,'Movimentação'!$B$7:$B$1006,'Movimentação'!$E$7:$E$1006,"",0,-1),""))} -> JERONIMO | K78: {=IF($A78="","",IFERROR(_xlfn.XLOOKUP($A78,'Movimentação'!$B$7:$B$1006,'Movimentação'!$G$7:$G$1006,"",0,-1),""))} -> ANA | L78: =IF($A78="","",IF($Q78=1,"MANUTENÇÃO",IF($P78="BAIXA","BAIXADO",IF($P78="FURTO","FURTADO",IF($J78<>"","EM OBRA","PENDENTE-PROCURAR"))))) -> EM OBRA | N78: {=IF($A78="","",IFERROR(IF(OR($L78="BAIXADO",$L78="FURTADO"),0,INDEX(Listas!$J$2:$J$40,MATCH($B78,Listas!$I$2:$I$40,0))),""))} -> 300 | P78: {=IF($A78="","",IFERROR(_xlfn.XLOOKUP($A78,'Movimentação'!$B$7:$B$1006,'Movimentação'!$F$7:$F$1006,"",0,-1),""))} -> TRANSFERÊNCIA | Q78: =IF(COUNTIFS('Manutenção'!$B$7:$B$1006,$A78,'Manutenção'!$H$7:$H$1006,"EM CONSERTO")>0,1,0) -> 0
A79: PEZ-08 | B79: PERFURATRIZ | C79: Perfuratriz | D79: ARITA | E79: ENGINEERING DRILL 9130 | F79: 202504 00485 | G79: 2554 | H79: S | I79: 485 | J79: {=IF($A79="","",IFERROR(_xlfn.XLOOKUP($A79,'Movimentação'!$B$7:$B$1006,'Movimentação'!$E$7:$E$1006,"",0,-1),""))} -> MAURO | K79: {=IF($A79="","",IFERROR(_xlfn.XLOOKUP($A79,'Movimentação'!$B$7:$B$1006,'Movimentação'!$G$7:$G$1006,"",0,-1),""))} -> JUNIOR | L79: =IF($A79="","",IF($Q79=1,"MANUTENÇÃO",IF($P79="BAIXA","BAIXADO",IF($P79="FURTO","FURTADO",IF($J79<>"","EM OBRA","PENDENTE-PROCURAR"))))) -> EM OBRA | N79: {=IF($A79="","",IFERROR(IF(OR($L79="BAIXADO",$L79="FURTADO"),0,INDEX(Listas!$J$2:$J$40,MATCH($B79,Listas!$I$2:$I$40,0))),""))} -> 300 | P79: {=IF($A79="","",IFERROR(_xlfn.XLOOKUP($A79,'Movimentação'!$B$7:$B$1006,'Movimentação'!$F$7:$F$1006,"",0,-1),""))} -> TRANSFERÊNCIA | Q79: =IF(COUNTIFS('Manutenção'!$B$7:$B$1006,$A79,'Manutenção'!$H$7:$H$1006,"EM CONSERTO")>0,1,0) -> 0
A80: PEZ-05 | B80: PERFURATRIZ | C80: Perfuratriz | D80: PLASTICON | E80: DIAMANTADA MANUAL | F80: 2022-0000950 | G80: 2554 | H80: N | J80: {=IF($A80="","",IFERROR(_xlfn.XLOOKUP($A80,'Movimentação'!$B$7:$B$1006,'Movimentação'!$E$7:$E$1006,"",0,-1),""))} | K80: {=IF($A80="","",IFERROR(_xlfn.XLOOKUP($A80,'Movimentação'!$B$7:$B$1006,'Movimentação'!$G$7:$G$1006,"",0,-1),""))} | L80: =IF($A80="","",IF($Q80=1,"MANUTENÇÃO",IF($P80="BAIXA","BAIXADO",IF($P80="FURTO","FURTADO",IF($J80<>"","EM OBRA","PENDENTE-PROCURAR"))))) -> PENDENTE-PROCURAR | N80: {=IF($A80="","",IFERROR(IF(OR($L80="BAIXADO",$L80="FURTADO"),0,INDEX(Listas!$J$2:$J$40,MATCH($B80,Listas!$I$2:$I$40,0))),""))} -> 300 | P80: {=IF($A80="","",IFERROR(_xlfn.XLOOKUP($A80,'Movimentação'!$B$7:$B$1006,'Movimentação'!$F$7:$F$1006,"",0,-1),""))} | Q80: =IF(COUNTIFS('Manutenção'!$B$7:$B$1006,$A80,'Manutenção'!$H$7:$H$1006,"EM CONSERTO")>0,1,0) -> 0
A81: PEZ-06 | B81: PERFURATRIZ | C81: Perfuratriz | D81: PLASTICON | E81: DIAMANTADA MANUAL | F81: 2023-00001025 | G81: 2554 | H81: N | I81: 9525 | J81: {=IF($A81="","",IFERROR(_xlfn.XLOOKUP($A81,'Movimentação'!$B$7:$B$1006,'Movimentação'!$E$7:$E$1006,"",0,-1),""))} | K81: {=IF($A81="","",IFERROR(_xlfn.XLOOKUP($A81,'Movimentação'!$B$7:$B$1006,'Movimentação'!$G$7:$G$1006,"",0,-1),""))} | L81: =IF($A81="","",IF($Q81=1,"MANUTENÇÃO",IF($P81="BAIXA","BAIXADO",IF($P81="FURTO","FURTADO",IF($J81<>"","EM OBRA","PENDENTE-PROCURAR"))))) -> PENDENTE-PROCURAR | N81: {=IF($A81="","",IFERROR(IF(OR($L81="BAIXADO",$L81="FURTADO"),0,INDEX(Listas!$J$2:$J$40,MATCH($B81,Listas!$I$2:$I$40,0))),""))} -> 300 | P81: {=IF($A81="","",IFERROR(_xlfn.XLOOKUP($A81,'Movimentação'!$B$7:$B$1006,'Movimentação'!$F$7:$F$1006,"",0,-1),""))} | Q81: =IF(COUNTIFS('Manutenção'!$B$7:$B$1006,$A81,'Manutenção'!$H$7:$H$1006,"EM CONSERTO")>0,1,0) -> 0
A82: PEZ-10 | B82: PERFURATRIZ | C82: Perfuratriz | D82: ARITA | E82: ENGINEERING DRILL 9130 | F82: 202504 00697 | G82: 2554 | H82: S | I82: 697 | J82: {=IF($A82="","",IFERROR(_xlfn.XLOOKUP($A82,'Movimentação'!$B$7:$B$1006,'Movimentação'!$E$7:$E$1006,"",0,-1),""))} -> ANGELICA | K82: {=IF($A82="","",IFERROR(_xlfn.XLOOKUP($A82,'Movimentação'!$B$7:$B$1006,'Movimentação'!$G$7:$G$1006,"",0,-1),""))} -> THIAGO | L82: =IF($A82="","",IF($Q82=1,"MANUTENÇÃO",IF($P82="BAIXA","BAIXADO",IF($P82="FURTO","FURTADO",IF($J82<>"","EM OBRA","PENDENTE-PROCURAR"))))) -> EM OBRA | N82: {=IF($A82="","",IFERROR(IF(OR($L82="BAIXADO",$L82="FURTADO"),0,INDEX(Listas!$J$2:$J$40,MATCH($B82,Listas!$I$2:$I$40,0))),""))} -> 300 | P82: {=IF($A82="","",IFERROR(_xlfn.XLOOKUP($A82,'Movimentação'!$B$7:$B$1006,'Movimentação'!$F$7:$F$1006,"",0,-1),""))} -> TRANSFERÊNCIA | Q82: =IF(COUNTIFS('Manutenção'!$B$7:$B$1006,$A82,'Manutenção'!$H$7:$H$1006,"EM CONSERTO")>0,1,0) -> 0
A83: PEZ-02 | B83: PERFURATRIZ | C83: Perfuratriz | D83: PLASTICON | E83: DIAMANTADA MANUAL | F83: 2022-0000961 | G83: 2517.47 | H83: N | I83: 8869 | J83: {=IF($A83="","",IFERROR(_xlfn.XLOOKUP($A83,'Movimentação'!$B$7:$B$1006,'Movimentação'!$E$7:$E$1006,"",0,-1),""))} -> ORIÇANGA | K83: LEONARDO | L83: =IF($A83="","",IF($Q83=1,"MANUTENÇÃO",IF($P83="BAIXA","BAIXADO",IF($P83="FURTO","FURTADO",IF($J83<>"","EM OBRA","PENDENTE-PROCURAR"))))) -> EM OBRA | N83: {=IF($A83="","",IFERROR(IF(OR($L83="BAIXADO",$L83="FURTADO"),0,INDEX(Listas!$J$2:$J$40,MATCH($B83,Listas!$I$2:$I$40,0))),""))} -> 300 | P83: {=IF($A83="","",IFERROR(_xlfn.XLOOKUP($A83,'Movimentação'!$B$7:$B$1006,'Movimentação'!$F$7:$F$1006,"",0,-1),""))} -> ENTRADA (NOVA) | Q83: =IF(COUNTIFS('Manutenção'!$B$7:$B$1006,$A83,'Manutenção'!$H$7:$H$1006,"EM CONSERTO")>0,1,0) -> 0
A84: PEZ-11 | B84: PERFURATRIZ | C84: Perfuratriz | D84: ARITA | E84: ENGINEERING DRILL 9130 | F84: 02504 00314 | G84: 2554 | H84: S | I84: 314 | J84: {=IF($A84="","",IFERROR(_xlfn.XLOOKUP($A84,'Movimentação'!$B$7:$B$1006,'Movimentação'!$E$7:$E$1006,"",0,-1),""))} -> SAMPA CONSOLAÇÃO | K84: TIAGO | L84: =IF($A84="","",IF($Q84=1,"MANUTENÇÃO",IF($P84="BAIXA","BAIXADO",IF($P84="FURTO","FURTADO",IF($J84<>"","EM OBRA","PENDENTE-PROCURAR"))))) -> EM OBRA | N84: {=IF($A84="","",IFERROR(IF(OR($L84="BAIXADO",$L84="FURTADO"),0,INDEX(Listas!$J$2:$J$40,MATCH($B84,Listas!$I$2:$I$40,0))),""))} -> 300 | P84: {=IF($A84="","",IFERROR(_xlfn.XLOOKUP($A84,'Movimentação'!$B$7:$B$1006,'Movimentação'!$F$7:$F$1006,"",0,-1),""))} -> TRANSFERÊNCIA | Q84: =IF(COUNTIFS('Manutenção'!$B$7:$B$1006,$A84,'Manutenção'!$H$7:$H$1006,"EM CONSERTO")>0,1,0) -> 0
A85: PEZ-07 | B85: PERFURATRIZ | C85: Perfuratriz | D85: PLASTICON | E85: DIAMANTADA MANUAL | F85: 2023-00001063 | G85: 2554 | H85: N | I85: 9980 | J85: {=IF($A85="","",IFERROR(_xlfn.XLOOKUP($A85,'Movimentação'!$B$7:$B$1006,'Movimentação'!$E$7:$E$1006,"",0,-1),""))} -> PJM | K85: CAMILA | L85: =IF($A85="","",IF($Q85=1,"MANUTENÇÃO",IF($P85="BAIXA","BAIXADO",IF($P85="FURTO","FURTADO",IF($J85<>"","EM OBRA","PENDENTE-PROCURAR"))))) -> EM OBRA | N85: {=IF($A85="","",IFERROR(IF(OR($L85="BAIXADO",$L85="FURTADO"),0,INDEX(Listas!$J$2:$J$40,MATCH($B85,Listas!$I$2:$I$40,0))),""))} -> 300 | P85: {=IF($A85="","",IFERROR(_xlfn.XLOOKUP($A85,'Movimentação'!$B$7:$B$1006,'Movimentação'!$F$7:$F$1006,"",0,-1),""))} -> TRANSFERÊNCIA | Q85: =IF(COUNTIFS('Manutenção'!$B$7:$B$1006,$A85,'Manutenção'!$H$7:$H$1006,"EM CONSERTO")>0,1,0) -> 0
A86: PEZ-04 | B86: PERFURATRIZ | C86: Perfuratriz | D86: PLASTICON | E86: DIAMANTADA MANUAL | F86: 2023-00001024 | G86: 2517.47 | H86: N | I86: 9525 | J86: {=IF($A86="","",IFERROR(_xlfn.XLOOKUP($A86,'Movimentação'!$B$7:$B$1006,'Movimentação'!$E$7:$E$1006,"",0,-1),""))} -> SAMPA CONSOLAÇÃO | K86: TIAGO | L86: =IF($A86="","",IF($Q86=1,"MANUTENÇÃO",IF($P86="BAIXA","BAIXADO",IF($P86="FURTO","FURTADO",IF($J86<>"","EM OBRA","PENDENTE-PROCURAR"))))) -> EM OBRA | N86: {=IF($A86="","",IFERROR(IF(OR($L86="BAIXADO",$L86="FURTADO"),0,INDEX(Listas!$J$2:$J$40,MATCH($B86,Listas!$I$2:$I$40,0))),""))} -> 300 | P86: {=IF($A86="","",IFERROR(_xlfn.XLOOKUP($A86,'Movimentação'!$B$7:$B$1006,'Movimentação'!$F$7:$F$1006,"",0,-1),""))} -> ENTRADA (NOVA) | Q86: =IF(COUNTIFS('Manutenção'!$B$7:$B$1006,$A86,'Manutenção'!$H$7:$H$1006,"EM CONSERTO")>0,1,0) -> 0
A87: PEZ-12 | B87: PERFURATRIZ | C87: Perfuratriz | D87: ??? | E87: ??? | F87: 28382 | G87: 2554 | H87: S | J87: {=IF($A87="","",IFERROR(_xlfn.XLOOKUP($A87,'Movimentação'!$B$7:$B$1006,'Movimentação'!$E$7:$E$1006,"",0,-1),""))} -> MANUTENÇÃO | K87: {=IF($A87="","",IFERROR(_xlfn.XLOOKUP($A87,'Movimentação'!$B$7:$B$1006,'Movimentação'!$G$7:$G$1006,"",0,-1),""))} -> LAÉRCIO | L87: =IF($A87="","",IF($Q87=1,"MANUTENÇÃO",IF($P87="BAIXA","BAIXADO",IF($P87="FURTO","FURTADO",IF($J87<>"","EM OBRA","PENDENTE-PROCURAR"))))) -> MANUTENÇÃO | N87: {=IF($A87="","",IFERROR(IF(OR($L87="BAIXADO",$L87="FURTADO"),0,INDEX(Listas!$J$2:$J$40,MATCH($B87,Listas!$I$2:$I$40,0))),""))} -> 300 | P87: {=IF($A87="","",IFERROR(_xlfn.XLOOKUP($A87,'Movimentação'!$B$7:$B$1006,'Movimentação'!$F$7:$F$1006,"",0,-1),""))} -> ENVIO P/ MANUTENÇÃO | Q87: =IF(COUNTIFS('Manutenção'!$B$7:$B$1006,$A87,'Manutenção'!$H$7:$H$1006,"EM CONSERTO")>0,1,0) -> 1
A88: MOR-01 | B88: MORSA | C88: Morsa | D88: SOMAR | E88: NR 8 SOMAR | F88: SOMAR LIDER | G88: 449.66 | H88: N | I88: 1051559 | J88: {=IF($A88="","",IFERROR(_xlfn.XLOOKUP($A88,'Movimentação'!$B$7:$B$1006,'Movimentação'!$E$7:$E$1006,"",0,-1),""))} -> MAURO | K88: TAYANE | L88: =IF($A88="","",IF($Q88=1,"MANUTENÇÃO",IF($P88="BAIXA","BAIXADO",IF($P88="FURTO","FURTADO",IF($J88<>"","EM OBRA","PENDENTE-PROCURAR"))))) -> EM OBRA | N88: {=IF($A88="","",IFERROR(IF(OR($L88="BAIXADO",$L88="FURTADO"),0,INDEX(Listas!$J$2:$J$40,MATCH($B88,Listas!$I$2:$I$40,0))),""))} -> 50 | P88: {=IF($A88="","",IFERROR(_xlfn.XLOOKUP($A88,'Movimentação'!$B$7:$B$1006,'Movimentação'!$F$7:$F$1006,"",0,-1),""))} -> ENTRADA (NOVA) | Q88: =IF(COUNTIFS('Manutenção'!$B$7:$B$1006,$A88,'Manutenção'!$H$7:$H$1006,"EM CONSERTO")>0,1,0) -> 0
A89: MOR-02 | B89: MORSA | C89: Morsa | D89: VONDER | F89: VONDER | G89: 800 | H89: N | I89: S/NF | J89: {=IF($A89="","",IFERROR(_xlfn.XLOOKUP($A89,'Movimentação'!$B$7:$B$1006,'Movimentação'!$E$7:$E$1006,"",0,-1),""))} -> PJM | K89: CAMILA | L89: =IF($A89="","",IF($Q89=1,"MANUTENÇÃO",IF($P89="BAIXA","BAIXADO",IF($P89="FURTO","FURTADO",IF($J89<>"","EM OBRA","PENDENTE-PROCURAR"))))) -> EM OBRA | N89: {=IF($A89="","",IFERROR(IF(OR($L89="BAIXADO",$L89="FURTADO"),0,INDEX(Listas!$J$2:$J$40,MATCH($B89,Listas!$I$2:$I$40,0))),""))} -> 50 | P89: {=IF($A89="","",IFERROR(_xlfn.XLOOKUP($A89,'Movimentação'!$B$7:$B$1006,'Movimentação'!$F$7:$F$1006,"",0,-1),""))} -> TRANSFERÊNCIA | Q89: =IF(COUNTIFS('Manutenção'!$B$7:$B$1006,$A89,'Manutenção'!$H$7:$H$1006,"EM CONSERTO")>0,1,0) -> 0
A90: TER-01 | B90: TERMOFUSOR | C90: Termofusor | D90: BUTT FUSION | F90: ZRJQ-63 | G90: 1220 | H90: N | J90: {=IF($A90="","",IFERROR(_xlfn.XLOOKUP($A90,'Movimentação'!$B$7:$B$1006,'Movimentação'!$E$7:$E$1006,"",0,-1),""))} -> ALPHA ONE | K90: {=IF($A90="","",IFERROR(_xlfn.XLOOKUP($A90,'Movimentação'!$B$7:$B$1006,'Movimentação'!$G$7:$G$1006,"",0,-1),""))} -> EICES | L90: =IF($A90="","",IF($Q90=1,"MANUTENÇÃO",IF($P90="BAIXA","BAIXADO",IF($P90="FURTO","FURTADO",IF($J90<>"","EM OBRA","PENDENTE-PROCURAR"))))) -> BAIXADO | N90: {=IF($A90="","",IFERROR(IF(OR($L90="BAIXADO",$L90="FURTADO"),0,INDEX(Listas!$J$2:$J$40,MATCH($B90,Listas!$I$2:$I$40,0))),""))} -> 0 | P90: {=IF($A90="","",IFERROR(_xlfn.XLOOKUP($A90,'Movimentação'!$B$7:$B$1006,'Movimentação'!$F$7:$F$1006,"",0,-1),""))} -> BAIXA | Q90: =IF(COUNTIFS('Manutenção'!$B$7:$B$1006,$A90,'Manutenção'!$H$7:$H$1006,"EM CONSERTO")>0,1,0) -> 0
A91: TER-02 | B91: TERMOFUSOR | C91: Termofusor | D91: TOPFUSION | E91: GRANDE RPC | F91: TF0129 | G91: 963.8 | H91: N | J91: {=IF($A91="","",IFERROR(_xlfn.XLOOKUP($A91,'Movimentação'!$B$7:$B$1006,'Movimentação'!$E$7:$E$1006,"",0,-1),""))} -> ASSISTENCIA TECNICA | K91: {=IF($A91="","",IFERROR(_xlfn.XLOOKUP($A91,'Movimentação'!$B$7:$B$1006,'Movimentação'!$G$7:$G$1006,"",0,-1),""))} -> LAÉRCIO | L91: =IF($A91="","",IF($Q91=1,"MANUTENÇÃO",IF($P91="BAIXA","BAIXADO",IF($P91="FURTO","FURTADO",IF($J91<>"","EM OBRA","PENDENTE-PROCURAR"))))) -> BAIXADO | N91: {=IF($A91="","",IFERROR(IF(OR($L91="BAIXADO",$L91="FURTADO"),0,INDEX(Listas!$J$2:$J$40,MATCH($B91,Listas!$I$2:$I$40,0))),""))} -> 0 | P91: {=IF($A91="","",IFERROR(_xlfn.XLOOKUP($A91,'Movimentação'!$B$7:$B$1006,'Movimentação'!$F$7:$F$1006,"",0,-1),""))} -> BAIXA | Q91: =IF(COUNTIFS('Manutenção'!$B$7:$B$1006,$A91,'Manutenção'!$H$7:$H$1006,"EM CONSERTO")>0,1,0) -> 0
A92: TER-03 | B92: TERMOFUSOR | C92: Termofusor | D92: TOPFUSION | E92: GRANDE RPC | F92: TF00027 | G92: 919.28 | H92: N | I92: 30789 | J92: {=IF($A92="","",IFERROR(_xlfn.XLOOKUP($A92,'Movimentação'!$B$7:$B$1006,'Movimentação'!$E$7:$E$1006,"",0,-1),""))} -> MAURO | K92: TAYANE | L92: =IF($A92="","",IF($Q92=1,"MANUTENÇÃO",IF($P92="BAIXA","BAIXADO",IF($P92="FURTO","FURTADO",IF($J92<>"","EM OBRA","PENDENTE-PROCURAR"))))) -> EM OBRA | N92: {=IF($A92="","",IFERROR(IF(OR($L92="BAIXADO",$L92="FURTADO"),0,INDEX(Listas!$J$2:$J$40,MATCH($B92,Listas!$I$2:$I$40,0))),""))} -> 200 | P92: {=IF($A92="","",IFERROR(_xlfn.XLOOKUP($A92,'Movimentação'!$B$7:$B$1006,'Movimentação'!$F$7:$F$1006,"",0,-1),""))} -> TRANSFERÊNCIA | Q92: =IF(COUNTIFS('Manutenção'!$B$7:$B$1006,$A92,'Manutenção'!$H$7:$H$1006,"EM CONSERTO")>0,1,0) -> 0
A93: TER-04 | B93: TERMOFUSOR | C93: Termofusor | D93: TOPFUSION | E93: PEQUENO RPC | F93: TF00342 | G93: 674.6 | H93: N | I93: 30789 | J93: {=IF($A93="","",IFERROR(_xlfn.XLOOKUP($A93,'Movimentação'!$B$7:$B$1006,'Movimentação'!$E$7:$E$1006,"",0,-1),""))} -> SAMPA CONSOLAÇÃO | K93: TIAGO | L93: =IF($A93="","",IF($Q93=1,"MANUTENÇÃO",IF($P93="BAIXA","BAIXADO",IF($P93="FURTO","FURTADO",IF($J93<>"","EM OBRA","PENDENTE-PROCURAR"))))) -> EM OBRA | N93: {=IF($A93="","",IFERROR(IF(OR($L93="BAIXADO",$L93="FURTADO"),0,INDEX(Listas!$J$2:$J$40,MATCH($B93,Listas!$I$2:$I$40,0))),""))} -> 200 | P93: {=IF($A93="","",IFERROR(_xlfn.XLOOKUP($A93,'Movimentação'!$B$7:$B$1006,'Movimentação'!$F$7:$F$1006,"",0,-1),""))} -> ENTRADA (NOVA) | Q93: =IF(COUNTIFS('Manutenção'!$B$7:$B$1006,$A93,'Manutenção'!$H$7:$H$1006,"EM CONSERTO")>0,1,0) -> 0
A94: TER-05 | B94: TERMOFUSOR | C94: Termofusor | D94: TOPFUSION | E94: PEQUENO RPC | F94: TF00343 | G94: 674.6 | H94: N | J94: {=IF($A94="","",IFERROR(_xlfn.XLOOKUP($A94,'Movimentação'!$B$7:$B$1006,'Movimentação'!$E$7:$E$1006,"",0,-1),""))} -> TANABI | K94: CAMILA | L94: =IF($A94="","",IF($Q94=1,"MANUTENÇÃO",IF($P94="BAIXA","BAIXADO",IF($P94="FURTO","FURTADO",IF($J94<>"","EM OBRA","PENDENTE-PROCURAR"))))) -> EM OBRA | N94: {=IF($A94="","",IFERROR(IF(OR($L94="BAIXADO",$L94="FURTADO"),0,INDEX(Listas!$J$2:$J$40,MATCH($B94,Listas!$I$2:$I$40,0))),""))} -> 200 | P94: {=IF($A94="","",IFERROR(_xlfn.XLOOKUP($A94,'Movimentação'!$B$7:$B$1006,'Movimentação'!$F$7:$F$1006,"",0,-1),""))} -> TRANSFERÊNCIA | Q94: =IF(COUNTIFS('Manutenção'!$B$7:$B$1006,$A94,'Manutenção'!$H$7:$H$1006,"EM CONSERTO")>0,1,0) -> 0
A95: TER-06 | B95: TERMOFUSOR | C95: Termofusor | D95: TOPFUSION | E95: PEQUENO RPC | G95: 674.6 | H95: N | J95: {=IF($A95="","",IFERROR(_xlfn.XLOOKUP($A95,'Movimentação'!$B$7:$B$1006,'Movimentação'!$E$7:$E$1006,"",0,-1),""))} -> ASSISTENCIA TECNICA | K95: TIAGO | L95: =IF($A95="","",IF($Q95=1,"MANUTENÇÃO",IF($P95="BAIXA","BAIXADO",IF($P95="FURTO","FURTADO",IF($J95<>"","EM OBRA","PENDENTE-PROCURAR"))))) -> BAIXADO | N95: {=IF($A95="","",IFERROR(IF(OR($L95="BAIXADO",$L95="FURTADO"),0,INDEX(Listas!$J$2:$J$40,MATCH($B95,Listas!$I$2:$I$40,0))),""))} -> 0 | P95: {=IF($A95="","",IFERROR(_xlfn.XLOOKUP($A95,'Movimentação'!$B$7:$B$1006,'Movimentação'!$F$7:$F$1006,"",0,-1),""))} -> BAIXA | Q95: =IF(COUNTIFS('Manutenção'!$B$7:$B$1006,$A95,'Manutenção'!$H$7:$H$1006,"EM CONSERTO")>0,1,0) -> 0
A96: SOP-01 | B96: SOPRADOR | C96: Soprador | D96: BLACK DECKER | F96: HG2000-B2 | G96: 285.9 | H96: N | J96: {=IF($A96="","",IFERROR(_xlfn.XLOOKUP($A96,'Movimentação'!$B$7:$B$1006,'Movimentação'!$E$7:$E$1006,"",0,-1),""))} | K96: {=IF($A96="","",IFERROR(_xlfn.XLOOKUP($A96,'Movimentação'!$B$7:$B$1006,'Movimentação'!$G$7:$G$1006,"",0,-1),""))} | L96: =IF($A96="","",IF($Q96=1,"MANUTENÇÃO",IF($P96="BAIXA","BAIXADO",IF($P96="FURTO","FURTADO",IF($J96<>"","EM OBRA","PENDENTE-PROCURAR"))))) -> PENDENTE-PROCURAR | N96: {=IF($A96="","",IFERROR(IF(OR($L96="BAIXADO",$L96="FURTADO"),0,INDEX(Listas!$J$2:$J$40,MATCH($B96,Listas!$I$2:$I$40,0))),""))} -> 100 | P96: {=IF($A96="","",IFERROR(_xlfn.XLOOKUP($A96,'Movimentação'!$B$7:$B$1006,'Movimentação'!$F$7:$F$1006,"",0,-1),""))} | Q96: =IF(COUNTIFS('Manutenção'!$B$7:$B$1006,$A96,'Manutenção'!$H$7:$H$1006,"EM CONSERTO")>0,1,0) -> 0
A97: SOP-02 | B97: SOPRADOR | C97: Soprador | D97: BLACK DECKER | F97: HG2000-B2 | G97: 285.9 | H97: N | J97: {=IF($A97="","",IFERROR(_xlfn.XLOOKUP($A97,'Movimentação'!$B$7:$B$1006,'Movimentação'!$E$7:$E$1006,"",0,-1),""))} -> PJM | K97: {=IF($A97="","",IFERROR(_xlfn.XLOOKUP($A97,'Movimentação'!$B$7:$B$1006,'Movimentação'!$G$7:$G$1006,"",0,-1),""))} -> CAMILA | L97: =IF($A97="","",IF($Q97=1,"MANUTENÇÃO",IF($P97="BAIXA","BAIXADO",IF($P97="FURTO","FURTADO",IF($J97<>"","EM OBRA","PENDENTE-PROCURAR"))))) -> EM OBRA | N97: {=IF($A97="","",IFERROR(IF(OR($L97="BAIXADO",$L97="FURTADO"),0,INDEX(Listas!$J$2:$J$40,MATCH($B97,Listas!$I$2:$I$40,0))),""))} -> 100 | P97: {=IF($A97="","",IFERROR(_xlfn.XLOOKUP($A97,'Movimentação'!$B$7:$B$1006,'Movimentação'!$F$7:$F$1006,"",0,-1),""))} -> TRANSFERÊNCIA | Q97: =IF(COUNTIFS('Manutenção'!$B$7:$B$1006,$A97,'Manutenção'!$H$7:$H$1006,"EM CONSERTO")>0,1,0) -> 0
A98: VAZ-01 | B98: VAZADOR | C98: Vazador | D98: WALSYWA | E98: PUNCIONADOR DE METAL | G98: 1601.43 | H98: N | I98: 65016 | J98: {=IF($A98="","",IFERROR(_xlfn.XLOOKUP($A98,'Movimentação'!$B$7:$B$1006,'Movimentação'!$E$7:$E$1006,"",0,-1),""))} -> BALTAZAR | K98: GEORGE | L98: =IF($A98="","",IF($Q98=1,"MANUTENÇÃO",IF($P98="BAIXA","BAIXADO",IF($P98="FURTO","FURTADO",IF($J98<>"","EM OBRA","PENDENTE-PROCURAR"))))) -> EM OBRA | N98: {=IF($A98="","",IFERROR(IF(OR($L98="BAIXADO",$L98="FURTADO"),0,INDEX(Listas!$J$2:$J$40,MATCH($B98,Listas!$I$2:$I$40,0))),""))} -> 300 | P98: {=IF($A98="","",IFERROR(_xlfn.XLOOKUP($A98,'Movimentação'!$B$7:$B$1006,'Movimentação'!$F$7:$F$1006,"",0,-1),""))} -> ENTRADA (NOVA) | Q98: =IF(COUNTIFS('Manutenção'!$B$7:$B$1006,$A98,'Manutenção'!$H$7:$H$1006,"EM CONSERTO")>0,1,0) -> 0
A99: VAZ-02 | B99: VAZADOR | C99: Vazador | D99: WALSYWA | E99: PUNCIONADOR DE METAL | G99: 1735.22 | H99: N | I99: 25756 | J99: {=IF($A99="","",IFERROR(_xlfn.XLOOKUP($A99,'Movimentação'!$B$7:$B$1006,'Movimentação'!$E$7:$E$1006,"",0,-1),""))} -> ESCRITÓRIO | K99: GEORGE | L99: =IF($A99="","",IF($Q99=1,"MANUTENÇÃO",IF($P99="BAIXA","BAIXADO",IF($P99="FURTO","FURTADO",IF($J99<>"","EM OBRA","PENDENTE-PROCURAR"))))) -> EM OBRA | N99: {=IF($A99="","",IFERROR(IF(OR($L99="BAIXADO",$L99="FURTADO"),0,INDEX(Listas!$J$2:$J$40,MATCH($B99,Listas!$I$2:$I$40,0))),""))} -> 300 | P99: {=IF($A99="","",IFERROR(_xlfn.XLOOKUP($A99,'Movimentação'!$B$7:$B$1006,'Movimentação'!$F$7:$F$1006,"",0,-1),""))} -> ENTRADA (NOVA) | Q99: =IF(COUNTIFS('Manutenção'!$B$7:$B$1006,$A99,'Manutenção'!$H$7:$H$1006,"EM CONSERTO")>0,1,0) -> 0
A100: PFP-01 | B100: PISTOLA FINCA PINO | C100: Pistola Finca Pino | D100: ANCORA | E100: FAI72N | F100: ANCORA | G100: 832.07 | H100: N | I100: 387327 | J100: {=IF($A100="","",IFERROR(_xlfn.XLOOKUP($A100,'Movimentação'!$B$7:$B$1006,'Movimentação'!$E$7:$E$1006,"",0,-1),""))} -> ASSISTENCIA TECNICA | K100: {=IF($A100="","",IFERROR(_xlfn.XLOOKUP($A100,'Movimentação'!$B$7:$B$1006,'Movimentação'!$G$7:$G$1006,"",0,-1),""))} -> EICES | L100: =IF($A100="","",IF($Q100=1,"MANUTENÇÃO",IF($P100="BAIXA","BAIXADO",IF($P100="FURTO","FURTADO",IF($J100<>"","EM OBRA","PENDENTE-PROCURAR"))))) -> BAIXADO | N100: {=IF($A100="","",IFERROR(IF(OR($L100="BAIXADO",$L100="FURTADO"),0,INDEX(Listas!$J$2:$J$40,MATCH($B100,Listas!$I$2:$I$40,0))),""))} -> 0 | P100: {=IF($A100="","",IFERROR(_xlfn.XLOOKUP($A100,'Movimentação'!$B$7:$B$1006,'Movimentação'!$F$7:$F$1006,"",0,-1),""))} -> BAIXA | Q100: =IF(COUNTIFS('Manutenção'!$B$7:$B$1006,$A100,'Manutenção'!$H$7:$H$1006,"EM CONSERTO")>0,1,0) -> 0
A101: PFP-02 | B101: PISTOLA FINCA PINO | C101: Pistola Finca Pino | D101: ANCORA | E101: FAI72N | F101: ANCORA | G101: 832.07 | H101: N | I101: 387327 | J101: ASSISTENCIA TECNICA | K101: {=IF($A101="","",IFERROR(_xlfn.XLOOKUP($A101,'Movimentação'!$B$7:$B$1006,'Movimentação'!$G$7:$G$1006,"",0,-1),""))} -> EICES | L101: =IF($A101="","",IF($Q101=1,"MANUTENÇÃO",IF($P101="BAIXA","BAIXADO",IF($P101="FURTO","FURTADO",IF($J101<>"","EM OBRA","PENDENTE-PROCURAR"))))) -> BAIXADO | N101: {=IF($A101="","",IFERROR(IF(OR($L101="BAIXADO",$L101="FURTADO"),0,INDEX(Listas!$J$2:$J$40,MATCH($B101,Listas!$I$2:$I$40,0))),""))} -> 0 | P101: {=IF($A101="","",IFERROR(_xlfn.XLOOKUP($A101,'Movimentação'!$B$7:$B$1006,'Movimentação'!$F$7:$F$1006,"",0,-1),""))} -> BAIXA | Q101: =IF(COUNTIFS('Manutenção'!$B$7:$B$1006,$A101,'Manutenção'!$H$7:$H$1006,"EM CONSERTO")>0,1,0) -> 0
A102: PFP-03 | B102: PISTOLA FINCA PINO | C102: Pistola Finca Pino | D102: ANCORA | E102: FAI72N | F102: ANCORA | G102: 832.07 | H102: N | I102: 387327 | J102: ASSISTENCIA TECNICA | K102: {=IF($A102="","",IFERROR(_xlfn.XLOOKUP($A102,'Movimentação'!$B$7:$B$1006,'Movimentação'!$G$7:$G$1006,"",0,-1),""))} -> EICES | L102: =IF($A102="","",IF($Q102=1,"MANUTENÇÃO",IF($P102="BAIXA","BAIXADO",IF($P102="FURTO","FURTADO",IF($J102<>"","EM OBRA","PENDENTE-PROCURAR"))))) -> BAIXADO | N102: {=IF($A102="","",IFERROR(IF(OR($L102="BAIXADO",$L102="FURTADO"),0,INDEX(Listas!$J$2:$J$40,MATCH($B102,Listas!$I$2:$I$40,0))),""))} -> 0 | P102: {=IF($A102="","",IFERROR(_xlfn.XLOOKUP($A102,'Movimentação'!$B$7:$B$1006,'Movimentação'!$F$7:$F$1006,"",0,-1),""))} -> BAIXA | Q102: =IF(COUNTIFS('Manutenção'!$B$7:$B$1006,$A102,'Manutenção'!$H$7:$H$1006,"EM CONSERTO")>0,1,0) -> 0
A103: PFP-04 | B103: PISTOLA FINCA PINO | C103: Pistola Finca Pino | D103: WALSYWA | E103: CALIBRE 27 PRA 10 | F103: WALSYWA | G103: 1000 | H103: N | I103: 25756 | J103: ASSISTENCIA TECNICA | K103: {=IF($A103="","",IFERROR(_xlfn.XLOOKUP($A103,'Movimentação'!$B$7:$B$1006,'Movimentação'!$G$7:$G$1006,"",0,-1),""))} -> EICES | L103: =IF($A103="","",IF($Q103=1,"MANUTENÇÃO",IF($P103="BAIXA","BAIXADO",IF($P103="FURTO","FURTADO",IF($J103<>"","EM OBRA","PENDENTE-PROCURAR"))))) -> BAIXADO | N103: {=IF($A103="","",IFERROR(IF(OR($L103="BAIXADO",$L103="FURTADO"),0,INDEX(Listas!$J$2:$J$40,MATCH($B103,Listas!$I$2:$I$40,0))),""))} -> 0 | P103: {=IF($A103="","",IFERROR(_xlfn.XLOOKUP($A103,'Movimentação'!$B$7:$B$1006,'Movimentação'!$F$7:$F$1006,"",0,-1),""))} -> BAIXA | Q103: =IF(COUNTIFS('Manutenção'!$B$7:$B$1006,$A103,'Manutenção'!$H$7:$H$1006,"EM CONSERTO")>0,1,0) -> 0
...

Sheet Movimentação
B1: MOVIMENTAÇÃO
B3: Registre 1 linha por evento: mudou de obra, quebrou, sumiu, foi baixada.
A6: Data | B6: Código | C6: Item (auto) | D6: Obra Origem | E6: Obra Destino | F6: Tipo / Motivo | G6: Responsável | H6: Observação
A7: 46235 | B7: PAR-01 | C7: {=IFERROR(INDEX('Patrimônio'!$C$7:$C$1003,MATCH($B7,'Patrimônio'!$A$7:$A$1003,0)),"")} -> Parafusadeira | D7: CARGA INICIAL | E7: PEDRO H | F7: ENTRADA (NOVA) | G7: EICES | H7: sincronizado c/ aferida ago/2026
A8: 46235 | B8: PAR-02 | C8: {=IFERROR(INDEX('Patrimônio'!$C$7:$C$1003,MATCH($B8,'Patrimônio'!$A$7:$A$1003,0)),"")} -> Parafusadeira | D8: CARGA INICIAL | E8: ALPHA ONE | F8: ENTRADA (NOVA) | G8: EICES | H8: sincronizado c/ aferida ago/2026
A9: 46235 | B9: PAR-03 | C9: {=IFERROR(INDEX('Patrimônio'!$C$7:$C$1003,MATCH($B9,'Patrimônio'!$A$7:$A$1003,0)),"")} -> Parafusadeira | E9: ALPHA ONE | F9: FURTO | G9: EICES
A10: 46235 | B10: PAR-04 | C10: {=IFERROR(INDEX('Patrimônio'!$C$7:$C$1003,MATCH($B10,'Patrimônio'!$A$7:$A$1003,0)),"")} -> Parafusadeira | D10: CARGA INICIAL | E10: ALPHA ONE | F10: ENTRADA (NOVA) | G10: EICES | H10: sincronizado c/ aferida ago/2026
A11: 46235 | B11: PAR-05 | C11: {=IFERROR(INDEX('Patrimônio'!$C$7:$C$1003,MATCH($B11,'Patrimônio'!$A$7:$A$1003,0)),"")} -> Parafusadeira | D11: CARGA INICIAL | E11: ALPHA ONE | F11: ENTRADA (NOVA) | G11: EICES | H11: sincronizado c/ aferida ago/2026
A12: 46235 | B12: PAR-5 | C12: {=IFERROR(INDEX('Patrimônio'!$C$7:$C$1003,MATCH($B12,'Patrimônio'!$A$7:$A$1003,0)),"")} -> Parafusadeira | D12: CARGA INICIAL | E12: ALPHA ONE | F12: ENTRADA (NOVA) | G12: EICES | H12: sincronizado c/ aferida ago/2026
A13: 46235 | B13: PAR-06 | C13: {=IFERROR(INDEX('Patrimônio'!$C$7:$C$1003,MATCH($B13,'Patrimônio'!$A$7:$A$1003,0)),"")} -> Parafusadeira | D13: CARGA INICIAL | E13: ANGELICA | F13: ENTRADA (NOVA) | G13: EICES | H13: sincronizado c/ aferida ago/2026
A14: 46235 | B14: PAR-07 | C14: {=IFERROR(INDEX('Patrimônio'!$C$7:$C$1003,MATCH($B14,'Patrimônio'!$A$7:$A$1003,0)),"")} -> Parafusadeira | D14: CARGA INICIAL | E14: TANABI | F14: ENTRADA (NOVA) | G14: EICES | H14: sincronizado c/ aferida ago/2026
A15: 46235 | B15: PAR-09 | C15: {=IFERROR(INDEX('Patrimônio'!$C$7:$C$1003,MATCH($B15,'Patrimônio'!$A$7:$A$1003,0)),"")} -> Parafusadeira | D15: CARGA INICIAL | E15: ESCRITÓRIO | F15: ENTRADA (NOVA) | G15: EICES | H15: sincronizado c/ aferida ago/2026
A16: 46235 | B16: PAR-11 | C16: {=IFERROR(INDEX('Patrimônio'!$C$7:$C$1003,MATCH($B16,'Patrimônio'!$A$7:$A$1003,0)),"")} -> Parafusadeira | D16: CARGA INICIAL | E16: MAURO | F16: ENTRADA (NOVA) | G16: EICES | H16: sincronizado c/ aferida ago/2026
A17: 46235 | B17: PAR-12 | C17: {=IFERROR(INDEX('Patrimônio'!$C$7:$C$1003,MATCH($B17,'Patrimônio'!$A$7:$A$1003,0)),"")} -> Parafusadeira | D17: CARGA INICIAL | E17: ESCRITÓRIO | F17: ENTRADA (NOVA) | G17: EICES | H17: sincronizado c/ aferida ago/2026
A18: 46235 | B18: PAR-14 | C18: {=IFERROR(INDEX('Patrimônio'!$C$7:$C$1003,MATCH($B18,'Patrimônio'!$A$7:$A$1003,0)),"")} -> Parafusadeira | D18: CARGA INICIAL | E18: BIOMA | F18: ENTRADA (NOVA) | G18: EICES | H18: sincronizado c/ aferida ago/2026
A19: 46235 | B19: PAR-15 | C19: {=IFERROR(INDEX('Patrimônio'!$C$7:$C$1003,MATCH($B19,'Patrimônio'!$A$7:$A$1003,0)),"")} -> Parafusadeira | D19: CARGA INICIAL | E19: ARENGA (TRISUL) | F19: ENTRADA (NOVA) | G19: EICES | H19: sincronizado c/ aferida ago/2026
A20: 46235 | B20: PAR-14 | C20: {=IFERROR(INDEX('Patrimônio'!$C$7:$C$1003,MATCH($B20,'Patrimônio'!$A$7:$A$1003,0)),"")} -> Parafusadeira | D20: CARGA INICIAL | E20: ASSISTENCIA TECNICA | F20: ENTRADA (NOVA) | G20: EICES | H20: sincronizado c/ aferida ago/2026
A21: 46235 | B21: PAR-17 | C21: {=IFERROR(INDEX('Patrimônio'!$C$7:$C$1003,MATCH($B21,'Patrimônio'!$A$7:$A$1003,0)),"")} -> Parafusadeira | D21: CARGA INICIAL | E21: PJM | F21: ENTRADA (NOVA) | G21: EICES | H21: sincronizado c/ aferida ago/2026
... A26: 46235 | B26: FRP-01 | C26: {=IFERROR(INDEX('Patrimônio'!$C$7:$C$1003,MATCH($B26,'Patrimônio'!$A$7:$A$1003,0)),"")} -> Rompedor | D26: CARGA INICIAL | E26: ORIÇANGA | F26: ENTRADA (NOVA) | G26: EICES | H26: sincronizado c/ aferida ago/2026
A27: 46235 | B27: FRP-02 | C27: {=IFERROR(INDEX('Patrimônio'!$C$7:$C$1003,MATCH($B27,'Patrimônio'!$A$7:$A$1003,0)),"")} -> Rompedor | F27: BAIXA | G27: EICES | H27: baixa (perda total)
A28: 46235 | B28: FRP-03 | C28: {=IFERROR(INDEX('Patrimônio'!$C$7:$C$1003,MATCH($B28,'Patrimônio'!$A$7:$A$1003,0)),"")} -> Rompedor | D28: CARGA INICIAL | E28: DIEGO | F28: ENTRADA (NOVA) | G28: EICES | H28: sincronizado c/ aferida ago/2026
A29: 46235 | B29: FRP-05 | C29: {=IFERROR(INDEX('Patrimônio'!$C$7:$C$1003,MATCH($B29,'Patrimônio'!$A$7:$A$1003,0)),"")} -> Rompedor | D29: CARGA INICIAL | E29: TANABI | F29: ENTRADA (NOVA) | G29: EICES | H29: sincronizado c/ aferida ago/2026
A30: 46235 | B30: FRP-06 | C30: {=IFERROR(INDEX('Patrimônio'!$C$7:$C$1003,MATCH($B30,'Patrimônio'!$A$7:$A$1003,0)),"")} -> Rompedor | D30: CARGA INICIAL | E30: ORIÇANGA | F30: ENTRADA (NOVA) | G30: EICES | H30: sincronizado c/ aferida ago/2026
A31: 46235 | B31: FRP-07 | C31: {=IFERROR(INDEX('Patrimônio'!$C$7:$C$1003,MATCH($B31,'Patrimônio'!$A$7:$A$1003,0)),"")} -> Rompedor | D31: CARGA INICIAL | E31: ALPHA ONE | F31: ENTRADA (NOVA) | G31: EICES | H31: sincronizado c/ aferida ago/2026
A32: 46235 | B32: FRP-08 | C32: {=IFERROR(INDEX('Patrimônio'!$C$7:$C$1003,MATCH($B32,'Patrimônio'!$A$7:$A$1003,0)),"")} -> Rompedor | D32: CARGA INICIAL | E32: MAURO | F32: ENTRADA (NOVA) | G32: EICES | H32: sincronizado c/ aferida ago/2026
A33: 46235 | B33: FRP-09 | C33: {=IFERROR(INDEX('Patrimônio'!$C$7:$C$1003,MATCH($B33,'Patrimônio'!$A$7:$A$1003,0)),"")} -> Rompedor | D33: CARGA INICIAL | E33: ALTIER | F33: ENTRADA (NOVA) | G33: EICES | H33: sincronizado c/ aferida ago/2026
A34: 46235 | B34: FRP-10 | C34: {=IFERROR(INDEX('Patrimônio'!$C$7:$C$1003,MATCH($B34,'Patrimônio'!$A$7:$A$1003,0)),"")} -> Rompedor | D34: CARGA INICIAL | E34: JOA | F34: ENTRADA (NOVA) | G34: EICES | H34: sincronizado c/ aferida ago/2026
A35: 46235 | B35: FRP-11 | C35: {=IFERROR(INDEX('Patrimônio'!$C$7:$C$1003,MATCH($B35,'Patrimônio'!$A$7:$A$1003,0)),"")} -> Rompedor | D35: CARGA INICIAL | E35: PJM | F35: ENTRADA (NOVA) | G35: EICES | H35: sincronizado c/ aferida ago/2026
A36: 46235 | B36: FRP-12 | C36: {=IFERROR(INDEX('Patrimônio'!$C$7:$C$1003,MATCH($B36,'Patrimônio'!$A$7:$A$1003,0)),"")} -> Rompedor | D36: CARGA INICIAL | E36: SAMPA CONSOLAÇÃO | F36: ENTRADA (NOVA) | G36: EICES | H36: sincronizado c/ aferida ago/2026
A37: 46235 | B37: FRP-14 | C37: {=IFERROR(INDEX('Patrimônio'!$C$7:$C$1003,MATCH($B37,'Patrimônio'!$A$7:$A$1003,0)),"")} -> Rompedor | D37: CARGA INICIAL | E37: MAURO | F37: ENTRADA (NOVA) | G37: EICES | H37: sincronizado c/ aferida ago/2026
A38: 46235 | B38: ESL-01 | C38: {=IFERROR(INDEX('Patrimônio'!$C$7:$C$1003,MATCH($B38,'Patrimônio'!$A$7:$A$1003,0)),"")} -> Esmerilhadeira | D38: CARGA INICIAL | E38: PEDRO H | F38: ENTRADA (NOVA) | G38: EICES | H38: sincronizado c/ aferida ago/2026
A39: 46235 | B39: ESL-02 | C39: {=IFERROR(INDEX('Patrimônio'!$C$7:$C$1003,MATCH($B39,'Patrimônio'!$A$7:$A$1003,0)),"")} -> Esmerilhadeira | D39: CARGA INICIAL | E39: MAURO | F39: ENTRADA (NOVA) | G39: EICES | H39: sincronizado c/ aferida ago/2026
... A43: 46235 | B43: MSE-01 | C43: {=IFERROR(INDEX('Patrimônio'!$C$7:$C$1003,MATCH($B43,'Patrimônio'!$A$7:$A$1003,0)),"")} -> Serra Mármore | D43: CARGA INICIAL | E43: PEDRO H | F43: ENTRADA (NOVA) | G43: EICES | H43: sincronizado c/ aferida ago/2026
A44: 46235 | B44: MSE-02 | C44: {=IFERROR(INDEX('Patrimônio'!$C$7:$C$1003,MATCH($B44,'Patrimônio'!$A$7:$A$1003,0)),"")} -> Serra Mármore | F44: BAIXA | G44: EICES | H44: baixa (perda total)
A45: 46235 | B45: MSE-03 | C45: {=IFERROR(INDEX('Patrimônio'!$C$7:$C$1003,MATCH($B45,'Patrimônio'!$A$7:$A$1003,0)),"")} -> Serra Mármore | D45: CARGA INICIAL | E45: ALPHA ONE | F45: ENTRADA (NOVA) | G45: EICES | H45: sincronizado c/ aferida ago/2026
A46: 46235 | B46: MSE-04 | C46: {=IFERROR(INDEX('Patrimônio'!$C$7:$C$1003,MATCH($B46,'Patrimônio'!$A$7:$A$1003,0)),"")} -> Serra Mármore | D46: CARGA INICIAL | E46: ALTIER | F46: ENTRADA (NOVA) | G46: EICES | H46: sincronizado c/ aferida ago/2026
A47: 46235 | B47: MSE-05 | C47: {=IFERROR(INDEX('Patrimônio'!$C$7:$C$1003,MATCH($B47,'Patrimônio'!$A$7:$A$1003,0)),"")} -> Serra Mármore | D47: CARGA INICIAL | E47: ORIÇANGA | F47: ENTRADA (NOVA) | G47: EICES | H47: sincronizado c/ aferida ago/2026
A48: 46235 | B48: MSE-06 | C48: {=IFERROR(INDEX('Patrimônio'!$C$7:$C$1003,MATCH($B48,'Patrimônio'!$A$7:$A$1003,0)),"")} -> Serra Mármore | D48: CARGA INICIAL | E48: SAMPA CONSOLAÇÃO | F48: ENTRADA (NOVA) | G48: EICES | H48: sincronizado c/ aferida ago/2026
A49: 46235 | B49: MSE-07 | C49: {=IFERROR(INDEX('Patrimônio'!$C$7:$C$1003,MATCH($B49,'Patrimônio'!$A$7:$A$1003,0)),"")} -> Serra Mármore | D49: CARGA INICIAL | E49: MAURO | F49: ENTRADA (NOVA) | G49: EICES | H49: sincronizado c/ aferida ago/2026
A50: 46235 | B50: CMA-01 | C50: {=IFERROR(INDEX('Patrimônio'!$C$7:$C$1003,MATCH($B50,'Patrimônio'!$A$7:$A$1003,0)),"")} -> Martelete 5Kg | D50: CARGA INICIAL | E50: MAURO | F50: ENTRADA (NOVA) | G50: EICES | H50: sincronizado c/ aferida ago/2026
A51: 46235 | B51: CMA-02 | C51: {=IFERROR(INDEX('Patrimônio'!$C$7:$C$1003,MATCH($B51,'Patrimônio'!$A$7:$A$1003,0)),"")} -> Martelete 5Kg | D51: CARGA INICIAL | E51: MAURO | F51: ENTRADA (NOVA) | G51: EICES | H51: sincronizado c/ aferida ago/2026
A52: 46235 | B52: CMA-03 | C52: {=IFERROR(INDEX('Patrimônio'!$C$7:$C$1003,MATCH($B52,'Patrimônio'!$A$7:$A$1003,0)),"")} -> Martelete 5Kg | D52: CARGA INICIAL | E52: ARTHUR PRADO | F52: ENTRADA (NOVA) | G52: EICES | H52: sincronizado c/ aferida ago/2026
A53: 46235 | B53: CMA-04 | C53: {=IFERROR(INDEX('Patrimônio'!$C$7:$C$1003,MATCH($B53,'Patrimônio'!$A$7:$A$1003,0)),"")} -> Martelete 5Kg | D53: CARGA INICIAL | E53: ALTIER | F53: ENTRADA (NOVA) | G53: EICES | H53: sincronizado c/ aferida ago/2026
A54: 46235 | B54: MDA-01 | C54: {=IFERROR(INDEX('Patrimônio'!$C$7:$C$1003,MATCH($B54,'Patrimônio'!$A$7:$A$1003,0)),"")} -> Martelete 10Kg | D54: CARGA INICIAL | E54: TANABI | F54: ENTRADA (NOVA) | G54: EICES | H54: sincronizado c/ aferida ago/2026
A55: 46235 | B55: LAS-01 | C55: {=IFERROR(INDEX('Patrimônio'!$C$7:$C$1003,MATCH($B55,'Patrimônio'!$A$7:$A$1003,0)),"")} -> Laser | D55: CARGA INICIAL | E55: ALPHA ONE | F55: ENTRADA (NOVA) | G55: EICES | H55: sincronizado c/ aferida ago/2026
A56: 46235 | B56: LAS-04 | C56: {=IFERROR(INDEX('Patrimônio'!$C$7:$C$1003,MATCH($B56,'Patrimônio'!$A$7:$A$1003,0)),"")} -> Laser | D56: CARGA INICIAL | E56: ESCRITÓRIO | F56: ENTRADA (NOVA) | G56: EICES | H56: sincronizado c/ aferida ago/2026
... A84: 46235 | B84: PFP-01 | C84: {=IFERROR(INDEX('Patrimônio'!$C$7:$C$1003,MATCH($B84,'Patrimônio'!$A$7:$A$1003,0)),"")} -> Pistola Finca Pino | D84: CARGA INICIAL | E84: WILLIAM | F84: ENTRADA (NOVA) | G84: EICES | H84: sincronizado c/ aferida ago/2026
A85: 46235 | B85: PFP-02 | C85: {=IFERROR(INDEX('Patrimônio'!$C$7:$C$1003,MATCH($B85,'Patrimônio'!$A$7:$A$1003,0)),"")} -> Pistola Finca Pino | F85: BAIXA | G85: EICES | H85: baixa (perda total)
A86: 46235 | B86: PFP-03 | C86: {=IFERROR(INDEX('Patrimônio'!$C$7:$C$1003,MATCH($B86,'Patrimônio'!$A$7:$A$1003,0)),"")} -> Pistola Finca Pino | F86: BAIXA | G86: EICES | H86: baixa (perda total)
A87: 46235 | B87: PFP-04 | C87: {=IFERROR(INDEX('Patrimônio'!$C$7:$C$1003,MATCH($B87,'Patrimônio'!$A$7:$A$1003,0)),"")} -> Pistola Finca Pino | F87: BAIXA | G87: EICES | H87: baixa (perda total)
A88: 46235 | B88: PFP-05 | C88: {=IFERROR(INDEX('Patrimônio'!$C$7:$C$1003,MATCH($B88,'Patrimônio'!$A$7:$A$1003,0)),"")} -> Pistola Finca Pino | F88: BAIXA | G88: EICES | H88: baixa (perda total)
A89: 46235 | B89: PFP-06 | C89: {=IFERROR(INDEX('Patrimônio'!$C$7:$C$1003,MATCH($B89,'Patrimônio'!$A$7:$A$1003,0)),"")} -> Pistola Finca Pino | F89: BAIXA | G89: EICES | H89: baixa (perda total)
A90: 46235 | B90: PFP-07 | C90: {=IFERROR(INDEX('Patrimônio'!$C$7:$C$1003,MATCH($B90,'Patrimônio'!$A$7:$A$1003,0)),"")} -> Pistola Finca Pino | D90: CARGA INICIAL | E90: ESCRITÓRIO | F90: ENTRADA (NOVA) | G90: EICES | H90: sincronizado c/ aferida ago/2026
A91: 46235 | B91: PFP-08 | C91: {=IFERROR(INDEX('Patrimônio'!$C$7:$C$1003,MATCH($B91,'Patrimônio'!$A$7:$A$1003,0)),"")} -> Pistola Finca Pino | D91: CARGA INICIAL | E91: ARENGA (TRISUL) | F91: ENTRADA (NOVA) | G91: EICES | H91: sincronizado c/ aferida ago/2026
A92: 46235 | B92: PFP-09 | C92: {=IFERROR(INDEX('Patrimônio'!$C$7:$C$1003,MATCH($B92,'Patrimônio'!$A$7:$A$1003,0)),"")} -> Pistola Finca Pino | D92: CARGA INICIAL | E92: ARTHUR PRADO | F92: ENTRADA (NOVA) | G92: EICES | H92: sincronizado c/ aferida ago/2026
A93: 46235 | B93: PRP-10 | C93: {=IFERROR(INDEX('Patrimônio'!$C$7:$C$1003,MATCH($B93,'Patrimônio'!$A$7:$A$1003,0)),"")} -> Pistola Finca Pino | D93: CARGA INICIAL | E93: JOA | F93: ENTRADA (NOVA) | G93: EICES | H93: sincronizado c/ aferida ago/2026
A94: 46235 | B94: PFP-11 | C94: {=IFERROR(INDEX('Patrimônio'!$C$7:$C$1003,MATCH($B94,'Patrimônio'!$A$7:$A$1003,0)),"")} -> Pistola Finca Pino | D94: CARGA INICIAL | E94: MAURO | F94: ENTRADA (NOVA) | G94: EICES | H94: sincronizado c/ aferida ago/2026
A95: 46235 | B95: PFP-12 | C95: {=IFERROR(INDEX('Patrimônio'!$C$7:$C$1003,MATCH($B95,'Patrimônio'!$A$7:$A$1003,0)),"")} -> Pistola Finca Pino | D95: CARGA INICIAL | E95: ARENGA (TRISUL) | F95: ENTRADA (NOVA) | G95: EICES | H95: sincronizado c/ aferida ago/2026
A96: 46235 | B96: PFP-13 | C96: {=IFERROR(INDEX('Patrimônio'!$C$7:$C$1003,MATCH($B96,'Patrimônio'!$A$7:$A$1003,0)),"")} -> Pistola Finca Pino | D96: CARGA INICIAL | E96: ANGELICA | F96: ENTRADA (NOVA) | G96: EICES | H96: sincronizado c/ aferida ago/2026
A97: 46235 | B97: TES-01 | C97: {=IFERROR(INDEX('Patrimônio'!$C$7:$C$1003,MATCH($B97,'Patrimônio'!$A$7:$A$1003,0)),"")} -> Máquina Teste Água | D97: CARGA INICIAL | E97: ALTIER | F97: ENTRADA (NOVA) | G97: EICES | H97: sincronizado c/ aferida ago/2026
A98: 46235 | B98: TES-02 | C98: {=IFERROR(INDEX('Patrimônio'!$C$7:$C$1003,MATCH($B98,'Patrimônio'!$A$7:$A$1003,0)),"")} -> Máquina Teste Água | D98: CARGA INICIAL | E98: ARENGA (TRISUL) | F98: ENTRADA (NOVA) | G98: EICES | H98: sincronizado c/ aferida ago/2026
A99: 46235 | B99: TES-03 | C99: {=IFERROR(INDEX('Patrimônio'!$C$7:$C$1003,MATCH($B99,'Patrimônio'!$A$7:$A$1003,0)),"")} -> Máquina Teste Água | D99: CARGA INICIAL | E99: BALTAZAR | F99: ENTRADA (NOVA) | G99: EICES | H99: sincronizado c/ aferida ago/2026
A100: 46235 | B100: TES-04 | C100: {=IFERROR(INDEX('Patrimônio'!$C$7:$C$1003,MATCH($B100,'Patrimônio'!$A$7:$A$1003,0)),"")} -> Máquina Teste Água | D100: CARGA INICIAL | E100: PJM | F100: ENTRADA (NOVA) | G100: EICES | H100: sincronizado c/ aferida ago/2026
A101: 46235 | B101: MIL-01 | C101: {=IFERROR(INDEX('Patrimônio'!$C$7:$C$1003,MATCH($B101,'Patrimônio'!$A$7:$A$1003,0)),"")} -> Máquina Teste Elétrica | D101: CARGA INICIAL | E101: INFRA | F101: ENTRADA (NOVA) | G101: EICES | H101: sincronizado c/ aferida ago/2026
... A113: 46235 | B113: PTE-02 | C113: {=IFERROR(INDEX('Patrimônio'!$C$7:$C$1003,MATCH($B113,'Patrimônio'!$A$7:$A$1003,0)),"")} -> Prensa Terminal | D113: CARGA INICIAL | E113: ESCRITÓRIO | F113: ENTRADA (NOVA) | G113: EICES | H113: sincronizado c/ aferida ago/2026
A114: 46235 | B114: PTE-03 | C114: {=IFERROR(INDEX('Patrimônio'!$C$7:$C$1003,MATCH($B114,'Patrimônio'!$A$7:$A$1003,0)),"")} -> Prensa Terminal | F114: BAIXA | G114: EICES | H114: baixa (perda total)
A115: 46235 | B115: PGA-01 | C115: {=IFERROR(INDEX('Patrimônio'!$C$7:$C$1003,MATCH($B115,'Patrimônio'!$A$7:$A$1003,0)),"")} -> Prensa Gás | D115: ALPHA ONE | E115: MAURO | F115: TRANSFERÊNCIA | G115: EICES | H115: sincronizado c/ aferida ago/2026
A116: 46235 | B116: MAN-02 | C116: {=IFERROR(INDEX('Patrimônio'!$C$7:$C$1003,MATCH($B116,'Patrimônio'!$A$7:$A$1003,0)),"")} -> Manômetro | D116: CARGA INICIAL | E116: TANABI | F116: ENTRADA (NOVA) | G116: EICES | H116: sincronizado c/ aferida ago/2026
A117: 46235 | B117: PCA-01 | C117: {=IFERROR(INDEX('Patrimônio'!$C$7:$C$1003,MATCH($B117,'Patrimônio'!$A$7:$A$1003,0)),"")} | D117: CARGA INICIAL | E117: ALPHA ONE | F117: ENTRADA (NOVA) | G117: EICES | H117: sincronizado c/ aferida ago/2026
A118: 46235 | B118: EXT-01 | C118: {=IFERROR(INDEX('Patrimônio'!$C$7:$C$1003,MATCH($B118,'Patrimônio'!$A$7:$A$1003,0)),"")} -> Perfuratriz Extratora | D118: CARGA INICIAL | E118: SAMPA CONSOLAÇÃO | F118: ENTRADA (NOVA) | G118: EICES | H118: sincronizado c/ aferida ago/2026
A119: 46235 | B119: SOP-02-B | C119: {=IFERROR(INDEX('Patrimônio'!$C$7:$C$1003,MATCH($B119,'Patrimônio'!$A$7:$A$1003,0)),"")} -> Soprador | D119: CARGA INICIAL | E119: ALPHA ONE | F119: ENTRADA (NOVA) | G119: EICES | H119: sincronizado c/ aferida ago/2026
A120: 46235 | B120: TSF-01 | C120: {=IFERROR(INDEX('Patrimônio'!$C$7:$C$1003,MATCH($B120,'Patrimônio'!$A$7:$A$1003,0)),"")} -> Tesoura Corta Ferro | D120: CARGA INICIAL | E120: SAMPA CONSOLAÇÃO | F120: ENTRADA (NOVA) | G120: EICES | H120: sincronizado c/ aferida ago/2026
A121: 46235 | B121: PTE-04 | C121: {=IFERROR(INDEX('Patrimônio'!$C$7:$C$1003,MATCH($B121,'Patrimônio'!$A$7:$A$1003,0)),"")} -> Prensa Terminal | D121: CARGA INICIAL | E121: ALTIER | F121: ENTRADA (NOVA) | G121: EICES | H121: sincronizado c/ aferida ago/2026
A122: 46235 | B122: PPE-07 | C122: {=IFERROR(INDEX('Patrimônio'!$C$7:$C$1003,MATCH($B122,'Patrimônio'!$A$7:$A$1003,0)),"")} -> Prensa Pex | D122: CARGA INICIAL | E122: TANABI | F122: ENTRADA (NOVA) | G122: EICES | H122: sincronizado c/ aferida ago/2026
A123: 46235 | B123: PUL-01 | C123: {=IFERROR(INDEX('Patrimônio'!$C$7:$C$1003,MATCH($B123,'Patrimônio'!$A$7:$A$1003,0)),"")} -> Pulverizadora | D123: CARGA INICIAL | E123: ARENGA (TRISUL) | F123: ENTRADA (NOVA) | G123: EICES | H123: sincronizado c/ aferida ago/2026
A124: 46235 | B124: APX-01 | C124: {=IFERROR(INDEX('Patrimônio'!$C$7:$C$1003,MATCH($B124,'Patrimônio'!$A$7:$A$1003,0)),"")} -> Alargador Pex | D124: CARGA INICIAL | E124: ARENGA (TRISUL) | F124: ENTRADA (NOVA) | G124: EICES | H124: sincronizado c/ aferida ago/2026
A125: 46235 | B125: APX-02 | C125: {=IFERROR(INDEX('Patrimônio'!$C$7:$C$1003,MATCH($B125,'Patrimônio'!$A$7:$A$1003,0)),"")} -> Alargador Pex | D125: CARGA INICIAL | E125: SAMPA CONSOLAÇÃO | F125: ENTRADA (NOVA) | G125: EICES | H125: sincronizado c/ aferida ago/2026
A126: 46235 | B126: MDA-02 | C126: {=IFERROR(INDEX('Patrimônio'!$C$7:$C$1003,MATCH($B126,'Patrimônio'!$A$7:$A$1003,0)),"")} | D126: CARGA INICIAL | E126: BALTAZAR | F126: ENTRADA (NOVA) | G126: EICES | H126: sincronizado c/ aferida ago/2026
... A132: 46235 | B132: SOL-01 | C132: {=IFERROR(INDEX('Patrimônio'!$C$7:$C$1003,MATCH($B132,'Patrimônio'!$A$7:$A$1003,0)),"")} -> Maquina De Solda | D132: CARGA INICIAL | E132: TANABI | F132: ENTRADA (NOVA) | G132: EICES | H132: sincronizado c/ aferida ago/2026
A133: 46236 | B133: CMA-03 | C133: {=IFERROR(INDEX('Patrimônio'!$C$7:$C$1003,MATCH($B133,'Patrimônio'!$A$7:$A$1003,0)),"")} -> Martelete 5Kg | D133: ARTHUR PRADO | E133: BALTAZAR | F133: ENTRADA (NOVA) | G133: JORGE
A134: 46245 | B134: EXT-01 | C134: {=IFERROR(INDEX('Patrimônio'!$C$7:$C$1003,MATCH($B134,'Patrimônio'!$A$7:$A$1003,0)),"")} -> Perfuratriz Extratora | D134: SAMPA CONSOLAÇÃO | E134: ENXOVIA | F134: ENTRADA (NOVA) | G134: GUILHERME | H134: mandar email para a assinatura do termo
A135: 46023 | B135: PAR-01 | C135: {=IFERROR(INDEX('Patrimônio'!$C$7:$C$1003,MATCH($B135,'Patrimônio'!$A$7:$A$1003,0)),"")} -> Parafusadeira | D135: PEDRO H | E135: PEDRO H | F135: BAIXA | G135: EICES | H135: baixa (perda total)
A136: 46023 | B136: PAR-02 | C136: {=IFERROR(INDEX('Patrimônio'!$C$7:$C$1003,MATCH($B136,'Patrimônio'!$A$7:$A$1003,0)),"")} -> Parafusadeira | D136: ALPHA ONE | E136: ALPHA ONE | F136: BAIXA | G136: EICES | H136: baixa (perda total)
A137: 46023 | B137: PAR-04 | C137: {=IFERROR(INDEX('Patrimônio'!$C$7:$C$1003,MATCH($B137,'Patrimônio'!$A$7:$A$1003,0)),"")} -> Parafusadeira | D137: ALPHA ONE | E137: ALPHA ONE | F137: BAIXA | G137: EICES | H137: baixa (perda total)
A138: 46024 | B138: PAR-05 | C138: {=IFERROR(INDEX('Patrimônio'!$C$7:$C$1003,MATCH($B138,'Patrimônio'!$A$7:$A$1003,0)),"")} -> Parafusadeira | E138: ASSISTENCIA TECNICA | F138: BAIXA | G138: EICES | H138: baixa (perda total)
A139: 46025 | B139: PAR-5 | C139: {=IFERROR(INDEX('Patrimônio'!$C$7:$C$1003,MATCH($B139,'Patrimônio'!$A$7:$A$1003,0)),"")} -> Parafusadeira | E139: ASSISTENCIA TECNICA | F139: BAIXA | G139: EICES | H139: baixa (perda total)
A140: 46025 | B140: FRP-03 | C140: {=IFERROR(INDEX('Patrimônio'!$C$7:$C$1003,MATCH($B140,'Patrimônio'!$A$7:$A$1003,0)),"")} -> Rompedor | E140: ASSISTENCIA TECNICA | F140: BAIXA | G140: EICES | H140: baixa (perda total)
A141: 46025 | B141: ESL-01 | C141: {=IFERROR(INDEX('Patrimônio'!$C$7:$C$1003,MATCH($B141,'Patrimônio'!$A$7:$A$1003,0)),"")} -> Esmerilhadeira | E141: ASSISTENCIA TECNICA | F141: BAIXA | G141: EICES | H141: baixa (perda total)
A142: 46025 | B142: MSE-01 | C142: {=IFERROR(INDEX('Patrimônio'!$C$7:$C$1003,MATCH($B142,'Patrimônio'!$A$7:$A$1003,0)),"")} -> Serra Mármore | E142: ASSISTENCIA TECNICA | F142: BAIXA | G142: EICES | H142: baixa (perda total)
A143: 46025 | B143: PEZ-01 | C143: {=IFERROR(INDEX('Patrimônio'!$C$7:$C$1003,MATCH($B143,'Patrimônio'!$A$7:$A$1003,0)),"")} -> Perfuratriz | E143: ASSISTENCIA TECNICA | F143: BAIXA | G143: EICES | H143: baixa (perda total)
A144: 46025 | B144: PFP-01 | C144: {=IFERROR(INDEX('Patrimônio'!$C$7:$C$1003,MATCH($B144,'Patrimônio'!$A$7:$A$1003,0)),"")} -> Pistola Finca Pino | E144: ASSISTENCIA TECNICA | F144: BAIXA | G144: EICES | H144: baixa (perda total)
A145: 46025 | B145: PTE-01 | C145: {=IFERROR(INDEX('Patrimônio'!$C$7:$C$1003,MATCH($B145,'Patrimônio'!$A$7:$A$1003,0)),"")} -> Prensa Terminal | E145: ASSISTENCIA TECNICA | F145: BAIXA | G145: EICES | H145: baixa (perda total)
A146: 46025 | B146: FRP-07 | C146: {=IFERROR(INDEX('Patrimônio'!$C$7:$C$1003,MATCH($B146,'Patrimônio'!$A$7:$A$1003,0)),"")} -> Rompedor | E146: ALPHA ONE | F146: BAIXA | G146: EICES | H146: baixa (perda total)
A147: 46025 | B147: MSE-03 | C147: {=IFERROR(INDEX('Patrimônio'!$C$7:$C$1003,MATCH($B147,'Patrimônio'!$A$7:$A$1003,0)),"")} -> Serra Mármore | D147: ALPHA ONE | E147: MAURO | F147: BAIXA | G147: EICES | H147: baixa (perda total)
A148: 46025 | B148: LAS-01 | C148: {=IFERROR(INDEX('Patrimônio'!$C$7:$C$1003,MATCH($B148,'Patrimônio'!$A$7:$A$1003,0)),"")} -> Laser | E148: ALPHA ONE | F148: BAIXA | G148: EICES | H148: baixa (perda total)
A149: 46025 | B149: TER-01 | C149: {=IFERROR(INDEX('Patrimônio'!$C$7:$C$1003,MATCH($B149,'Patrimônio'!$A$7:$A$1003,0)),"")} -> Termofusor | E149: ALPHA ONE | F149: BAIXA | G149: EICES | H149: baixa (perda total)
A150: 46025 | B150: SOP-02-B | C150: {=IFERROR(INDEX('Patrimônio'!$C$7:$C$1003,MATCH($B150,'Patrimônio'!$A$7:$A$1003,0)),"")} -> Soprador | D150: ALPHA ONE | E150: ALPHA ONE | F150: BAIXA | G150: EICES | H150: baixa (perda total)
A151: 46235 | B151: PPE-04 | C151: {=IFERROR(INDEX('Patrimônio'!$C$7:$C$1003,MATCH($B151,'Patrimônio'!$A$7:$A$1003,0)),"")} -> Prensa Pex | D151: ALPHA ONE | E151: MAURO | F151: TRANSFERÊNCIA | G151: TAYANE
A152: 46235 | B152: PPE-05 | C152: {=IFERROR(INDEX('Patrimônio'!$C$7:$C$1003,MATCH($B152,'Patrimônio'!$A$7:$A$1003,0)),"")} -> Prensa Pex | D152: ESCRITORIO | E152: TANABI | F152: TRANSFERÊNCIA | G152: MAYARA
A153: 46236 | B153: PFP-09 | C153: {=IFERROR(INDEX('Patrimônio'!$C$7:$C$1003,MATCH($B153,'Patrimônio'!$A$7:$A$1003,0)),"")} -> Pistola Finca Pino | E153: ARTHUR PRADO | F153: BAIXA | G153: LUCAS | H153: baixa (perda total)
...

Sheet Manutenção
B1: MANUTENÇÃO — FICHA DE CONSERTOS
B3: Cada conserto = 1 linha. Alimenta o giro de estoque e o custo de manutenção.
A6: Data Entrada | B6: Código | C6: Item (auto) | D6: Categoria (auto) | E6: Obra onde Quebrou | F6: Custo (R$) | G6: Data Retorno | H6: Status | I6: Obra Retorno | J6: Dias Parado (auto) | K6: Observação
A7: 46235 | B7: PAR-18 | C7: {=IFERROR(INDEX('Patrimônio'!$C$7:$C$1003,MATCH($B7,'Patrimônio'!$A$7:$A$1003,0)),"")} -> Parafusadeira | D7: {=IFERROR(INDEX('Patrimônio'!$B$7:$B$1003,MATCH($B7,'Patrimônio'!$A$7:$A$1003,0)),"")} -> PARAFUSADEIRA | E7: ANGELICA | G7: 46246 | H7: VOLTOU | I7: ANGELICA | J7: =IF(AND($A7<>"",$G7<>""),$G7-$A7,"") -> 11 | K7: auditoria ago/2026
A8: 46235 | B8: FRP-06 | C8: {=IFERROR(INDEX('Patrimônio'!$C$7:$C$1003,MATCH($B8,'Patrimônio'!$A$7:$A$1003,0)),"")} -> Rompedor | D8: {=IFERROR(INDEX('Patrimônio'!$B$7:$B$1003,MATCH($B8,'Patrimônio'!$A$7:$A$1003,0)),"")} -> ROMPEDOR | E8: ORIÇANGA | G8: 46248 | H8: VOLTOU | I8: SAMPA CONSOLAÇÃO | J8: =IF(AND($A8<>"",$G8<>""),$G8-$A8,"") -> 13 | K8: auditoria ago/2026
A9: 46235 | B9: PEZ-02 | C9: {=IFERROR(INDEX('Patrimônio'!$C$7:$C$1003,MATCH($B9,'Patrimônio'!$A$7:$A$1003,0)),"")} -> Perfuratriz | D9: {=IFERROR(INDEX('Patrimônio'!$B$7:$B$1003,MATCH($B9,'Patrimônio'!$A$7:$A$1003,0)),"")} -> PERFURATRIZ | E9: ORIÇANGA | G9: 46244 | H9: VOLTOU | I9: ORIÇANGA | J9: =IF(AND($A9<>"",$G9<>""),$G9-$A9,"") -> 9 | K9: auditoria ago/2026
A10: 46235 | B10: PEZ-12 | C10: {=IFERROR(INDEX('Patrimônio'!$C$7:$C$1003,MATCH($B10,'Patrimônio'!$A$7:$A$1003,0)),"")} -> Perfuratriz | D10: {=IFERROR(INDEX('Patrimônio'!$B$7:$B$1003,MATCH($B10,'Patrimônio'!$A$7:$A$1003,0)),"")} -> PERFURATRIZ | E10: JOA | H10: VOLTOU | J10: =IF(AND($A10<>"",$G10<>""),$G10-$A10,"") | K10: auditoria ago/2026
A11: 46235 | B11: TER-04 | C11: {=IFERROR(INDEX('Patrimônio'!$C$7:$C$1003,MATCH($B11,'Patrimônio'!$A$7:$A$1003,0)),"")} -> Termofusor | D11: {=IFERROR(INDEX('Patrimônio'!$B$7:$B$1003,MATCH($B11,'Patrimônio'!$A$7:$A$1003,0)),"")} -> TERMOFUSOR | E11: SAMPA CONSOLAÇÃO | G11: 46235 | H11: VOLTOU | I11: SAMPA CONSOLAÇÃO | J11: =IF(AND($A11<>"",$G11<>""),$G11-$A11,"") -> 0 | K11: auditoria ago/2026
A12: 46235 | B12: TER-06 | C12: {=IFERROR(INDEX('Patrimônio'!$C$7:$C$1003,MATCH($B12,'Patrimônio'!$A$7:$A$1003,0)),"")} -> Termofusor | D12: {=IFERROR(INDEX('Patrimônio'!$B$7:$B$1003,MATCH($B12,'Patrimônio'!$A$7:$A$1003,0)),"")} -> TERMOFUSOR | E12: SAMPA CONSOLAÇÃO | G12: 46235 | H12: VOLTOU | I12: SAMPA CONSOLAÇÃO | J12: =IF(AND($A12<>"",$G12<>""),$G12-$A12,"") -> 0 | K12: auditoria ago/2026
A13: 46235 | B13: PFP-12 | C13: {=IFERROR(INDEX('Patrimônio'!$C$7:$C$1003,MATCH($B13,'Patrimônio'!$A$7:$A$1003,0)),"")} -> Pistola Finca Pino | D13: {=IFERROR(INDEX('Patrimônio'!$B$7:$B$1003,MATCH($B13,'Patrimônio'!$A$7:$A$1003,0)),"")} -> PISTOLA FINCA PINO | E13: ARENGA (TRISUL) | H13: BAIXA | J13: =IF(AND($A13<>"",$G13<>""),$G13-$A13,"") | K13: auditoria ago/2026
A14: 46235 | B14: PPE-02 | C14: {=IFERROR(INDEX('Patrimônio'!$C$7:$C$1003,MATCH($B14,'Patrimônio'!$A$7:$A$1003,0)),"")} -> Prensa Pex | D14: {=IFERROR(INDEX('Patrimônio'!$B$7:$B$1003,MATCH($B14,'Patrimônio'!$A$7:$A$1003,0)),"")} -> PRENSA PEX | E14: SAMPA CONSOLAÇÃO | H14: BAIXA | J14: =IF(AND($A14<>"",$G14<>""),$G14-$A14,"") | K14: SEM CONSERTO
A15: 46253 | B15: PEZ-10 | C15: {=IFERROR(INDEX('Patrimônio'!$C$7:$C$1003,MATCH($B15,'Patrimônio'!$A$7:$A$1003,0)),"")} -> Perfuratriz | D15: {=IFERROR(INDEX('Patrimônio'!$B$7:$B$1003,MATCH($B15,'Patrimônio'!$A$7:$A$1003,0)),"")} -> PERFURATRIZ | E15: JOA | G15: 46258 | H15: VOLTOU | I15: JOA | J15: =IF(AND($A15<>"",$G15<>""),$G15-$A15,"") -> 5
A16: 46258 | B16: FRP-14 | C16: {=IFERROR(INDEX('Patrimônio'!$C$7:$C$1003,MATCH($B16,'Patrimônio'!$A$7:$A$1003,0)),"")} -> Rompedor | D16: {=IFERROR(INDEX('Patrimônio'!$B$7:$B$1003,MATCH($B16,'Patrimônio'!$A$7:$A$1003,0)),"")} -> ROMPEDOR | E16: MAURO | H16: EM CONSERTO | J16: =IF(AND($A16<>"",$G16<>""),$G16-$A16,"")
A17: 46258 | B17: PAR-01 | C17: {=IFERROR(INDEX('Patrimônio'!$C$7:$C$1003,MATCH($B17,'Patrimônio'!$A$7:$A$1003,0)),"")} -> Parafusadeira | D17: {=IFERROR(INDEX('Patrimônio'!$B$7:$B$1003,MATCH($B17,'Patrimônio'!$A$7:$A$1003,0)),"")} -> PARAFUSADEIRA | G17: 46258 | H17: VOLTOU | I17: ALTIER | J17: =IF(AND($A17<>"",$G17<>""),$G17-$A17,"") -> 0
A18: 46260 | B18: PEZ-03 | C18: {=IFERROR(INDEX('Patrimônio'!$C$7:$C$1003,MATCH($B18,'Patrimônio'!$A$7:$A$1003,0)),"")} -> Perfuratriz | D18: {=IFERROR(INDEX('Patrimônio'!$B$7:$B$1003,MATCH($B18,'Patrimônio'!$A$7:$A$1003,0)),"")} -> PERFURATRIZ | E18: JOA | G18: 46268 | H18: VOLTOU | I18: JERONIMO | J18: =IF(AND($A18<>"",$G18<>""),$G18-$A18,"") -> 8
A19: 46261 | B19: FRP-09 | C19: {=IFERROR(INDEX('Patrimônio'!$C$7:$C$1003,MATCH($B19,'Patrimônio'!$A$7:$A$1003,0)),"")} -> Rompedor | D19: {=IFERROR(INDEX('Patrimônio'!$B$7:$B$1003,MATCH($B19,'Patrimônio'!$A$7:$A$1003,0)),"")} -> ROMPEDOR | E19: ALTIER | H19: BAIXA | J19: =IF(AND($A19<>"",$G19<>""),$G19-$A19,"")
A20: 46274 | B20: PEZ-10 | C20: {=IFERROR(INDEX('Patrimônio'!$C$7:$C$1003,MATCH($B20,'Patrimônio'!$A$7:$A$1003,0)),"")} -> Perfuratriz | D20: {=IFERROR(INDEX('Patrimônio'!$B$7:$B$1003,MATCH($B20,'Patrimônio'!$A$7:$A$1003,0)),"")} -> PERFURATRIZ | E20: JOA | G20: 46275 | H20: VOLTOU | I20: ANGELICA | J20: =IF(AND($A20<>"",$G20<>""),$G20-$A20,"") -> 1
A21: 46235 | B21: CMA-05 | C21: {=IFERROR(INDEX('Patrimônio'!$C$7:$C$1003,MATCH($B21,'Patrimônio'!$A$7:$A$1003,0)),"")} -> Martelete 5Kg | D21: {=IFERROR(INDEX('Patrimônio'!$B$7:$B$1003,MATCH($B21,'Patrimônio'!$A$7:$A$1003,0)),"")} -> MARTELETE 5KG | E21: CARGA INICIAL | H21: VOLTOU | I21: ESCRITORIO | J21: =IF(AND($A21<>"",$G21<>""),$G21-$A21,"")
A22: 46281 | B22: PEZ-12 | C22: {=IFERROR(INDEX('Patrimônio'!$C$7:$C$1003,MATCH($B22,'Patrimônio'!$A$7:$A$1003,0)),"")} -> Perfuratriz | D22: {=IFERROR(INDEX('Patrimônio'!$B$7:$B$1003,MATCH($B22,'Patrimônio'!$A$7:$A$1003,0)),"")} -> PERFURATRIZ | E22: SAMPA CONSOLAÇÃO | H22: EM CONSERTO | J22: =IF(AND($A22<>"",$G22<>""),$G22-$A22,"")
C23: {=IFERROR(INDEX('Patrimônio'!$C$7:$C$1003,MATCH($B23,'Patrimônio'!$A$7:$A$1003,0)),"")} | D23: {=IFERROR(INDEX('Patrimônio'!$B$7:$B$1003,MATCH($B23,'Patrimônio'!$A$7:$A$1003,0)),"")} | J23: =IF(AND($A23<>"",$G23<>""),$G23-$A23,"")
C24: {=IFERROR(INDEX('Patrimônio'!$C$7:$C$1003,MATCH($B24,'Patrimônio'!$A$7:$A$1003,0)),"")} | D24: {=IFERROR(INDEX('Patrimônio'!$B$7:$B$1003,MATCH($B24,'Patrimônio'!$A$7:$A$1003,0)),"")} | J24: =IF(AND($A24<>"",$G24<>""),$G24-$A24,"")
C25: {=IFERROR(INDEX('Patrimônio'!$C$7:$C$1003,MATCH($B25,'Patrimônio'!$A$7:$A$1003,0)),"")} | D25: {=IFERROR(INDEX('Patrimônio'!$B$7:$B$1003,MATCH($B25,'Patrimônio'!$A$7:$A$1003,0)),"")} | J25: =IF(AND($A25<>"",$G25<>""),$G25-$A25,"")
C26: {=IFERROR(INDEX('Patrimônio'!$C$7:$C$1003,MATCH($B26,'Patrimônio'!$A$7:$A$1003,0)),"")} | D26: {=IFERROR(INDEX('Patrimônio'!$B$7:$B$1003,MATCH($B26,'Patrimônio'!$A$7:$A$1003,0)),"")} | J26: =IF(AND($A26<>"",$G26<>""),$G26-$A26,"")
C27: {=IFERROR(INDEX('Patrimônio'!$C$7:$C$1003,MATCH($B27,'Patrimônio'!$A$7:$A$1003,0)),"")} | D27: {=IFERROR(INDEX('Patrimônio'!$B$7:$B$1003,MATCH($B27,'Patrimônio'!$A$7:$A$1003,0)),"")} | J27: =IF(AND($A27<>"",$G27<>""),$G27-$A27,"")
C28: {=IFERROR(INDEX('Patrimônio'!$C$7:$C$1003,MATCH($B28,'Patrimônio'!$A$7:$A$1003,0)),"")} | D28: {=IFERROR(INDEX('Patrimônio'!$B$7:$B$1003,MATCH($B28,'Patrimônio'!$A$7:$A$1003,0)),"")} | J28: =IF(AND($A28<>"",$G28<>""),$G28-$A28,"")
C29: {=IFERROR(INDEX('Patrimônio'!$C$7:$C$1003,MATCH($B29,'Patrimônio'!$A$7:$A$1003,0)),"")} | D29: {=IFERROR(INDEX('Patrimônio'!$B$7:$B$1003,MATCH($B29,'Patrimônio'!$A$7:$A$1003,0)),"")} | J29: =IF(AND($A29<>"",$G29<>""),$G29-$A29,"")
C30: {=IFERROR(INDEX('Patrimônio'!$C$7:$C$1003,MATCH($B30,'Patrimônio'!$A$7:$A$1003,0)),"")} | D30: {=IFERROR(INDEX('Patrimônio'!$B$7:$B$1003,MATCH($B30,'Patrimônio'!$A$7:$A$1003,0)),"")} | J30: =IF(AND($A30<>"",$G30<>""),$G30-$A30,"")
C31: {=IFERROR(INDEX('Patrimônio'!$C$7:$C$1003,MATCH($B31,'Patrimônio'!$A$7:$A$1003,0)),"")} | D31: {=IFERROR(INDEX('Patrimônio'!$B$7:$B$1003,MATCH($B31,'Patrimônio'!$A$7:$A$1003,0)),"")} | J31: =IF(AND($A31<>"",$G31<>""),$G31-$A31,"")
C32: {=IFERROR(INDEX('Patrimônio'!$C$7:$C$1003,MATCH($B32,'Patrimônio'!$A$7:$A$1003,0)),"")} | D32: {=IFERROR(INDEX('Patrimônio'!$B$7:$B$1003,MATCH($B32,'Patrimônio'!$A$7:$A$1003,0)),"")} | J32: =IF(AND($A32<>"",$G32<>""),$G32-$A32,"")
C33: {=IFERROR(INDEX('Patrimônio'!$C$7:$C$1003,MATCH($B33,'Patrimônio'!$A$7:$A$1003,0)),"")} | D33: {=IFERROR(INDEX('Patrimônio'!$B$7:$B$1003,MATCH($B33,'Patrimônio'!$A$7:$A$1003,0)),"")} | J33: =IF(AND($A33<>"",$G33<>""),$G33-$A33,"")
C34: {=IFERROR(INDEX('Patrimônio'!$C$7:$C$1003,MATCH($B34,'Patrimônio'!$A$7:$A$1003,0)),"")} | D34: {=IFERROR(INDEX('Patrimônio'!$B$7:$B$1003,MATCH($B34,'Patrimônio'!$A$7:$A$1003,0)),"")} | J34: =IF(AND($A34<>"",$G34<>""),$G34-$A34,"")
... C1006: {=IFERROR(INDEX('Patrimônio'!$C$7:$C$1003,MATCH($B1006,'Patrimônio'!$A$7:$A$1003,0)),"")} | D1006: {=IFERROR(INDEX('Patrimônio'!$B$7:$B$1003,MATCH($B1006,'Patrimônio'!$A$7:$A$1003,0)),"")} | J1006: =IF(AND($A1006<>"",$G1006<>""),$G1006-$A1006,"")

Sheet Rádio
B1: RÁDIO — CONTROLE POR OBRA
B3: Rádio é sempre locado (nunca patrimônio). Preencha a Data Devolução ao encerrar a obra — o custo sai sozinho.
A6: 1. SITUAÇÃO ATUAL POR OBRA
A7: Obra | B7: Locadora | C7: Qtd Atual | D7: Custo Mensal Unit. (R$) | E7: Custo Mensal Total (R$) | F7: Data Início | G7: Data Devolução | H7: Status | I7: Observação
A8: TANABI | B8: STOCK TOTAL | C8: 4 | D8: 65 | E8: =IF($C8="","",IF($G8<>"",0,$C8*$D8)) -> 260 | F8: 46143 | H8: =IF($A8="","",IF($G8<>"","ENCERRADO","ATIVO")) -> ATIVO | I8: carga inicial ago/2026
A9: ANGELICA | B9: OLUAP | C9: 5 | D9: 71.88 | E9: =IF($C9="","",IF($G9<>"",0,$C9*$D9)) -> 359.4 | H9: =IF($A9="","",IF($G9<>"","ENCERRADO","ATIVO")) -> ATIVO | I9: carga inicial ago/2026
A10: ALTIER | B10: OLUAP | C10: 4 | D10: 71.88 | E10: =IF($C10="","",IF($G10<>"",0,$C10*$D10)) -> 287.52 | H10: =IF($A10="","",IF($G10<>"","ENCERRADO","ATIVO")) -> ATIVO | I10: carga inicial ago/2026
A11: MAURO | B11: RADIO WAY | C11: 6 | D11: 78 | E11: =IF($C11="","",IF($G11<>"",0,$C11*$D11)) -> 468 | H11: =IF($A11="","",IF($G11<>"","ENCERRADO","ATIVO")) -> ATIVO | I11: carga inicial ago/2026
A12: PJM | B12: OLUAP | C12: 6 | D12: 71.88 | E12: =IF($C12="","",IF($G12<>"",0,$C12*$D12)) -> 431.28 | F12: 46121 | H12: =IF($A12="","",IF($G12<>"","ENCERRADO","ATIVO")) -> ATIVO | I12: entrada de 3 uni em 21/08/2026
A13: BALTAZAR | B13: HALCEPE | C13: 3 | D13: 49 | E13: =IF($C13="","",IF($G13<>"",0,$C13*$D13)) -> 147 | F13: 46136 | H13: =IF($A13="","",IF($G13<>"","ENCERRADO","ATIVO")) -> ATIVO | I13: carga inicial ago/2026
A14: SAMPA CONSOLAÇÃO | B14: OLUAP | C14: 6 | D14: 71.88 | E14: =IF($C14="","",IF($G14<>"",0,$C14*$D14)) -> 431.28 | H14: =IF($A14="","",IF($G14<>"","ENCERRADO","ATIVO")) -> ATIVO | I14: entrada de 3 uni em 21/08/2026
A15: ORIÇANGA | B15: RADIO WAY | C15: 4 | D15: 78 | E15: =IF($C15="","",IF($G15<>"",0,$C15*$D15)) -> 312 | H15: =IF($A15="","",IF($G15<>"","ENCERRADO","ATIVO")) -> ATIVO | I15: carga inicial ago/2026
A16: VIRGILIO | B16: STOCK TOTAL | C16: 0 | D16: 65 | E16: =IF($C16="","",IF($G16<>"",0,$C16*$D16)) -> 0 | F16: 46157 | H16: =IF($A16="","",IF($G16<>"","ENCERRADO","ATIVO")) -> ATIVO | I16: carga inicial ago/2026
A17: CUNHA GAGO | B17: HALCEPE | C17: 6 | D17: 49 | E17: =IF($C17="","",IF($G17<>"",0,$C17*$D17)) -> 294 | F17: 46261 | H17: =IF($A17="","",IF($G17<>"","ENCERRADO","ATIVO")) -> ATIVO
A18: ARENGA (TRISUL) | B18: OLUAP | C18: 3 | D18: 71.88 | E18: =IF($C18="","",IF($G18<>"",0,$C18*$D18)) -> 215.64 | H18: =IF($A18="","",IF($G18<>"","ENCERRADO","ATIVO")) -> ATIVO
A19: JERONIMO | B19: OLUAP | C19: 5 | D19: 71.88 | E19: =IF($C19="","",IF($G19<>"",0,$C19*$D19)) -> 359.4 | F19: 46280 | H19: =IF($A19="","",IF($G19<>"","ENCERRADO","ATIVO")) -> ATIVO
A20: JOA | B20: OLUAP | C20: 4 | D20: 71.88 | E20: =IF($C20="","",IF($G20<>"",0,$C20*$D20)) -> 287.52 | F20: 46281 | H20: =IF($A20="","",IF($G20<>"","ENCERRADO","ATIVO")) -> ATIVO
E21: =IF($C21="","",IF($G21<>"",0,$C21*$D21)) | H21: =IF($A21="","",IF($G21<>"","ENCERRADO","ATIVO"))
E22: =IF($C22="","",IF($G22<>"",0,$C22*$D22)) | H22: =IF($A22="","",IF($G22<>"","ENCERRADO","ATIVO"))
E23: =IF($C23="","",IF($G23<>"",0,$C23*$D23)) | H23: =IF($A23="","",IF($G23<>"","ENCERRADO","ATIVO"))
E24: =IF($C24="","",IF($G24<>"",0,$C24*$D24)) | H24: =IF($A24="","",IF($G24<>"","ENCERRADO","ATIVO"))
E25: =IF($C25="","",IF($G25<>"",0,$C25*$D25)) | H25: =IF($A25="","",IF($G25<>"","ENCERRADO","ATIVO"))
E26: =IF($C26="","",IF($G26<>"",0,$C26*$D26)) | H26: =IF($A26="","",IF($G26<>"","ENCERRADO","ATIVO"))
E27: =IF($C27="","",IF($G27<>"",0,$C27*$D27)) | H27: =IF($A27="","",IF($G27<>"","ENCERRADO","ATIVO"))
E28: =IF($C28="","",IF($G28<>"",0,$C28*$D28)) | H28: =IF($A28="","",IF($G28<>"","ENCERRADO","ATIVO"))
E29: =IF($C29="","",IF($G29<>"",0,$C29*$D29)) | H29: =IF($A29="","",IF($G29<>"","ENCERRADO","ATIVO"))
E30: =IF($C30="","",IF($G30<>"",0,$C30*$D30)) | H30: =IF($A30="","",IF($G30<>"","ENCERRADO","ATIVO"))
E31: =IF($C31="","",IF($G31<>"",0,$C31*$D31)) | H31: =IF($A31="","",IF($G31<>"","ENCERRADO","ATIVO"))
E32: =IF($C32="","",IF($G32<>"",0,$C32*$D32)) | H32: =IF($A32="","",IF($G32<>"","ENCERRADO","ATIVO"))
... E37: =IF($C37="","",IF($G37<>"",0,$C37*$D37)) | H37: =IF($A37="","",IF($G37<>"","ENCERRADO","ATIVO"))
D38: TOTAL MENSAL RÁDIO: | E38: =SUM($E$8:$E$37) -> 3853.04
A40: 2. HISTÓRICO DE EVENTOS (entrega / quebra / sumiço / reposição)
A41: Data | B41: Obra | C41: Locadora | D41: Evento | E41: Qtd | F41: Custo do Item (R$) | G41: Recuperado de | H41: Observação
A93: RESUMO DE PERDAS DE RÁDIO
A94: Total perdido/quebrado (R$): | C94: =SUMIFS($F$42:$F$91,$D$42:$D$91,"SUMIÇO")+SUMIFS($F$42:$F$91,$D$42:$D$91,"QUEBRA") -> 0
A95: Recuperado (empreiteiro+equipe): | C95: =SUMIFS($F$42:$F$91,$G$42:$G$91,"EMPREITEIRO")+SUMIFS($F$42:$F$91,$G$42:$G$91,"EQUIPE DA OBRA") -> 0
A96: Prejuízo EICES (não recuperado): | C96: =SUMIFS($F$42:$F$91,$G$42:$G$91,"NINGUÉM (PREJUÍZO EICES)") -> 0

Sheet Locado
B1: LOCADO — FERRAMENTAS ALUGADAS DE TERCEIROS
B3: Controle do custo mensal. Preencha a Data Devolução ao encerrar — o custo sai sozinho.
A6: Fornecedor (Locadora) | B6: Categoria | C6: Item | D6: Obra | E6: Qtd | F6: Custo Mensal Unit. (R$) | G6: Custo Mensal Total (R$) | H6: Cód. Locadora | I6: Data Início | J6: Data Devolução | K6: Status | L6: Observação
A7: ONIX | B7: ROMPEDOR | C7: Rompedor | D7: ALTIER | E7: 0 | F7: 160 | G7: =IF($E7="","",IF($J7<>"",0,$E7*$F7)) -> 0 | H7: F 22 | I7: 46246 | J7: 46283 | K7: =IF($A7="","",IF($J7<>"","ENCERRADO","ATIVO")) -> ENCERRADO | L7: carga inicial ago/2026
A8: ONIX | B8: ROMPEDOR | C8: Rompedor | D8: ALTIER | E8: 0 | F8: 160 | G8: =IF($E8="","",IF($J8<>"",0,$E8*$F8)) -> 0 | H8: EM 31 | I8: 46171 | J8: 46283 | K8: =IF($A8="","",IF($J8<>"","ENCERRADO","ATIVO")) -> ENCERRADO | L8: carga inicial ago/2026
A9: ONIX | B9: ESMERILHADEIRA | C9: Esmerilhadeira | D9: ALTIER | E9: 0 | F9: 160 | G9: =IF($E9="","",IF($J9<>"",0,$E9*$F9)) -> 0 | I9: 46171 | J9: 46266 | K9: =IF($A9="","",IF($J9<>"","ENCERRADO","ATIVO")) -> ENCERRADO | L9: carga inicial ago/2026
A10: ONIX | B10: ESMERILHADEIRA | C10: Esmerilhadeira | D10: ALTIER | E10: 1 | F10: 160 | G10: =IF($E10="","",IF($J10<>"",0,$E10*$F10)) -> 160 | H10: L 50 | I10: 46171 | K10: =IF($A10="","",IF($J10<>"","ENCERRADO","ATIVO")) -> ATIVO | L10: carga inicial ago/2026
A11: ONIX | B11: SERRA MÁRMORE | C11: Serra Marmore | D11: ALTIER | E11: 1 | F11: 160 | G11: =IF($E11="","",IF($J11<>"",0,$E11*$F11)) -> 160 | H11: SM 28 | I11: 46171 | K11: =IF($A11="","",IF($J11<>"","ENCERRADO","ATIVO")) -> ATIVO | L11: carga inicial ago/2026
A12: IMPACTO | B12: ANDAIME | C12: Andaime | D12: ALPHA ONE | E12: 1 | F12: 924.88 | G12: =IF($E12="","",IF($J12<>"",0,$E12*$F12)) -> 924.88 | I12: 46246 | K12: =IF($A12="","",IF($J12<>"","ENCERRADO","ATIVO")) -> ATIVO
A13: ONIX | B13: MARTELETE 10KG | C13: Martelete 10Kg | D13: ARENGA (TRISUL) | E13: 1 | F13: 480 | G13: =IF($E13="","",IF($J13<>"",0,$E13*$F13)) -> 480 | I13: 46111 | K13: =IF($A13="","",IF($J13<>"","ENCERRADO","ATIVO")) -> ATIVO | L13: carga inicial ago/2026
A14: INOVATRI | B14: MÁQUINA DE RANHURA | C14: Maquina De Ranhura | D14: MAURO | E14: 1 | F14: 1600 | G14: =IF($E14="","",IF($J14<>"",0,$E14*$F14)) -> 1600 | K14: =IF($A14="","",IF($J14<>"","ENCERRADO","ATIVO")) -> ATIVO | L14: carga inicial ago/2026
A15: INOVATRI | B15: MÁQUINA DE ROSCA | C15: Maquina De Rosca | D15: MAURO | E15: 1 | F15: 900 | G15: =IF($E15="","",IF($J15<>"",0,$E15*$F15)) -> 900 | K15: =IF($A15="","",IF($J15<>"","ENCERRADO","ATIVO")) -> ATIVO | L15: carga inicial ago/2026
A16: IMPACTO | B16: ANDAIME | C16: Andaime | D16: ALTIER | E16: 1 | F16: 680 | G16: =IF($E16="","",IF($J16<>"",0,$E16*$F16)) -> 680 | I16: 46143 | K16: =IF($A16="","",IF($J16<>"","ENCERRADO","ATIVO")) -> ATIVO | L16: carga inicial ago/2026
A17: IMPACTO | B17: ROMPEDOR | C17: Rompedor | D17: ALTIER | E17: 1 | F17: 210 | G17: =IF($E17="","",IF($J17<>"",0,$E17*$F17)) -> 210 | H17: EM 015 | I17: 46246 | K17: =IF($A17="","",IF($J17<>"","ENCERRADO","ATIVO")) -> ATIVO | L17: Acompanha 1x punho
A18: INOVATRI | B18: MÁQUINA DE RANHURA | C18: Maquina De Ranhura | D18: ANGELICA | E18: 1 | F18: 1600 | G18: =IF($E18="","",IF($J18<>"",0,$E18*$F18)) -> 1600 | I18: 46282 | K18: =IF($A18="","",IF($J18<>"","ENCERRADO","ATIVO")) -> ATIVO | L18: carga inicial ago/2026
A19: ONIX | B19: SERRA MÁRMORE | C19: Serra Marmore | D19: ORIÇANGA | E19: 0 | F19: 150 | G19: =IF($E19="","",IF($J19<>"",0,$E19*$F19)) -> 0 | I19: 46163 | J19: 46235 | K19: =IF($A19="","",IF($J19<>"","ENCERRADO","ATIVO")) -> ENCERRADO | L19: carga inicial ago/2026
A20: ONIX | B20: ROMPEDOR | C20: Rompedor | D20: ARENGA (TRISUL) | E20: 0 | F20: 450 | G20: =IF($E20="","",IF($J20<>"",0,$E20*$F20)) -> 0 | I20: 46112 | J20: 46266 | K20: =IF($A20="","",IF($J20<>"","ENCERRADO","ATIVO")) -> ENCERRADO | L20: carga inicial ago/2026
A21: INOVATRI | B21: MÁQUINA DE RANHURA | C21: Maquina De Ranhura | D21: PJM | E21: 1 | F21: 1600 | G21: =IF($E21="","",IF($J21<>"",0,$E21*$F21)) -> 1600 | I21: 46253 | K21: =IF($A21="","",IF($J21<>"","ENCERRADO","ATIVO")) -> ATIVO | L21: carga inicial ago/2026
A22: ONIX | B22: SERRA CIRCULAR MAKITA | C22: Serra Circular Makita | D22: PJM | E22: 1 | F22: 220 | G22: =IF($E22="","",IF($J22<>"",0,$E22*$F22)) -> 220 | I22: 46223 | K22: =IF($A22="","",IF($J22<>"","ENCERRADO","ATIVO")) -> ATIVO | L22: carga inicial ago/2026
A23: INOVATRI | B23: MÁQUINA DE RANHURA | C23: Maquina De Ranhura | D23: ENXOVIA | E23: 1 | F23: 1600 | G23: =IF($E23="","",IF($J23<>"",0,$E23*$F23)) -> 1600 | I23: 46245 | K23: =IF($A23="","",IF($J23<>"","ENCERRADO","ATIVO")) -> ATIVO | L23: carga inicial ago/2026
A24: ONIX | B24: MARTELETE 5KG | C24: Martelete 5Kg | D24: JOA | E24: 1 | F24: 350 | G24: =IF($E24="","",IF($J24<>"",0,$E24*$F24)) -> 350 | H24: MT-09 | K24: =IF($A24="","",IF($J24<>"","ENCERRADO","ATIVO")) -> ATIVO | L24: carga inicial ago/2026
A25: ONIX | B25: MARTELETE 10KG | C25: Martelete 10Kg | D25: BALTAZAR | E25: 0 | F25: 400 | G25: =IF($E25="","",IF($J25<>"",0,$E25*$F25)) -> 0 | I25: 46163 | J25: 46262 | K25: =IF($A25="","",IF($J25<>"","ENCERRADO","ATIVO")) -> ENCERRADO | L25: carga inicial ago/2026
A26: IMPACTO | B26: ROMPEDOR | C26: Rompedor | D26: ALTIER | E26: 1 | F26: 210 | G26: =IF($E26="","",IF($J26<>"",0,$E26*$F26)) -> 210 | H26: EM 031 | I26: 46246 | K26: =IF($A26="","",IF($J26<>"","ENCERRADO","ATIVO")) -> ATIVO | L26: Acompanha 1x punho
A27: IMPACTO | B27: ROMPEDOR | C27: Rompedor | D27: ALTIER | E27: 1 | F27: 150 | G27: =IF($E27="","",IF($J27<>"",0,$E27*$F27)) -> 150 | H27: EC 207 | I27: 46246 | K27: =IF($A27="","",IF($J27<>"","ENCERRADO","ATIVO")) -> ATIVO | L27: Acompanha 1x punho
A28: ONIX | B28: MARTELETE 5KG | C28: Martelete 5Kg | D28: SAMPA CONSOLAÇÃO | E28: 0 | F28: 380 | G28: =IF($E28="","",IF($J28<>"",0,$E28*$F28)) -> 0 | I28: 46235 | J28: 46239 | K28: =IF($A28="","",IF($J28<>"","ENCERRADO","ATIVO")) -> ENCERRADO | L28: carga inicial ago/2026
A29: ONIX | B29: MARTELETE 10KG | C29: Martelete 10Kg | D29: SAMPA CONSOLAÇÃO | E29: 0 | F29: 480 | G29: =IF($E29="","",IF($J29<>"",0,$E29*$F29)) -> 0 | I29: 46223 | J29: 46238 | K29: =IF($A29="","",IF($J29<>"","ENCERRADO","ATIVO")) -> ENCERRADO | L29: carga inicial ago/2026
A30: IMPACTO | B30: ROMPEDOR | C30: Rompedor | D30: ALTIER | E30: 1 | F30: 150 | G30: =IF($E30="","",IF($J30<>"",0,$E30*$F30)) -> 150 | H30: EC 231 | I30: 46246 | K30: =IF($A30="","",IF($J30<>"","ENCERRADO","ATIVO")) -> ATIVO | L30: Acompanha 1x punho
A31: IMPACTO | B31: PARAFUSADEIRA | C31: Parafusadeira | D31: ALTIER | E31: 1 | F31: 190 | G31: =IF($E31="","",IF($J31<>"",0,$E31*$F31)) -> 190 | H31: GQ 071 | I31: 46246 | K31: =IF($A31="","",IF($J31<>"","ENCERRADO","ATIVO")) -> ATIVO | L31: Acompanha bateria, carregador e maleta
A32: IMPACTO | B32: PARAFUSADEIRA | C32: Parafusadeira | D32: ALTIER | E32: 1 | F32: 190 | G32: =IF($E32="","",IF($J32<>"",0,$E32*$F32)) -> 190 | H32: GQ 076 | I32: 46246 | K32: =IF($A32="","",IF($J32<>"","ENCERRADO","ATIVO")) -> ATIVO | L32: Acompanha bateria, carregador e maleta
A33: ONIX | B33: MARTELETE 10KG | C33: Martelete 10Kg | D33: ORIÇANGA | E33: 1 | F33: 480 | G33: =IF($E33="","",IF($J33<>"",0,$E33*$F33)) -> 480 | I33: 46231 | K33: =IF($A33="","",IF($J33<>"","ENCERRADO","ATIVO")) -> ATIVO | L33: carga inicial ago/2026
A34: ONIX | B34: LASER (tripé) | C34: Laser (Tripé) | D34: ORIÇANGA | E34: 1 | F34: 200 | G34: =IF($E34="","",IF($J34<>"",0,$E34*$F34)) -> 200 | I34: 46163 | K34: =IF($A34="","",IF($J34<>"","ENCERRADO","ATIVO")) -> ATIVO | L34: carga inicial ago/2026
A35: IMPACTO | B35: ANDAIME | C35: Andaime | D35: ANGELICA | E35: 1 | F35: 235 | G35: =IF($E35="","",IF($J35<>"",0,$E35*$F35)) -> 235 | K35: =IF($A35="","",IF($J35<>"","ENCERRADO","ATIVO")) -> ATIVO | L35: carga inicial ago/2026
A36: IMPACTO | B36: ANDAIME | C36: Andaime | D36: ARENGA (TRISUL) | E36: 1 | F36: 370 | G36: =IF($E36="","",IF($J36<>"",0,$E36*$F36)) -> 370 | I36: 46246 | K36: =IF($A36="","",IF($J36<>"","ENCERRADO","ATIVO")) -> ATIVO
A37: IMPACTO | B37: ROMPEDOR | C37: Rompedor | D37: ARENGA (TRISUL) | E37: 0 | F37: 240 | G37: =IF($E37="","",IF($J37<>"",0,$E37*$F37)) -> 0 | H37: ?? | I37: 46279 | K37: =IF($A37="","",IF($J37<>"","ENCERRADO","ATIVO")) -> ATIVO
A38: IMPACTO | B38: ANDAIME | C38: Andaime | D38: ARTHUR PRADO | E38: 0 | F38: 450 | G38: =IF($E38="","",IF($J38<>"",0,$E38*$F38)) -> 0 | I38: 46244 | J38: 46289 | K38: =IF($A38="","",IF($J38<>"","ENCERRADO","ATIVO")) -> ENCERRADO
A39: IMPACTO | B39: ANDAIME | C39: Andaime | D39: ARTHUR PRADO | E39: 0 | F39: 530 | G39: =IF($E39="","",IF($J39<>"",0,$E39*$F39)) -> 0 | I39: 46274 | J39: 46281 | K39: ENCERRADO
A40: IMPACTO | B40: ANDAIME | C40: Andaime | D40: BALTAZAR | E40: 1 | F40: 570 | G40: =IF($E40="","",IF($J40<>"",0,$E40*$F40)) -> 570 | K40: =IF($A40="","",IF($J40<>"","ENCERRADO","ATIVO")) -> ATIVO | L40: carga inicial ago/2026
A41: IMPACTO | B41: PISTOLA FINCA PINO | C41: Pistola Finca Pino | D41: CUNHA GAGO | E41: 1 | F41: 400 | G41: =IF($E41="","",IF($J41<>"",0,$E41*$F41)) -> 400 | H41: CA 015 | I41: 46261 | K41: =IF($A41="","",IF($J41<>"","ENCERRADO","ATIVO")) -> ATIVO
A42: IMPACTO | B42: ROMPEDOR | C42: Rompedor | D42: CUNHA GAGO | E42: 1 | F42: 150 | G42: =IF($E42="","",IF($J42<>"",0,$E42*$F42)) -> 150 | H42: EC 253 | I42: 46261 | K42: =IF($A42="","",IF($J42<>"","ENCERRADO","ATIVO")) -> ATIVO
A43: IMPACTO | B43: FURADEIRA DE BANCADA | C43: Furadeira De Bancada | D43: ENXOVIA | E43: 1 | F43: 380 | G43: =IF($E43="","",IF($J43<>"",0,$E43*$F43)) -> 380 | H43: GE 001 | K43: =IF($A43="","",IF($J43<>"","ENCERRADO","ATIVO")) -> ATIVO | L43: carga inicial ago/2026
A44: IMPACTO | B44: ANDAIME | C44: Andaime | D44: ENXOVIA | E44: 1 | F44: 920 | G44: =IF($E44="","",IF($J44<>"",0,$E44*$F44)) -> 920 | I44: 46246 | K44: =IF($A44="","",IF($J44<>"","ENCERRADO","ATIVO")) -> ATIVO
A45: IMPACTO | B45: ROMPEDOR | C45: Rompedor | D45: ENXOVIA | E45: 1 | F45: 150 | G45: =IF($E45="","",IF($J45<>"",0,$E45*$F45)) -> 150 | H45: EC 217 | I45: 46246 | K45: =IF($A45="","",IF($J45<>"","ENCERRADO","ATIVO")) -> ATIVO | L45: Acompanha 1x punho
A46: IMPACTO | B46: PARAFUSADEIRA | C46: Parafusadeira | D46: ENXOVIA | E46: 1 | F46: 190 | G46: =IF($E46="","",IF($J46<>"",0,$E46*$F46)) -> 190 | H46: GQ 092 | I46: 46246 | K46: =IF($A46="","",IF($J46<>"","ENCERRADO","ATIVO")) -> ATIVO | L46: Acompanha bateria, carregador e maleta
A47: IMPACTO | B47: LASER | C47: Laser | D47: ENXOVIA | E47: 0 | F47: 1700 | G47: =IF($E47="","",IF($J47<>"",0,$E47*$F47)) -> 0 | H47: UH 002 | I47: 46246 | J47: 46248 | K47: =IF($A47="","",IF($J47<>"","ENCERRADO","ATIVO")) -> ENCERRADO | L47: Acompanha tripé, régua, base, óculos, receptor e controle RC1 Bosch
A48: IMPACTO | B48: ESMERILHADEIRA | C48: Esmerilhadeira | D48: ENXOVIA | E48: 1 | F48: 140 | G48: =IF($E48="","",IF($J48<>"",0,$E48*$F48)) -> 140 | H48: WE 014 | I48: 46246 | K48: =IF($A48="","",IF($J48<>"","ENCERRADO","ATIVO")) -> ATIVO | L48: Acompanha flange superior, flange inferior, chave pinus, punho e proteção
A49: IMPACTO | B49: ANDAIME | C49: Andaime | D49: ENXOVIA | E49: 1 | F49: 800 | G49: =IF($E49="","",IF($J49<>"",0,$E49*$F49)) -> 800 | I49: 46259 | K49: =IF($A49="","",IF($J49<>"","ENCERRADO","ATIVO")) -> ATIVO
A50: IMPACTO | B50: ESMERILHADEIRA | C50: Esmerilhadeira | D50: JERONIMO | E50: 1 | F50: 140 | G50: =IF($E50="","",IF($J50<>"",0,$E50*$F50)) -> 140 | H50: WE 151 | I50: 46269 | K50: =IF($A50="","",IF($J50<>"","ENCERRADO","ATIVO")) -> ATIVO
A51: IMPACTO | B51: MARTELETE 10KG | C51: Martelete 10Kg | D51: CUNHA GAGO | E51: 1 | F51: 450 | G51: =IF($E51="","",IF($J51<>"",0,$E51*$F51)) -> 450 | H51: EG 080 | I51: 46261 | K51: =IF($A51="","",IF($J51<>"","ENCERRADO","ATIVO")) -> ATIVO
A52: ONIX | B52: ESMERILHADEIRA | C52: Esmerilhadeira | D52: ORIÇANGA | E52: 1 | F52: 160 | G52: =IF($E52="","",IF($J52<>"",0,$E52*$F52)) -> 160 | I52: 46235 | K52: =IF($A52="","",IF($J52<>"","ENCERRADO","ATIVO")) -> ATIVO
A53: ONIX | B53: ROMPEDOR | C53: Rompedor | D53: ORIÇANGA | E53: 1 | F53: 160 | G53: =IF($E53="","",IF($J53<>"",0,$E53*$F53)) -> 160 | I53: 46235 | K53: =IF($A53="","",IF($J53<>"","ENCERRADO","ATIVO")) -> ATIVO
A54: IMPACTO | B54: MARTELETE 10KG | C54: Martelete 10Kg | D54: JERONIMO | E54: 1 | F54: 450 | G54: =IF($E54="","",IF($J54<>"",0,$E54*$F54)) -> 450 | H54: EG 108 | I54: 46275 | K54: =IF($A54="","",IF($J54<>"","ENCERRADO","ATIVO")) -> ATIVO | L54: ROMPEDOR DE 10KG
A55: IMPACTO | B55: MARTELETE 10KG | C55: Martelete 10Kg | D55: JERONIMO | E55: 1 | F55: 450 | G55: =IF($E55="","",IF($J55<>"",0,$E55*$F55)) -> 450 | H55: EG 090 | I55: 46275 | K55: =IF($A55="","",IF($J55<>"","ENCERRADO","ATIVO")) -> ATIVO | L55: ROMPEDOR DE 10KG
A56: IMPACTO | B56: MARTELETE 5KG | C56: Martelete 5Kg | D56: JERONIMO | E56: 1 | F56: 400 | G56: 380 | H56: XR 048 | I56: 46269 | K56: =IF($A56="","",IF($J56<>"","ENCERRADO","ATIVO")) -> ATIVO
A57: INOVATRI | B57: POLIGROOVET CUT 8 | C57: Máquina de corte de tubo 1" - 8" | D57: ENXOVIA | E57: 1 | F57: 900 | G57: =IF($E57="","",IF($J57<>"",0,$E57*$F57)) -> 900 | I57: 46258 | K57: =IF($A57="","",IF($J57<>"","ENCERRADO","ATIVO")) -> ATIVO
A58: IMPACTO | B58: PISTOLA FINCA PINO | C58: Pistola Finca Pino | D58: JERONIMO | E58: 1 | F58: 400 | G58: =IF($E58="","",IF($J58<>"",0,$E58*$F58)) -> 400 | H58: CA 039 | I58: 46261 | K58: =IF($A58="","",IF($J58<>"","ENCERRADO","ATIVO")) -> ATIVO
A59: IMPACTO | B59: PISTOLA FINCA PINO | C59: Pistola Finca Pino | D59: JERONIMO | E59: 1 | F59: 400 | G59: =IF($E59="","",IF($J59<>"",0,$E59*$F59)) -> 400 | H59: CB 029 | I59: 46269 | K59: =IF($A59="","",IF($J59<>"","ENCERRADO","ATIVO")) -> ATIVO
A60: IMPACTO | B60: PISTOLA FINCA PINO | C60: Pistola Finca Pino | D60: JERONIMO | E60: 1 | F60: 400 | G60: =IF($E60="","",IF($J60<>"",0,$E60*$F60)) -> 400 | H60: CB 025 | I60: 46269 | K60: =IF($A60="","",IF($J60<>"","ENCERRADO","ATIVO")) -> ATIVO
A61: IMPACTO | B61: ROMPEDOR | C61: Rompedor | D61: JERONIMO | E61: 1 | F61: 150 | G61: =IF($E61="","",IF($J61<>"",0,$E61*$F61)) -> 150 | H61: EM 009 | I61: 46261 | K61: =IF($A61="","",IF($J61<>"","ENCERRADO","ATIVO")) -> ATIVO
A62: IMPACTO | B62: SERRA MÁRMORE | C62: Serra Marmore | D62: JERONIMO | E62: 1 | F62: 170 | G62: =IF($E62="","",IF($J62<>"",0,$E62*$F62)) -> 170 | H62: PM 114 | I62: 46261 | K62: =IF($A62="","",IF($J62<>"","ENCERRADO","ATIVO")) -> ATIVO
A63: IMPACTO | B63: ROMPEDOR | C63: Rompedor | D63: JOA | E63: 1 | F63: 150 | G63: =IF($E63="","",IF($J63<>"",0,$E63*$F63)) -> 150 | H63: EC 242 | I63: 46246 | K63: =IF($A63="","",IF($J63<>"","ENCERRADO","ATIVO")) -> ATIVO | L63: Acompanha 1x punho
A64: IMPACTO | B64: SERRA MÁRMORE | C64: Serra Marmore | D64: JOA | E64: 1 | F64: 170 | G64: =IF($E64="","",IF($J64<>"",0,$E64*$F64)) -> 170 | H64: PI 010 | I64: 46246 | K64: =IF($A64="","",IF($J64<>"","ENCERRADO","ATIVO")) -> ATIVO | L64: Acompanha 2x chave fixa, punho, flange inferior e flange superior
A65: IMPACTO | B65: ANDAIME | C65: Andaime | D65: JOA | E65: 1 | F65: 430 | G65: =IF($E65="","",IF($J65<>"",0,$E65*$F65)) -> 430 | I65: 46244 | K65: =IF($A65="","",IF($J65<>"","ENCERRADO","ATIVO")) -> ATIVO
A66: IMPACTO | B66: ANDAIME | C66: Andaime | D66: MAURO | E66: 1 | F66: 490 | G66: =IF($E66="","",IF($J66<>"",0,$E66*$F66)) -> 490 | I66: 46143 | K66: =IF($A66="","",IF($J66<>"","ENCERRADO","ATIVO")) -> ATIVO | L66: carga inicial ago/2026
A67: IMPACTO | B67: ANDAIME | C67: Andaime | D67: ORIÇANGA | E67: 1 | F67: 630 | G67: =IF($E67="","",IF($J67<>"",0,$E67*$F67)) -> 630 | K67: =IF($A67="","",IF($J67<>"","ENCERRADO","ATIVO")) -> ATIVO | L67: carga inicial ago/2026
A68: IMPACTO | B68: PISTOLA FINCA PINO | C68: Pistola Finca Pino | D68: ORIÇANGA | E68: 1 | F68: 480 | G68: =IF($E68="","",IF($J68<>"",0,$E68*$F68)) -> 480 | H68: CA 034 | I68: 46246 | K68: =IF($A68="","",IF($J68<>"","ENCERRADO","ATIVO")) -> ATIVO
A69: IMPACTO | B69: SERRA POLICORTE | C69: Serra Policorte | D69: ORIÇANGA | E69: 1 | F69: 320 | G69: =IF($E69="","",IF($J69<>"",0,$E69*$F69)) -> 320 | H69: PM 114 | I69: 46268 | K69: =IF($A69="","",IF($J69<>"","ENCERRADO","ATIVO")) -> ATIVO | L69: DISCO DIAMANTADO 14" (VENDA) R$ 100,00
A70: IMPACTO | B70: PISTOLA FINCA PINO | C70: Pistola Finca Pino | D70: PJM | E70: 1 | F70: 480 | G70: =IF($E70="","",IF($J70<>"",0,$E70*$F70)) -> 480 | H70: CA 033 | I70: 46255 | K70: =IF($A70="","",IF($J70<>"","ENCERRADO","ATIVO")) -> ATIVO
A71: IMPACTO | B71: ANDAIME | C71: Andaime | D71: PJM | E71: 1 | F71: 800 | G71: =IF($E71="","",IF($J71<>"",0,$E71*$F71)) -> 800 | I71: 46267 | K71: =IF($A71="","",IF($J71<>"","ENCERRADO","ATIVO")) -> ATIVO
A72: IMPACTO | B72: ANDAIME | C72: Andaime | D72: SAMPA CONSOLAÇÃO | E72: 1 | F72: 200 | G72: =IF($E72="","",IF($J72<>"",0,$E72*$F72)) -> 200 | K72: =IF($A72="","",IF($J72<>"","ENCERRADO","ATIVO")) -> ATIVO | L72: carga inicial ago/2026
A73: IMPACTO | B73: PISTOLA FINCA PINO | C73: Pistola Finca Pino | D73: SAMPA CONSOLAÇÃO | E73: 1 | F73: 480 | G73: =IF($E73="","",IF($J73<>"",0,$E73*$F73)) -> 480 | H73: CA 035 | K73: =IF($A73="","",IF($J73<>"","ENCERRADO","ATIVO")) -> ATIVO | L73: carga inicial ago/2026
A74: IMPACTO | B74: PISTOLA FINCA PINO | C74: Pistola Finca Pino | D74: SAMPA CONSOLAÇÃO | E74: 0 | F74: 480 | G74: =IF($E74="","",IF($J74<>"",0,$E74*$F74)) -> 0 | J74: 46244 | K74: =IF($A74="","",IF($J74<>"","ENCERRADO","ATIVO")) -> ENCERRADO | L74: carga inicial ago/2026
A75: IMPACTO | B75: ANDAIME | C75: Andaime | D75: SAMPA CONSOLAÇÃO | E75: 1 | F75: 490 | G75: =IF($E75="","",IF($J75<>"",0,$E75*$F75)) -> 490 | I75: 46280 | K75: ATIVO
A76: IMPACTO | B76: ANDAIME | C76: Andaime | D76: JOA | E76: 1 | F76: 490 | G76: =IF($E76="","",IF($J76<>"",0,$E76*$F76)) -> 490 | I76: 46286 | K76: ATIVO
A77: IMPACTO | B77: ROMPEDOR | C77: Rompedor | D77: ALTIER | E77: 1 | F77: 150 | G77: =IF($E77="","",IF($J77<>"",0,$E77*$F77)) -> 150 | I77: 46286 | K77: ATIVO
A78: IMPACTO | B78: ROMPEDOR | C78: Rompedor | D78: ALTIER | E78: 1 | F78: 150 | G78: =IF($E78="","",IF($J78<>"",0,$E78*$F78)) -> 150 | I78: 46286 | K78: ATIVO
G82: =IF($E82="","",IF($J82<>"",0,$E82*$F82)) | K82: =IF($A82="","",IF($J82<>"","ENCERRADO","ATIVO"))
A85: RESUMO DE LOCAÇÃO (MENSAL)
A86: CUSTO TOTAL MENSAL DE LOCAÇÃO: | C86: =SUM($G$7:$G$82) -> 26879.88
A88: Por categoria:
A89: ANDAIME | C89: =SUMIF($B$7:$B$82,"ANDAIME",$G$7:$G$82) -> 8029.88
A90: MARTELETE 10KG | C90: =SUMIF($B$7:$B$82,"MARTELETE 10KG",$G$7:$G$82) -> 2310
A91: MARTELETE 5KG | C91: =SUMIF($B$7:$B$82,"MARTELETE 5KG",$G$7:$G$82) -> 730
A92: PARAFUSADEIRA | C92: =SUMIF($B$7:$B$82,"PARAFUSADEIRA",$G$7:$G$82) -> 570
A93: PERFURATRIZ | C93: =SUMIF($B$7:$B$82,"PERFURATRIZ",$G$7:$G$82) -> 0
A94: FURADEIRA | C94: =SUMIF($B$7:$B$82,"FURADEIRA",$G$7:$G$82) -> 0
A95: MÁQUINA DE RANHURA | C95: =SUMIF($B$7:$B$82,"MÁQUINA DE RANHURA",$G$7:$G$82) -> 6400
A96: SERRA MÁRMORE | C96: =SUMIF($B$7:$B$82,"SERRA MÁRMORE",$G$7:$G$82) -> 500
A97: OUTROS | C97: =SUM($G$7:$G$82)-(SUMIF($B$7:$B$82,"ANDAIME",$G$7:$G$82)+SUMIF($B$7:$B$82,"MARTELETE 10KG",$G$7:$G$82)+SUMIF($B$7:$B$82,"MARTELETE 5KG",$G$7:$G$82)+SUMIF($B$7:$B$82,"PARAFUSADEIRA",$G$7:$G$82)+SUMIF($B$7:$B$82,"PERFURATRIZ",$G$7:$G$82)+SUMIF($B$7:$B$82,"FURADEIRA",$G$7:$G$82)+SUMIF($B$7:$B$82,"MÁQUINA DE RANHURA",$G$7:$G$82)+SUMIF($B$7:$B$82,"SERRA MÁRMORE",$G$7:$G$82)) -> 8340

Sheet Painel
B1: PAINEL — VISÃO GERAL
B3: Números calculados automaticamente a partir das outras abas.
B6: FROTA PRÓPRIA | E6: CUSTO DE LOCAÇÃO
B7: Valor da frota — com Nota Fiscal (R$) | C7: =SUMIF('Patrimônio'!$H$7:$H$1003,"N",'Patrimônio'!$G$7:$G$1003) -> 115293.92 | E7: Locação ferramentas / mês (R$) | F7: =SUM(Locado!$G$7:$G$82) -> 26879.88
B8: Valor da frota — ESTIMADO (R$) | C8: =SUMIF('Patrimônio'!$H$7:$H$1003,"S",'Patrimônio'!$G$7:$G$1003) -> 74961.73 | E8: Locação rádio / mês (R$) | F8: =SUM('Rádio'!$E$8:$E$37) -> 3853.04
B9: VALOR TOTAL DA FROTA (R$) | C9: =SUM('Patrimônio'!$G$7:$G$1003) -> 190255.65 | E9: CUSTO TOTAL DE LOCAÇÃO / MÊS (R$) | F9: =SUM(Locado!$G$7:$G$82)+SUM('Rádio'!$E$8:$E$37) -> 30732.92
B10: Qtd. de ferramentas próprias | C10: =COUNTA('Patrimônio'!$A$7:$A$1003) -> 161
E11: MANUTENÇÃO
B12: SITUAÇÃO DA FROTA | E12: Itens em conserto agora | F12: =COUNTIF('Manutenção'!$H$7:$H$1006,"EM CONSERTO") -> 2
B13: Em obra | C13: =COUNTIF('Patrimônio'!$L$7:$L$1003,"EM OBRA") -> 90 | E13: Custo total de manutenção (R$) | F13: =SUM('Manutenção'!$F$7:$F$1006) -> 0
B14: Em manutenção | C14: =COUNTIF('Patrimônio'!$L$7:$L$1003,"MANUTENÇÃO") -> 2
B15: Pendente — procurar | C15: =COUNTIF('Patrimônio'!$L$7:$L$1003,"PENDENTE-PROCURAR") -> 30 | E15: ALERTAS DE COMPRA / PERDA
B16: Furtado | C16: =COUNTIF('Patrimônio'!$L$7:$L$1003,"FURTADO") -> 4 | E16: Ferramentas a procurar (poss. perda) | F16: =COUNTIF('Patrimônio'!$L$7:$L$1003,"PENDENTE-PROCURAR") -> 30
B17: Baixado | C17: =COUNTIF('Patrimônio'!$L$7:$L$1003,"BAIXADO") -> 35 | E17: Ferramentas furtadas | F17: =COUNTIF('Patrimônio'!$L$7:$L$1003,"FURTADO") -> 4
E18: Prejuízo em rádio não recuperado (R$) | F18: =SUMIFS('Rádio'!$F$42:$F$91,'Rádio'!$G$42:$G$91,"NINGUÉM (PREJUÍZO EICES)") -> 0
B20: Todos os números deste painel se atualizam sozinhos conforme as abas são preenchidas.

Sheet Listas
A1: CATEGORIAS | B1: PREFIXO | D1: TIPOS_MOV | E1: STATUS_MANUT | F1: EVENTOS_RADIO | G1: RECUPERADO_DE | H1: S_N | I1: CATEGORIA_LOCAÇÃO | J1: LOCAÇÃO EICES (R$/mês)
A2: PARAFUSADEIRA | B2: PAR | D2: TRANSFERÊNCIA | E2: EM CONSERTO | F2: ENTREGA | G2: EMPREITEIRO | H2: N | I2: PARAFUSADEIRA | J2: 200
A3: FURADEIRA | B3: FUR | D3: ENVIO P/ MANUTENÇÃO | E3: VOLTOU | F3: QUEBRA | G3: EQUIPE DA OBRA | H3: S | I3: FURADEIRA
A4: ROMPEDOR | B4: ROM | D4: RETORNO MANUTENÇÃO | E4: BAIXA | F4: SUMIÇO | G4: NINGUÉM (PREJUÍZO EICES) | I4: ROMPEDOR | J4: 200
A5: ESMERILHADEIRA | B5: ESM | D5: QUEBRA | F5: REPOSIÇÃO | I5: ESMERILHADEIRA | J5: 200
A6: SERRA MÁRMORE | B6: SMA | D6: FURTO | F6: DEVOLUÇÃO | I6: SERRA MÁRMORE | J6: 300
A7: SERRA DE ESQUADRIA | B7: SES | D7: DEVOLUÇÃO | I7: SERRA DE ESQUADRIA
A8: MARTELETE 5KG | B8: MT5 | D8: BAIXA | I8: MARTELETE 5KG | J8: 350
A9: MARTELETE 10KG | B9: M10 | D9: ENTRADA (NOVA) | I9: MARTELETE 10KG | J9: 400
A10: LASER | B10: LAS | I10: LASER | J10: 200
A11: TRIPÉ LASER | B11: TLA | I11: TRIPÉ LASER | J11: 40
A12: PERFURATRIZ | B12: PEZ | I12: PERFURATRIZ | J12: 300
A13: PERFURATRIZ EXTRATORA | B13: PEX | I13: PERFURATRIZ EXTRATORA | J13: 300
A14: MORSA | B14: MOR | I14: MORSA | J14: 50
A15: TERMOFUSOR | B15: TER | I15: TERMOFUSOR | J15: 200
A16: SOPRADOR | B16: SOP | I16: SOPRADOR | J16: 100
A17: VAZADOR | B17: VAZ | I17: VAZADOR | J17: 300
A18: PISTOLA FINCA PINO | B18: PFP | I18: PISTOLA FINCA PINO | J18: 300
A19: MÁQUINA TESTE ÁGUA | B19: MTA | I19: MÁQUINA TESTE ÁGUA | J19: 300
A20: MÁQUINA TESTE ELÉTRICA | B20: MTE | I20: MÁQUINA TESTE ELÉTRICA
A21: COMPRESSOR | B21: COM | I21: COMPRESSOR | J21: 300
A22: PRENSA PEX | B22: PPE | I22: PRENSA PEX | J22: 200
A23: PRENSA TERMINAL | B23: PTE | I23: PRENSA TERMINAL | J23: 200
A24: PRENSA GÁS | B24: PGA | I24: PRENSA GÁS | J24: 100
A25: MÁQUINA DE TINTA | B25: MTI | I25: MÁQUINA DE TINTA
A26: MANÔMETRO | B26: MAN | I26: MANÔMETRO | J26: 50
A27: TESOURA CORTA FERRO | B27: TCF | I27: TESOURA CORTA FERRO | J27: 50
I28: ALARGADOR PEX | J28: 50
I29: GRIFO | J29: 50
I30: JOGO DE CHAVE CATRACA | J30: 100
I31: MÁQUINA DE SOLDA
I32: PULVERIZADORA | J32: 200
I33: MÁQUINA TESTE ÁGUA QUENTE | J33: 600
I34: Valores mensais informados pelo usuário (VALORES.xlsx).
I35: Células amarelas = categoria sem valor definido. Preencher aqui.
